Workbook

Sheet Avg
A1: Avg. Semantic Percision | B1: BPMNChatbot++ | C1: XML Baseline | F1: Avg. Semantic Recall | G1: BPMNChatbot++ | H1: XML Baseline | K1: Avg. Semantic F1 | L1: BPMNChatbot++ | M1: XML Baseline
A2: 1 | B2: =AVERAGE('c1'!C1:E1) -> 92.307692 | C2: =AVERAGE('c1'!F1:H1) -> 91.666667 | F2: 1 | G2: =AVERAGE('c1'!C2:E2) -> 100 | H2: =AVERAGE('c1'!F2:H2) -> 100 | K2: 1 | L2: =2 * (B2 * G2) / (B2 + G2) -> 96 | M2: =2 * (C2 * H2) / (C2 + H2) -> 95.652174
A3: 2 | B3: =AVERAGE('c2'!C1:E1) -> 94.444444 | C3: =AVERAGE('c2'!F1:H1) -> 85.858586 | F3: 2 | G3: =AVERAGE('c2'!C2:E2) -> 100 | H3: =AVERAGE('c2'!F2:H2) -> 100 | K3: 2 | L3: =2 * (B3 * G3) / (B3 + G3) -> 97.142857 | M3: =2 * (C3 * H3) / (C3 + H3) -> 92.391304
A4: 3 | B4: =AVERAGE('c3'!C1:E1) -> 79.545455 | C4: =AVERAGE('c3'!F1:H1) -> 84.545455 | F4: 3 | G4: =AVERAGE('c3'!C2:E2) -> 100 | H4: =AVERAGE('c3'!F2:H2) -> 100 | K4: 3 | L4: =2 * (B4 * G4) / (B4 + G4) -> 88.607595 | M4: =2 * (C4 * H4) / (C4 + H4) -> 91.625616
A5: 4 | B5: =AVERAGE('c4'!C1:E1) -> 97.222222 | C5: =AVERAGE('c4'!F1:H1) -> 85.990338 | F5: 4 | G5: =AVERAGE('c4'!C2:E2) -> 100 | H5: =AVERAGE('c4'!F2:H2) -> 100 | K5: 4 | L5: =2 * (B5 * G5) / (B5 + G5) -> 98.591549 | M5: =2 * (C5 * H5) / (C5 + H5) -> 92.467532
A6: 5 | B6: =AVERAGE('c5'!C1:E1) -> 100 | C6: =AVERAGE('c5'!F1:H1) -> 95.238095 | F6: 5 | G6: =AVERAGE('c5'!C2:E2) -> 100 | H6: =AVERAGE('c5'!F2:H2) -> 100 | K6: 5 | L6: =2 * (B6 * G6) / (B6 + G6) -> 100 | M6: =2 * (C6 * H6) / (C6 + H6) -> 97.560976
A7: 6 | B7: =AVERAGE('c6'!C1:E1) -> 97.435897 | C7: =AVERAGE('c6'!F1:H1) -> 83.915344 | F7: 6 | G7: =AVERAGE('c6'!C2:E2) -> 85.714286 | H7: =AVERAGE('c6'!F2:H2) -> 92.857143 | K7: 6 | L7: =2 * (B7 * G7) / (B7 + G7) -> 91.2 | M7: =2 * (C7 * H7) / (C7 + H7) -> 88.160089
A8: 7 | B8: =AVERAGE('c7'!C1:E1) -> 98.765432 | C8: =AVERAGE('c7'!F1:H1) -> 98.550725 | F8: 7 | G8: =AVERAGE('c7'!C2:E2) -> 95.238095 | H8: =AVERAGE('c7'!F2:H2) -> 73.809524 | K8: 7 | L8: =2 * (B8 * G8) / (B8 + G8) -> 96.969697 | M8: =2 * (C8 * H8) / (C8 + H8) -> 84.404404
A9: 8 | B9: =AVERAGE('c8'!C1:E1) -> 95.034483 | C9: =AVERAGE('c8'!F1:H1) -> 89.170041 | F9: 8 | G9: =AVERAGE('c8'!C2:E2) -> 87.777778 | H9: =AVERAGE('c8'!F2:H2) -> 97.777778 | K9: 8 | L9: =2 * (B9 * G9) / (B9 + G9) -> 91.262103 | M9: =2 * (C9 * H9) / (C9 + H9) -> 93.275744
A10: 9 | B10: =AVERAGE('c9'!C1:E1) -> 100 | C10: =AVERAGE('c9'!F1:H1) -> 91.911765 | F10: 9 | G10: =AVERAGE('c9'!C2:E2) -> 100 | H10: =AVERAGE('c9'!F2:H2) -> 95.833333 | K10: 9 | L10: =2 * (B10 * G10) / (B10 + G10) -> 100 | M10: =2 * (C10 * H10) / (C10 + H10) -> 93.831593
A11: 10 | B11: =AVERAGE('c10'!C1:E1) -> 84.366472 | C11: =AVERAGE('c10'!F1:H1) -> 83.856209 | F11: 10 | G11: =AVERAGE('c10'!C2:E2) -> 100 | H11: =AVERAGE('c10'!F2:H2) -> 95.833333 | K11: 10 | L11: =2 * (B11 * G11) / (B11 + G11) -> 91.520406 | M11: =2 * (C11 * H11) / (C11 + H11) -> 89.445606
A12: 11 | B12: =AVERAGE('c11'!C1:E1) -> 100 | C12: =AVERAGE('c11'!F1:H1) -> 93.174603 | F12: 11 | G12: =AVERAGE('c11'!C2:E2) -> 93.75 | H12: =AVERAGE('c11'!F2:H2) -> 81.25 | K12: 11 | L12: =2 * (B12 * G12) / (B12 + G12) -> 96.774194 | M12: =2 * (C12 * H12) / (C12 + H12) -> 86.804687
A13: 12 | B13: =AVERAGE('c12'!C1:E1) -> 97.777778 | C13: =AVERAGE('c12'!F1:H1) -> 98.148148 | F13: 12 | G13: =AVERAGE('c12'!C2:E2) -> 94.252874 | H13: =AVERAGE('c12'!F2:H2) -> 62.068966 | K13: 12 | L13: =2 * (B13 * G13) / (B13 + G13) -> 95.982974 | M13: =2 * (C13 * H13) / (C13 + H13) -> 76.046234
A14: 13 | B14: =AVERAGE('c13'!C1:E1) -> 95.238095 | C14: =AVERAGE('c13'!F1:H1) -> 89.102564 | F14: 13 | G14: =AVERAGE('c13'!C2:E2) -> 70.588235 | H14: =AVERAGE('c13'!F2:H2) -> 70.588235 | K14: 13 | L14: =2 * (B14 * G14) / (B14 + G14) -> 81.081081 | M14: =2 * (C14 * H14) / (C14 + H14) -> 78.772137
A15: 14 | B15: =AVERAGE('c14'!C1:E1) -> 81.880952 | C15: =AVERAGE('c14'!F1:H1) -> 93.205128 | F15: 14 | G15: =AVERAGE('c14'!C2:E2) -> 100 | H15: =AVERAGE('c14'!F2:H2) -> 70.175439 | K15: 14 | L15: =2 * (B15 * G15) / (B15 + G15) -> 90.037963 | M15: =2 * (C15 * H15) / (C15 + H15) -> 80.067182
A16: 15 | B16: =AVERAGE('c15'!C1:E1) -> 100 | C16: =AVERAGE('c15'!F1:H1) -> 100 | F16: 15 | G16: =AVERAGE('c15'!C2:E2) -> 95.391533 | H16: =AVERAGE('c15'!F2:H2) -> 92.517628 | K16: 15 | L16: =2 * (B16 * G16) / (B16 + G16) -> 97.641419 | M16: =2 * (C16 * H16) / (C16 + H16) -> 96.113409
A17: 16 | B17: =AVERAGE('c16'!C1:E1) -> 97.346405 | C17: =AVERAGE('c16'!F1:H1) -> 99.29078 | F17: 16 | G17: =AVERAGE('c16'!C2:E2) -> 91.311437 | H17: =AVERAGE('c16'!F2:H2) -> 83.857442 | K17: 16 | L17: =2 * (B17 * G17) / (B17 + G17) -> 94.232395 | M17: =2 * (C17 * H17) / (C17 + H17) -> 90.923851
A19: Avg. Semantic Percision | B19: BPMNChatbot++ | C19: XML Baseline | F19: Avg. Semantic Recall | G19: BPMNChatbot++ | H19: XML Baseline | K19: Avg. Semantic F1 | L19: BPMNChatbot++ | M19: XML Baseline
A20: cluster 1 | B20: =AVERAGE(B2:B5) -> 90.879953 | C20: =AVERAGE(C2:C5) -> 87.015261 | F20: cluster 1 | G20: =AVERAGE(G2:G5) -> 100 | H20: =AVERAGE(H2:H5) -> 100 | K20: cluster 1 | L20: =2 * (B20 * G20) / (B20 + G20) -> 95.222103 | M20: =2 * (C20 * H20) / (C20 + H20) -> 93.056856
A21: cluster 2 | B21: =AVERAGE(B6:B9) -> 97.808953 | C21: =AVERAGE(C6:C9) -> 91.718551 | F21: cluster 2 | G21: =AVERAGE(G6:G9) -> 92.18254 | H21: =AVERAGE(H6:H9) -> 91.111111 | K21: cluster 2 | L21: =2 * (B21 * G21) / (B21 + G21) -> 94.912436 | M21: =2 * (C21 * H21) / (C21 + H21) -> 91.413822
A22: cluster 3 | B22: =AVERAGE(B10:B13) -> 95.536062 | C22: =AVERAGE(C10:C13) -> 91.772681 | F22: cluster 3 | G22: =AVERAGE(G10:G13) -> 97.000718 | H22: =AVERAGE(H10:H13) -> 83.746408 | K22: cluster 3 | L22: =2 * (B22 * G22) / (B22 + G22) -> 96.262819 | M22: =2 * (C22 * H22) / (C22 + H22) -> 87.576029
A23: cluster 4 | B23: =AVERAGE(B14:B17) -> 93.616363 | C23: =AVERAGE(C14:C17) -> 95.399618 | F23: cluster 4 | G23: =AVERAGE(G14:G17) -> 89.322801 | H23: =AVERAGE(H14:H17) -> 79.284686 | K23: cluster 4 | L23: =2 * (B23 * G23) / (B23 + G23) -> 91.419198 | M23: =2 * (C23 * H23) / (C23 + H23) -> 86.598837

Sheet Jaccard
E1: Avg Strict Jaccard Measure Chatbot runs | F1: Avg Strict Jaccard Measure XML runs | G1: Avg Strict Jaccard Measure Chatbot vs XML runs | H1: Avg Loose Jaccard Measure Chatbot runs | I1: Avg Loose Jaccard Measure XML runs | J1: Avg Loose Jaccard Measure Chatbot vs XML runs
D2: 1 | E2: =AVERAGE('c1'!K3, 'c1'!K4, 'c1'!L4) -> 0.78333333
D3: 2 | E3: =AVERAGE('c2'!K3, 'c2'!K4, 'c2'!L4) -> 0.86666667
D4: 3 | E4: =AVERAGE('c3'!K3, 'c3'!K4, 'c3'!L4) -> 0.91111111
A5: Avg Strict Jaccard Measure Chatbot runs | B5: =AVERAGE('c1:c16'!K3, 'c1:c16'!K4, 'c1:c16'!L4) -> 0.79502676 | D5: 4 | E5: =AVERAGE('c4'!K3, 'c4'!K4, 'c4'!L4) -> 0.71408046
A6: Avg Strict Jaccard Measure XML runs | B6: =AVERAGE('c1:c16'!N6, 'c1:c16'!N7, 'c1:c16'!O7) -> 0.64488943 | D6: 5 | E6: =AVERAGE('c5'!K3, 'c5'!K4, 'c5'!L4) -> 0.95555556
A7: Avg Strict Jaccard Measure Chatbot vs XML runs | B7: =AVERAGE('c1:c16'!K5:M7) -> 0.59604945 | D7: 6 | E7: =AVERAGE('c6'!K3, 'c6'!K4, 'c6'!L4) -> 0.86811966
D8: 7 | E8: =AVERAGE('c7'!K3, 'c7'!K4, 'c7'!L4) -> 0.64558306
A9: Avg Loose Jaccard Measure Chatbot runs | B9: =AVERAGE('c1:c16'!R3, 'c1:c16'!R4, 'c1:c16'!S4) -> 0.8161682 | D9: 8 | E9: =AVERAGE('c8'!K3, 'c8'!K4, 'c8'!L4) -> 0.63445596
A10: Avg Loose Jaccard Measure XML runs | B10: =AVERAGE('c1:c16'!U6, 'c1:c16'!U7, 'c1:c16'!V7) -> 0.70244017 | D10: 9 | E10: =AVERAGE('c9'!K3, 'c9'!K4, 'c9'!L4) -> 0.79541446
A11: Avg Loose Jaccard Measure Chatbot vs XML runs | B11: =AVERAGE('c1:c16'!R5:T7) -> 0.64139767 | D11: 10 | E11: =AVERAGE('c10'!K3, 'c10'!K4, 'c10'!L4) -> 0.87042316
D12: 11 | E12: =AVERAGE('c11'!K3, 'c11'!K4, 'c11'!L4) -> 0.96825397
D13: 12 | E13: =AVERAGE('c12'!K3, 'c12'!K4, 'c12'!L4) -> 0.76640299
D14: 13 | E14: =AVERAGE('c13'!K3, 'c13'!K4, 'c13'!L4) -> 0.52739215
D15: 14 | E15: =AVERAGE('c14'!K3, 'c14'!K4, 'c14'!L4) -> 0.78935574
D16: 15 | E16: =AVERAGE('c15'!K3, 'c15'!K4, 'c15'!L4) -> 0.84940572
D17: 16 | E17: =AVERAGE('c16'!K3, 'c16'!K4, 'c16'!L4) -> 0.77487419
D20: cluster 1 | E20: =AVERAGE('c1:c4'!K3, 'c1:c4'!K4, 'c1:c4'!L4) -> 0.81879789
D21: cluster 2 | E21: =AVERAGE('c5:c8'!K3,'c5:c8'!K4,'c5:c8'!L4) -> 0.77592856
D22: cluster 3 | E22: =AVERAGE('c9:c12'!K3, 'c9:c12'!K4, 'c9:c12'!L4) -> 0.85012364
D23: cluster 4 | E23: =AVERAGE('c13:c16'!K3, 'c13:c16'!K4, 'c13:c16'!L4) -> 0.73525695

Sheet Total (c1-c16)
B1: Chatbot | C1: XML
A2: Avg. Semantic Percision | B2: =AVERAGE('c1:c16'!C1:E1) -> 94.460333 | C2: =AVERAGE('c1:c16'!F1:H1) -> 91.476528
A3: Avg. Semantic Recall | B3: =AVERAGE('c1:c16'!C2:E2) -> 94.626515 | C3: =AVERAGE('c1:c16'!F2:H2) -> 88.535551
A5: Avg Strict Jaccard Measure Chatbot runs | B5: =AVERAGE('c1:c16'!K3, 'c1:c16'!K4, 'c1:c16'!L4) -> 0.79502676
A6: Avg Strict Jaccard Measure XML runs | B6: =AVERAGE('c1:c16'!N6, 'c1:c16'!N7, 'c1:c16'!O7) -> 0.64488943
A7: Avg Strict Jaccard Measure Chatbot vs XML runs | B7: =AVERAGE('c1:c16'!K5:M7) -> 0.59604945
A9: Avg Loose Jaccard Measure Chatbot runs | B9: =AVERAGE('c1:c16'!R3, 'c1:c16'!R4, 'c1:c16'!S4) -> 0.8161682
A10: Avg Loose Jaccard Measure XML runs | B10: =AVERAGE('c1:c16'!U6, 'c1:c16'!U7, 'c1:c16'!V7) -> 0.70244017
A11: Avg Loose Jaccard Measure Chatbot vs XML runs | B11: =AVERAGE('c1:c16'!R5:T7) -> 0.64139767

Sheet Total (c1-c12)
B1: Chatbot | C1: XML
A2: Avg. Semantic Percision | B2: =AVERAGE('c1:c12'!C1:E1) -> 94.741656 | C2: =AVERAGE('c1:c12'!F1:H1) -> 90.168831
A3: Avg. Semantic Recall | B3: =AVERAGE('c1:c12'!C2:E2) -> 96.394419 | C3: =AVERAGE('c1:c12'!F2:H2) -> 91.619173
A5: Avg Strict Jaccard Measure Chatbot runs | B5: =AVERAGE('c1:c12'!K3, 'c1:c12'!K4, 'c1:c12'!L4) -> 0.81495003
A6: Avg Strict Jaccard Measure XML runs | B6: =AVERAGE('c1:c12'!N6, 'c1:c12'!N7, 'c1:c12'!O7) -> 0.65316831
A7: Avg Strict Jaccard Measure Chatbot vs XML runs | B7: =AVERAGE('c1:c12'!K5:M7) -> 0.61825199
A9: Avg Loose Jaccard Measure Chatbot runs | B9: =AVERAGE('c1:c12'!R3, 'c1:c12'!R4, 'c1:c12'!S4) -> 0.84002699
A10: Avg Loose Jaccard Measure XML runs | B10: =AVERAGE('c1:c12'!U6, 'c1:c12'!U7, 'c1:c12'!V7) -> 0.70950305
A11: Avg Loose Jaccard Measure Chatbot vs XML runs | B11: =AVERAGE('c1:c12'!R5:T7) -> 0.65927859

Sheet Total (c13-c16)
B1: Chatbot | C1: XML
A2: Avg. Semantic Percision | B2: =AVERAGE('c13:c16'!C1:E1) -> 93.616363 | C2: =AVERAGE('c13:c16'!F1:H1) -> 95.399618
A3: Avg. Semantic Recall | B3: =AVERAGE('c13:c16'!C2:E2) -> 89.322801 | C3: =AVERAGE('c13:c16'!F2:H2) -> 79.284686
A5: Avg Strict Jaccard Measure Chatbot runs | B5: =AVERAGE('c13:c16'!K3, 'c13:c16'!K4, 'c13:c16'!L4) -> 0.73525695
A6: Avg Strict Jaccard Measure XML runs | B6: =AVERAGE('c13:c16'!N6, 'c13:c16'!N7, 'c13:c16'!O7) -> 0.62005278
A7: Avg Strict Jaccard Measure Chatbot vs XML runs | B7: =AVERAGE('c13:c16'!K5:M7) -> 0.52944182
A9: Avg Loose Jaccard Measure Chatbot runs | B9: =AVERAGE('c13:c16'!R3, 'c13:c16'!R4, 'c13:c16'!S4) -> 0.74459183
A10: Avg Loose Jaccard Measure XML runs | B10: =AVERAGE('c13:c16'!U6, 'c13:c16'!U7, 'c13:c16'!V7) -> 0.68125151
A11: Avg Loose Jaccard Measure Chatbot vs XML runs | B11: =AVERAGE('c13:c16'!R5:T7) -> 0.58775494

Sheet c1
A1: Semantic Percision | C1: =SUM(C3:C4) / (C3+ C4+ C7) * 100 -> 92.307692 | D1: =SUM(D3:D4) / (D3+ D4+ D7) * 100 -> 92.307692 | E1: =SUM(E3:E4) / (E3+ E4+ E7) * 100 -> 92.307692 | F1: =SUM(F3:F4) / (F3+ F4+ F7) * 100 -> 100 | G1: =SUM(G3:G4) / (G3+ G4+ G7) * 100 -> 75 | H1: =SUM(H3:H4) / (H3+ H4+ H7) * 100 -> 100 | J1: Jaccard Strict | K1: Chatbot run 1 | L1: Chatbot run 2 | M1: Chatbot run 3 | N1: XML run 1 | O1: XML run 2 | P1: XML run 3 | Q1: Jaccard Loose | R1: Chatbot run 1 | S1: Chatbot run 2 | T1: Chatbot run 3 | U1: XML run 1 | V1: XML run 2 | W1: XML run 3
A2: Semantic Recall | C2: =SUM(C3:C4) / SUM(C3:C5) *100 -> 100 | D2: =SUM(D3:D4) / SUM(D3:D5) *100 -> 100 | E2: =SUM(E3:E4) / SUM(E3:E5) *100 -> 100 | F2: =SUM(F3:F4) / SUM(F3:F5) *100 -> 100 | G2: =SUM(G3:G4) / SUM(G3:G5) *100 -> 100 | H2: =SUM(H3:H4) / SUM(H3:H5) *100 -> 100 | J2: Chatbot run 1 | Q2: Chatbot run 1
A3: Semantic TP Explicit | C3: =COUNTIF(C10:C21, 2) -> 11 | D3: =COUNTIF(D10:D21, 2) -> 11 | E3: =COUNTIF(E10:E21, 2) -> 11 | F3: =COUNTIF(F10:F21, 2) -> 12 | G3: =COUNTIF(G10:G21, 2) -> 11 | H3: =COUNTIF(H10:H21, 2) -> 12 | J3: Chatbot run 2 | K3: {=IFERROR(SUMPRODUCT((C10:C100<>"")*(D10:D100<>"")*(C10:C100=D10:D100))/SUMPRODUCT(--((C10:C100<>"")+(D10:D100<>"")>0)),"")} -> 0.85 | Q3: Chatbot run 2 | R3: {=IFERROR( SUMPRODUCT((C10:C100<>"")*(D10:D100<>"")* ((C10:C100=D10:D100)+((C10:C100=1)*(D10:D100=2))+((C10:C100=2)*(D10:D100=1)))) / SUMPRODUCT(--((C10:C100<>"")+(D10:D100<>"")>0)), "")} -> 0.85
A4: Semantic TP Implicit | C4: =COUNTIF(C10:C21, 1) -> 1 | D4: =COUNTIF(D10:D21, 1) -> 1 | E4: =COUNTIF(E10:E21, 1) -> 1 | F4: =COUNTIF(F10:F21, 1) -> 0 | G4: =COUNTIF(G10:G21, 1) -> 1 | H4: =COUNTIF(H10:H21, 1) -> 0 | J4: Chatbot run 3 | K4: {=IFERROR(SUMPRODUCT((C10:C100<>"")*(E10:E100<>"")*(C10:C100=E10:E100))/SUMPRODUCT(--((C10:C100<>"")+(E10:E100<>"")>0)),"")} -> 0.68181818 | L4: {=IFERROR(SUMPRODUCT((E10:E100<>"")*(D10:D100<>"")*(E10:E100=D10:D100))/SUMPRODUCT(--((E10:E100<>"")+(D10:D100<>"")>0)),"")} -> 0.81818182 | Q4: Chatbot run 3 | R4: {=IFERROR( SUMPRODUCT((C10:C100<>"")*(E10:E100<>"")* ((C10:C100=E10:E100)+((C10:C100=1)*(E10:E100=2))+((C10:C100=2)*(E10:E100=1)))) / SUMPRODUCT(--((C10:C100<>"")+(E10:E100<>"")>0)), "")} -> 0.77272727 | S4: {=IFERROR( SUMPRODUCT((E10:E100<>"")*(D10:D100<>"")* ((E10:E100=D10:D100)+((E10:E100=1)*(D10:D100=2))+((E10:E100=2)*(D10:D100=1)))) / SUMPRODUCT(--((E10:E100<>"")+(D10:D100<>"")>0)), "")} -> 0.90909091
A5: Semantic FN | C5: =COUNTIF(C10:C21, 0) -> 0 | D5: =COUNTIF(D10:D21, 0) -> 0 | E5: =COUNTIF(E10:E21, 0) -> 0 | F5: =COUNTIF(F10:F21, 0) -> 0 | G5: =COUNTIF(G10:G21, 0) -> 0 | H5: =COUNTIF(H10:H21, 0) -> 0 | J5: XML run 1 | K5: {=IFERROR(SUMPRODUCT((C10:C100<>"")*(F10:F100<>"")*(C10:C100=F10:F100))/SUMPRODUCT(--((C10:C100<>"")+(F10:F100<>"")>0)),"")} -> 0.63157895 | L5: {=IFERROR(SUMPRODUCT((F10:F100<>"")*(D10:D100<>"")*(F10:F100=D10:D100))/SUMPRODUCT(--((F10:F100<>"")+(D10:D100<>"")>0)),"")} -> 0.54545455 | M5: {=IFERROR(SUMPRODUCT((F10:F100<>"")*(E10:E100<>"")*(F10:F100=E10:E100))/SUMPRODUCT(--((F10:F100<>"")+(E10:E100<>"")>0)),"")} -> 0.5 | Q5: XML run 1 | R5: {=IFERROR( SUMPRODUCT((C10:C100<>"")*(F10:F100<>"")* ((C10:C100=F10:F100)+((C10:C100=1)*(F10:F100=2))+((C10:C100=2)*(F10:F100=1)))) / SUMPRODUCT(--((C10:C100<>"")+(F10:F100<>"")>0)), "")} -> 0.68421053 | S5: {=IFERROR( SUMPRODUCT((F10:F100<>"")*(D10:D100<>"")* ((F10:F100=D10:D100)+((F10:F100=1)*(D10:D100=2))+((F10:F100=2)*(D10:D100=1)))) / SUMPRODUCT(--((F10:F100<>"")+(D10:D100<>"")>0)), "")} -> 0.59090909 | T5: {=IFERROR( SUMPRODUCT((F10:F100<>"")*(E10:E100<>"")* ((F10:F100=E10:E100)+((F10:F100=1)*(E10:E100=2))+((F10:F100=2)*(E10:E100=1)))) / SUMPRODUCT(--((F10:F100<>"")+(E10:E100<>"")>0)), "")} -> 0.54166667
A6: Semantic FP Strict | C6: =COUNTIF(C23:C41,0) + COUNTIF(C23:C41,1) -> 5 | D6: =COUNTIF(D23:D41,0) + COUNTIF(D23:D41,1) -> 8 | E6: =COUNTIF(E23:E41,0) + COUNTIF(E23:E41,1) -> 10 | F6: =COUNTIF(F23:F41,0) + COUNTIF(F23:F41,1) -> 3 | G6: =COUNTIF(G23:G41,0) + COUNTIF(G23:G41,1) -> 6 | H6: =COUNTIF(H23:H41,0) + COUNTIF(H23:H41,1) -> 7 | J6: XML run 2 | K6: {=IFERROR(SUMPRODUCT((C10:C100<>"")*(G10:G100<>"")*(C10:C100=G10:G100))/SUMPRODUCT(--((C10:C100<>"")+(G10:G100<>"")>0)),"")} -> 0.5 | L6: {=SUMPRODUCT((D10:D100<>0)*(G10:G100<>0)) / SUMPRODUCT(((D10:D100<>0)+(G10:G100<>0)>0)*1)} -> 0.65 | M6: {=IFERROR(SUMPRODUCT((G10:G100<>"")*(E10:E100<>"")*(G10:G100=E10:E100))/SUMPRODUCT(--((G10:G100<>"")+(E10:E100<>"")>0)),"")} -> 0.48148148 | N6: {=IFERROR(SUMPRODUCT((G10:G100<>"")*(F10:F100<>"")*(G10:G100=F10:F100))/SUMPRODUCT(--((G10:G100<>"")+(F10:F100<>"")>0)),"")} -> 0.6 | Q6: XML run 2 | R6: {=IFERROR( SUMPRODUCT((C10:C100<>"")*(G10:G100<>"")* ((C10:C100=G10:G100)+((C10:C100=1)*(G10:G100=2))+((C10:C100=2)*(G10:G100=1)))) / SUMPRODUCT(--((C10:C100<>"")+(G10:G100<>"")>0)), "")} -> 0.59090909 | S6: {=IFERROR( SUMPRODUCT((D10:D100<>"")*(G10:G100<>"")* ((D10:D100=G10:G100)+((D10:D100=1)*(G10:G100=2))+((D10:D100=2)*(G10:G100=1)))) / SUMPRODUCT(--((D10:D100<>"")+(G10:G100<>"")>0)), "")} -> 0.52 | T6: {=IFERROR( SUMPRODUCT((G10:G100<>"")*(E10:E100<>"")* ((G10:G100=E10:E100)+((G10:G100=1)*(E10:E100=2))+((G10:G100=2)*(E10:E100=1)))) / SUMPRODUCT(--((G10:G100<>"")+(E10:E100<>"")>0)), "")} -> 0.48148148 | U6: {=IFERROR( SUMPRODUCT((F10:F100<>"")*(G10:G100<>"")* ((F10:F100=G10:G100)+((F10:F100=1)*(G10:G100=2))+((F10:F100=2)*(G10:G100=1)))) / SUMPRODUCT(--((F10:F100<>"")+(G10:G100<>"")>0)), "")} -> 0.65
A7: Semantic FP Loose | C7: =COUNTIF(C23:C41,0) -> 1 | D7: =COUNTIF(D23:D41,0) -> 1 | E7: =COUNTIF(E23:E41,0) -> 1 | F7: =COUNTIF(F23:F41,0) -> 0 | G7: =COUNTIF(G23:G41,0) -> 4 | H7: =COUNTIF(H23:H41,0) -> 0 | J7: XML run 3 | K7: {=IFERROR(SUMPRODUCT((C10:C100<>"")*(H10:H100<>"")*(C10:C100=H10:H100))/SUMPRODUCT(--((C10:C100<>"")+(H10:H100<>"")>0)),"")} -> 0.75 | L7: {=IFERROR(SUMPRODUCT((H10:H100<>"")*(D10:D100<>"")*(H10:H100=D10:D100))/SUMPRODUCT(--((H10:H100<>"")+(D10:D100<>"")>0)),"")} -> 0.72727273 | M7: {=IFERROR(SUMPRODUCT((H10:H100<>"")*(E10:E100<>"")*(H10:H100=E10:E100))/SUMPRODUCT(--((H10:H100<>"")+(E10:E100<>"")>0)),"")} -> 0.66666667 | N7: {=IFERROR(SUMPRODUCT((F10:F100<>"")*(H10:H100<>"")*(F10:F100=H10:H100))/SUMPRODUCT(--((F10:F100<>"")+(H10:H100<>"")>0)),"")} -> 0.61904762 | O7: {=IFERROR(SUMPRODUCT((G10:G100<>"")*(H10:H100<>"")*(G10:G100=H10:H100))/SUMPRODUCT(--((G10:G100<>"")+(H10:H100<>"")>0)),"")} -> 0.5 | Q7: XML run 3 | R7: {=IFERROR( SUMPRODUCT((C10:C100<>"")*(H10:H100<>"")* ((C10:C100=H10:H100)+((C10:C100=1)*(H10:H100=2))+((C10:C100=2)*(H10:H100=1)))) / SUMPRODUCT(--((C10:C100<>"")+(H10:H100<>"")>0)), "")} -> 0.8 | S7: {=IFERROR( SUMPRODUCT((H10:H100<>"")*(D10:D100<>"")* ((H10:H100=D10:D100)+((H10:H100=1)*(D10:D100=2))+((H10:H100=2)*(D10:D100=1)))) / SUMPRODUCT(--((H10:H100<>"")+(D10:D100<>"")>0)), "")} -> 0.77272727 | T7: {=IFERROR( SUMPRODUCT((H10:H100<>"")*(E10:E100<>"")* ((H10:H100=E10:E100)+((H10:H100=1)*(E10:E100=2))+((H10:H100=2)*(E10:E100=1)))) / SUMPRODUCT(--((H10:H100<>"")+(E10:E100<>"")>0)), "")} -> 0.70833333 | U7: {=IFERROR( SUMPRODUCT((F10:F100<>"")*(H10:H100<>"")* ((F10:F100=H10:H100)+((F10:F100=1)*(H10:H100=2))+((F10:F100=2)*(H10:H100=1)))) / SUMPRODUCT(--((F10:F100<>"")+(H10:H100<>"")>0)), "")} -> 0.61904762 | V7: {=IFERROR( SUMPRODUCT((H10:H100<>"")*(G10:G100<>"")* ((H10:H100=G10:G100)+((H10:H100=1)*(G10:G100=2))+((H10:H100=2)*(G10:G100=1)))) / SUMPRODUCT(--((H10:H100<>"")+(G10:G100<>"")>0)), "")} -> 0.54166667
C9: Chatbot run 1 | D9: Chatbot run 2 | E9: Chatbot run 3 | F9: XML run 1 | G9: XML run 2 | H9: XML run 3
A10: Pools | B10: Bank | C10: 2 | D10: 2 | E10: 2 | F10: 2 | G10: 2 | H10: 2
B11: Customer | C11: 1 | D11: 1 | E11: 2 | F11: 2 | G11: 2 | H11: 2
A12: Tasks/Messages/Events | B12: Receive Application | C12: 2 | D12: 2 | E12: 2 | F12: 2 | G12: 2 | H12: 2
B13: Evaluate Application | C13: 2 | D13: 2 | E13: 2 | F13: 2 | G13: 2 | H13: 2
B14: Notify Customer | C14: 2 | D14: 2 | E14: 2 | F14: 2 | G14: 2 | H14: 2
B15: Create Account | C15: 2 | D15: 2 | E15: 2 | F15: 2 | G15: 2 | H15: 2
B16: Send Welcome Pack | C16: 2 | D16: 2 | E16: 2 | F16: 2 | G16: 2 | H16: 2
B17: Send Bank Card | C17: 2 | D17: 2 | E17: 2 | F17: 2 | G17: 2 | H17: 2
B18: Send PIN | C18: 2 | D18: 2 | E18: 2 | F18: 2 | G18: 2 | H18: 2
A19: Conditions/Loops/Parallel: | B19: x Is application rejected? | C19: 2 | D19: 2 | E19: 2 | F19: 2 | G19: 2 | H19: 2
A20: Data Objects | B20: Application Form | C20: 2 | D20: 2 | E20: 2 | F20: 2 | G20: 2 | H20: 2
B21: Account | C21: 2 | D21: 2 | E21: 1 | F21: 2 | G21: 1 | H21: 2
A23: False Positives | B23: Account Opening Department Lane | C23: 0 | D23: 0 | E23: 0
B24: Parallel GW | C24: 1 | D24: 1 | E24: 1 | F24: 1 | G24: 1 | H24: 1
B25: Welcome Pack DO | C25: 1 | D25: 1 | E25: 1 | H25: 1
B26: Bank Card DO | C26: 1 | D26: 1 | E26: 1 | H26: 1
B27: PIN Number DO | C27: 1 | D27: 1 | E27: 1 | H27: 1
B28: Prepare Welcome Pack | D28: 1 | E28: 1 | H28: 1
B29: Prepare Bank card | D29: 1 | E29: 1
B30: Prepare PIN | D30: 1 | E30: 1
B31: Prepare Rejection Email | E31: 1
B32: Receive Notification from Bank | E32: 1
B33: Customer Service Lane | F33: 1
B34: Operations Lane | F34: 1
B35: Bank Back Office | G35: 1
B36: Second Send Rejection Notification | G36: 0
B37: Second Send Welcome Pack | G37: 0
B38: Second Send Bank card | G38: 0
B39: Second Send PIN | G39: 0
B40: Application Processing Lane | H40: 1
B41: Account Services Lane | H41: 1

Sheet c2
A1: Semantic Percision | C1: =SUM(C3:C4) / (C3+ C4+ C7) * 100 -> 100 | D1: =SUM(D3:D4) / (D3+ D4+ D7) * 100 -> 83.333333 | E1: =SUM(E3:E4) / (E3+ E4+ E7) * 100 -> 100 | F1: =SUM(F3:F4) / (F3+ F4+ F7) * 100 -> 83.333333 | G1: =SUM(G3:G4) / (G3+ G4+ G7) * 100 -> 83.333333 | H1: =SUM(H3:H4) / (H3+ H4+ H7) * 100 -> 90.909091 | J1: Jaccard Strict | K1: Chatbot run 1 | L1: Chatbot run 2 | M1: Chatbot run 3 | N1: XML run 1 | O1: XML run 2 | P1: XML run 3 | Q1: Jaccard Loose | R1: Chatbot run 1 | S1: Chatbot run 2 | T1: Chatbot run 3 | U1: XML run 1 | V1: XML run 2 | W1: XML run 3
A2: Semantic Recall | C2: =SUM(C3:C4) / SUM(C3:C5) *100 -> 100 | D2: =SUM(D3:D4) / SUM(D3:D5) *100 -> 100 | E2: =SUM(E3:E4) / SUM(E3:E5) *100 -> 100 | F2: =SUM(F3:F4) / SUM(F3:F5) *100 -> 100 | G2: =SUM(G3:G4) / SUM(G3:G5) *100 -> 100 | H2: =SUM(H3:H4) / SUM(H3:H5) *100 -> 100 | J2: Chatbot run 1 | Q2: Chatbot run 1
A3: Semantic TP Explicit | C3: =COUNTIF(C10:C19, 2) -> 10 | D3: =COUNTIF(D10:D19, 2) -> 10 | E3: =COUNTIF(E10:E19, 2) -> 10 | F3: =COUNTIF(F10:F19, 2) -> 8 | G3: =COUNTIF(G10:G19, 2) -> 9 | H3: =COUNTIF(H10:H19, 2) -> 10 | J3: Chatbot run 2 | K3: {=IFERROR(SUMPRODUCT((C10:C100<>"")*(D10:D100<>"")*(C10:C100=D10:D100))/SUMPRODUCT(--((C10:C100<>"")+(D10:D100<>"")>0)),"")} -> 0.8 | Q3: Chatbot run 2 | R3: {=IFERROR( SUMPRODUCT((C10:C100<>"")*(D10:D100<>"")* ((C10:C100=D10:D100)+((C10:C100=1)*(D10:D100=2))+((C10:C100=2)*(D10:D100=1)))) / SUMPRODUCT(--((C10:C100<>"")+(D10:D100<>"")>0)), "")} -> 0.8
A4: Semantic TP Implicit | C4: =COUNTIF(C10:C19, 1) -> 0 | D4: =COUNTIF(D10:D19, 1) -> 0 | E4: =COUNTIF(E10:E19, 1) -> 0 | F4: =COUNTIF(F10:F19, 1) -> 2 | G4: =COUNTIF(G10:G19, 1) -> 1 | H4: =COUNTIF(H10:H19, 1) -> 0 | J4: Chatbot run 3 | K4: {=IFERROR(SUMPRODUCT((C10:C100<>"")*(E10:E100<>"")*(C10:C100=E10:E100))/SUMPRODUCT(--((C10:C100<>"")+(E10:E100<>"")>0)),"")} -> 1 | L4: {=IFERROR(SUMPRODUCT((E10:E100<>"")*(D10:D100<>"")*(E10:E100=D10:D100))/SUMPRODUCT(--((E10:E100<>"")+(D10:D100<>"")>0)),"")} -> 0.8 | Q4: Chatbot run 3 | R4: {=IFERROR( SUMPRODUCT((C10:C100<>"")*(E10:E100<>"")* ((C10:C100=E10:E100)+((C10:C100=1)*(E10:E100=2))+((C10:C100=2)*(E10:E100=1)))) / SUMPRODUCT(--((C10:C100<>"")+(E10:E100<>"")>0)), "")} -> 1 | S4: {=IFERROR( SUMPRODUCT((E10:E100<>"")*(D10:D100<>"")* ((E10:E100=D10:D100)+((E10:E100=1)*(D10:D100=2))+((E10:E100=2)*(D10:D100=1)))) / SUMPRODUCT(--((E10:E100<>"")+(D10:D100<>"")>0)), "")} -> 0.8
A5: Semantic FN | C5: =COUNTIF(C10:C19, 0) -> 0 | D5: =COUNTIF(D10:D19, 0) -> 0 | E5: =COUNTIF(E10:E19, 0) -> 0 | F5: =COUNTIF(F10:F19, 0) -> 0 | G5: =COUNTIF(G10:G19, 0) -> 0 | H5: =COUNTIF(H10:H19, 0) -> 0 | J5: XML run 1 | K5: {=IFERROR(SUMPRODUCT((C10:C100<>"")*(F10:F100<>"")*(C10:C100=F10:F100))/SUMPRODUCT(--((C10:C100<>"")+(F10:F100<>"")>0)),"")} -> 0.53333333 | L5: {=IFERROR(SUMPRODUCT((F10:F100<>"")*(D10:D100<>"")*(F10:F100=D10:D100))/SUMPRODUCT(--((F10:F100<>"")+(D10:D100<>"")>0)),"")} -> 0.71428571 | M5: {=IFERROR(SUMPRODUCT((F10:F100<>"")*(E10:E100<>"")*(F10:F100=E10:E100))/SUMPRODUCT(--((F10:F100<>"")+(E10:E100<>"")>0)),"")} -> 0.53333333 | Q5: XML run 1 | R5: {=IFERROR( SUMPRODUCT((C10:C100<>"")*(F10:F100<>"")* ((C10:C100=F10:F100)+((C10:C100=1)*(F10:F100=2))+((C10:C100=2)*(F10:F100=1)))) / SUMPRODUCT(--((C10:C100<>"")+(F10:F100<>"")>0)), "")} -> 0.66666667 | S5: {=IFERROR( SUMPRODUCT((F10:F100<>"")*(D10:D100<>"")* ((F10:F100=D10:D100)+((F10:F100=1)*(D10:D100=2))+((F10:F100=2)*(D10:D100=1)))) / SUMPRODUCT(--((F10:F100<>"")+(D10:D100<>"")>0)), "")} -> 0.85714286 | T5: {=IFERROR( SUMPRODUCT((F10:F100<>"")*(E10:E100<>"")* ((F10:F100=E10:E100)+((F10:F100=1)*(E10:E100=2))+((F10:F100=2)*(E10:E100=1)))) / SUMPRODUCT(--((F10:F100<>"")+(E10:E100<>"")>0)), "")} -> 0.66666667
A6: Semantic FP Strict | C6: =COUNTIF(C21:C41,0) + COUNTIF(C21:C41,1) -> 3 | D6: =COUNTIF(D21:D41,0) + COUNTIF(D21:D41,1) -> 4 | E6: =COUNTIF(E21:E41,0) + COUNTIF(E21:E41,1) -> 3 | F6: =COUNTIF(F21:F41,0) + COUNTIF(F21:F41,1) -> 2 | G6: =COUNTIF(G21:G41,0) + COUNTIF(G21:G41,1) -> 3 | H6: =COUNTIF(H21:H41,0) + COUNTIF(H21:H41,1) -> 2 | J6: XML run 2 | K6: {=IFERROR(SUMPRODUCT((C10:C100<>"")*(G10:G100<>"")*(C10:C100=G10:G100))/SUMPRODUCT(--((C10:C100<>"")+(G10:G100<>"")>0)),"")} -> 0.5625 | L6: {=SUMPRODUCT((D10:D100<>0)*(G10:G100<>0)) / SUMPRODUCT(((D10:D100<>0)+(G10:G100<>0)>0)*1)} -> 0.76923077 | M6: {=IFERROR(SUMPRODUCT((G10:G100<>"")*(E10:E100<>"")*(G10:G100=E10:E100))/SUMPRODUCT(--((G10:G100<>"")+(E10:E100<>"")>0)),"")} -> 0.5625 | N6: {=IFERROR(SUMPRODUCT((G10:G100<>"")*(F10:F100<>"")*(G10:G100=F10:F100))/SUMPRODUCT(--((G10:G100<>"")+(F10:F100<>"")>0)),"")} -> 0.84615385 | Q6: XML run 2 | R6: {=IFERROR( SUMPRODUCT((C10:C100<>"")*(G10:G100<>"")* ((C10:C100=G10:G100)+((C10:C100=1)*(G10:G100=2))+((C10:C100=2)*(G10:G100=1)))) / SUMPRODUCT(--((C10:C100<>"")+(G10:G100<>"")>0)), "")} -> 0.625 | S6: {=IFERROR( SUMPRODUCT((D10:D100<>"")*(G10:G100<>"")* ((D10:D100=G10:G100)+((D10:D100=1)*(G10:G100=2))+((D10:D100=2)*(G10:G100=1)))) / SUMPRODUCT(--((D10:D100<>"")+(G10:G100<>"")>0)), "")} -> 0.8 | T6: {=IFERROR( SUMPRODUCT((G10:G100<>"")*(E10:E100<>"")* ((G10:G100=E10:E100)+((G10:G100=1)*(E10:E100=2))+((G10:G100=2)*(E10:E100=1)))) / SUMPRODUCT(--((G10:G100<>"")+(E10:E100<>"")>0)), "")} -> 0.625 | U6: {=IFERROR( SUMPRODUCT((F10:F100<>"")*(G10:G100<>"")* ((F10:F100=G10:G100)+((F10:F100=1)*(G10:G100=2))+((F10:F100=2)*(G10:G100=1)))) / SUMPRODUCT(--((F10:F100<>"")+(G10:G100<>"")>0)), "")} -> 0.92307692
A7: Semantic FP Loose | C7: =COUNTIF(C21:C41,0) -> 0 | D7: =COUNTIF(D21:D41,0) -> 2 | E7: =COUNTIF(E21:E41,0) -> 0 | F7: =COUNTIF(F21:F41,0) -> 2 | G7: =COUNTIF(G21:G41,0) -> 2 | H7: =COUNTIF(H21:H41,0) -> 1 | J7: XML run 3 | K7: {=IFERROR(SUMPRODUCT((C10:C100<>"")*(H10:H100<>"")*(C10:C100=H10:H100))/SUMPRODUCT(--((C10:C100<>"")+(H10:H100<>"")>0)),"")} -> 0.71428571 | L7: {=IFERROR(SUMPRODUCT((H10:H100<>"")*(D10:D100<>"")*(H10:H100=D10:D100))/SUMPRODUCT(--((H10:H100<>"")+(D10:D100<>"")>0)),"")} -> 0.66666667 | M7: {=IFERROR(SUMPRODUCT((H10:H100<>"")*(E10:E100<>"")*(H10:H100=E10:E100))/SUMPRODUCT(--((H10:H100<>"")+(E10:E100<>"")>0)),"")} -> 0.71428571 | N7: {=IFERROR(SUMPRODUCT((F10:F100<>"")*(H10:H100<>"")*(F10:F100=H10:H100))/SUMPRODUCT(--((F10:F100<>"")+(H10:H100<>"")>0)),"")} -> 0.57142857 | O7: {=IFERROR(SUMPRODUCT((G10:G100<>"")*(H10:H100<>"")*(G10:G100=H10:H100))/SUMPRODUCT(--((G10:G100<>"")+(H10:H100<>"")>0)),"")} -> 0.71428571 | Q7: XML run 3 | R7: {=IFERROR( SUMPRODUCT((C10:C100<>"")*(H10:H100<>"")* ((C10:C100=H10:H100)+((C10:C100=1)*(H10:H100=2))+((C10:C100=2)*(H10:H100=1)))) / SUMPRODUCT(--((C10:C100<>"")+(H10:H100<>"")>0)), "")} -> 0.71428571 | S7: {=IFERROR( SUMPRODUCT((H10:H100<>"")*(D10:D100<>"")* ((H10:H100=D10:D100)+((H10:H100=1)*(D10:D100=2))+((H10:H100=2)*(D10:D100=1)))) / SUMPRODUCT(--((H10:H100<>"")+(D10:D100<>"")>0)), "")} -> 0.66666667 | T7: {=IFERROR( SUMPRODUCT((H10:H100<>"")*(E10:E100<>"")* ((H10:H100=E10:E100)+((H10:H100=1)*(E10:E100=2))+((H10:H100=2)*(E10:E100=1)))) / SUMPRODUCT(--((H10:H100<>"")+(E10:E100<>"")>0)), "")} -> 0.71428571 | U7: {=IFERROR( SUMPRODUCT((F10:F100<>"")*(H10:H100<>"")* ((F10:F100=H10:H100)+((F10:F100=1)*(H10:H100=2))+((F10:F100=2)*(H10:H100=1)))) / SUMPRODUCT(--((F10:F100<>"")+(H10:H100<>"")>0)), "")} -> 0.71428571 | V7: {=IFERROR( SUMPRODUCT((H10:H100<>"")*(G10:G100<>"")* ((H10:H100=G10:G100)+((H10:H100=1)*(G10:G100=2))+((H10:H100=2)*(G10:G100=1)))) / SUMPRODUCT(--((H10:H100<>"")+(G10:G100<>"")>0)), "")} -> 0.78571429
C9: Chatbot run 1 | D9: Chatbot run 2 | E9: Chatbot run 3 | F9: XML run 1 | G9: XML run 2 | H9: XML run 3
A10: Pools | B10: Management | C10: 2 | D10: 2 | E10: 2 | F10: 2 | G10: 2 | H10: 2
B11: Accountant | C11: 2 | D11: 2 | E11: 2 | F11: 2 | G11: 2 | H11: 2
A12: Tasks/Messages/Events | B12: Order Cash-out Report | C12: 2 | D12: 2 | E12: 2 | F12: 2 | G12: 2 | H12: 2
B13: Filter Cash Transactions | C13: 2 | D13: 2 | E13: 2 | F13: 2 | G13: 2 | H13: 2
B14: Print Cash-out Report | C14: 2 | D14: 2 | E14: 2 | F14: 2 | G14: 2 | H14: 2
B15: Give Report to Management | C15: 2 | D15: 2 | E15: 2 | F15: 2 | G15: 2 | H15: 2
A16: Conditions/Loops/Parallel: | B16: Is Query Not Empty? | C16: 2 | D16: 2 | E16: 2 | F16: 2 | G16: 2 | H16: 2
A17: Data Objects | B17: Cash Database | C17: 2 | D17: 2 | E17: 2 | F17: 2 | G17: 2 | H17: 2
B18: Cash Transactions | C18: 2 | D18: 2 | E18: 2 | F18: 1 | G18: 2 | H18: 2
B19: Cash-out Report | C19: 2 | D19: 2 | E19: 2 | F19: 1 | G19: 1 | H19: 2
A21: False Positives | B21: Management Pool | D21: 0 | F21: 0 | G21: 0
B22: Accountant Pool | D22: 0 | F22: 0 | G22: 0
B23: Send Year and Month / Receive Year and Month | G23: 1 | H23: 1
B24: Year and Month DO | C24: 1 | D24: 1 | E24: 1 | H24: 0
B25: Wait for Report Order
B26: Company Pool | C26: 1 | E26: 1
B27: Specify Year and Month | C27: 1 | D27: 1 | E27: 1

Sheet c3
A1: Semantic Percision | C1: =SUM(C3:C4) / (C3+ C4+ C7) * 100 -> 81.818182 | D1: =SUM(D3:D4) / (D3+ D4+ D7) * 100 -> 75 | E1: =SUM(E3:E4) / (E3+ E4+ E7) * 100 -> 81.818182 | F1: =SUM(F3:F4) / (F3+ F4+ F7) * 100 -> 81.818182 | G1: =SUM(G3:G4) / (G3+ G4+ G7) * 100 -> 81.818182 | H1: =SUM(H3:H4) / (H3+ H4+ H7) * 100 -> 90 | J1: Jaccard Strict | K1: Chatbot run 1 | L1: Chatbot run 2 | M1: Chatbot run 3 | N1: XML run 1 | O1: XML run 2 | P1: XML run 3 | Q1: Jaccard Loose | R1: Chatbot run 1 | S1: Chatbot run 2 | T1: Chatbot run 3 | U1: XML run 1 | V1: XML run 2 | W1: XML run 3
A2: Semantic Recall | C2: =SUM(C3:C4) / SUM(C3:C5) *100 -> 100 | D2: =SUM(D3:D4) / SUM(D3:D5) *100 -> 100 | E2: =SUM(E3:E4) / SUM(E3:E5) *100 -> 100 | F2: =SUM(F3:F4) / SUM(F3:F5) *100 -> 100 | G2: =SUM(G3:G4) / SUM(G3:G5) *100 -> 100 | H2: =SUM(H3:H4) / SUM(H3:H5) *100 -> 100 | J2: Chatbot run 1 | Q2: Chatbot run 1
A3: Semantic TP Explicit | C3: =COUNTIF(C10:C18, 2) -> 9 | D3: =COUNTIF(D10:D18, 2) -> 9 | E3: =COUNTIF(E10:E18, 2) -> 9 | F3: =COUNTIF(F10:F18, 2) -> 9 | G3: =COUNTIF(G10:G18, 2) -> 7 | H3: =COUNTIF(H10:H18, 2) -> 8 | J3: Chatbot run 2 | K3: {=IFERROR(SUMPRODUCT((C10:C100<>"")*(D10:D100<>"")*(C10:C100=D10:D100))/SUMPRODUCT(--((C10:C100<>"")+(D10:D100<>"")>0)),"")} -> 0.93333333 | Q3: Chatbot run 2 | R3: {=IFERROR( SUMPRODUCT((C10:C100<>"")*(D10:D100<>"")* ((C10:C100=D10:D100)+((C10:C100=1)*(D10:D100=2))+((C10:C100=2)*(D10:D100=1)))) / SUMPRODUCT(--((C10:C100<>"")+(D10:D100<>"")>0)), "")} -> 0.93333333
A4: Semantic TP Implicit | C4: =COUNTIF(C10:C18, 1) -> 0 | D4: =COUNTIF(D10:D18, 1) -> 0 | E4: =COUNTIF(E10:E18, 1) -> 0 | F4: =COUNTIF(F10:F18, 1) -> 0 | G4: =COUNTIF(G10:G18, 1) -> 2 | H4: =COUNTIF(H10:H18, 1) -> 1 | J4: Chatbot run 3 | K4: {=IFERROR(SUMPRODUCT((C10:C100<>"")*(E10:E100<>"")*(C10:C100=E10:E100))/SUMPRODUCT(--((C10:C100<>"")+(E10:E100<>"")>0)),"")} -> 0.86666667 | L4: {=IFERROR(SUMPRODUCT((E10:E100<>"")*(D10:D100<>"")*(E10:E100=D10:D100))/SUMPRODUCT(--((E10:E100<>"")+(D10:D100<>"")>0)),"")} -> 0.93333333 | Q4: Chatbot run 3 | R4: {=IFERROR( SUMPRODUCT((C10:C100<>"")*(E10:E100<>"")* ((C10:C100=E10:E100)+((C10:C100=1)*(E10:E100=2))+((C10:C100=2)*(E10:E100=1)))) / SUMPRODUCT(--((C10:C100<>"")+(E10:E100<>"")>0)), "")} -> 0.86666667 | S4: {=IFERROR( SUMPRODUCT((E10:E100<>"")*(D10:D100<>"")* ((E10:E100=D10:D100)+((E10:E100=1)*(D10:D100=2))+((E10:E100=2)*(D10:D100=1)))) / SUMPRODUCT(--((E10:E100<>"")+(D10:D100<>"")>0)), "")} -> 0.93333333
A5: Semantic FN | C5: =COUNTIF(C10:C18, 0) -> 0 | D5: =COUNTIF(D10:D18, 0) -> 0 | E5: =COUNTIF(E10:E18, 0) -> 0 | F5: =COUNTIF(F10:F18, 0) -> 0 | G5: =COUNTIF(G10:G18, 0) -> 0 | H5: =COUNTIF(H10:H18, 0) -> 0 | J5: XML run 1 | K5: {=IFERROR(SUMPRODUCT((C10:C100<>"")*(F10:F100<>"")*(C10:C100=F10:F100))/SUMPRODUCT(--((C10:C100<>"")+(F10:F100<>"")>0)),"")} -> 0.875 | L5: {=IFERROR(SUMPRODUCT((F10:F100<>"")*(D10:D100<>"")*(F10:F100=D10:D100))/SUMPRODUCT(--((F10:F100<>"")+(D10:D100<>"")>0)),"")} -> 0.82352941 | M5: {=IFERROR(SUMPRODUCT((F10:F100<>"")*(E10:E100<>"")*(F10:F100=E10:E100))/SUMPRODUCT(--((F10:F100<>"")+(E10:E100<>"")>0)),"")} -> 0.76470588 | Q5: XML run 1 | R5: {=IFERROR( SUMPRODUCT((C10:C100<>"")*(F10:F100<>"")* ((C10:C100=F10:F100)+((C10:C100=1)*(F10:F100=2))+((C10:C100=2)*(F10:F100=1)))) / SUMPRODUCT(--((C10:C100<>"")+(F10:F100<>"")>0)), "")} -> 0.875 | S5: {=IFERROR( SUMPRODUCT((F10:F100<>"")*(D10:D100<>"")* ((F10:F100=D10:D100)+((F10:F100=1)*(D10:D100=2))+((F10:F100=2)*(D10:D100=1)))) / SUMPRODUCT(--((F10:F100<>"")+(D10:D100<>"")>0)), "")} -> 0.82352941 | T5: {=IFERROR( SUMPRODUCT((F10:F100<>"")*(E10:E100<>"")* ((F10:F100=E10:E100)+((F10:F100=1)*(E10:E100=2))+((F10:F100=2)*(E10:E100=1)))) / SUMPRODUCT(--((F10:F100<>"")+(E10:E100<>"")>0)), "")} -> 0.76470588
A6: Semantic FP Strict | C6: =COUNTIF(C20:C56,0) + COUNTIF(C20:C56,1) -> 5 | D6: =COUNTIF(D20:D56,0) + COUNTIF(D20:D56,1) -> 6 | E6: =COUNTIF(E20:E56,0) + COUNTIF(E20:E56,1) -> 5 | F6: =COUNTIF(F20:F56,0) + COUNTIF(F20:F56,1) -> 7 | G6: =COUNTIF(G20:G56,0) + COUNTIF(G20:G56,1) -> 5 | H6: =COUNTIF(H20:H56,0) + COUNTIF(H20:H56,1) -> 6 | J6: XML run 2 | K6: {=IFERROR(SUMPRODUCT((C10:C100<>"")*(G10:G100<>"")*(C10:C100=G10:G100))/SUMPRODUCT(--((C10:C100<>"")+(G10:G100<>"")>0)),"")} -> 0.73333333 | L6: {=SUMPRODUCT((D10:D100<>0)*(G10:G100<>0)) / SUMPRODUCT(((D10:D100<>0)+(G10:G100<>0)>0)*1)} -> 1 | M6: {=IFERROR(SUMPRODUCT((G10:G100<>"")*(E10:E100<>"")*(G10:G100=E10:E100))/SUMPRODUCT(--((G10:G100<>"")+(E10:E100<>"")>0)),"")} -> 0.73333333 | N6: {=IFERROR(SUMPRODUCT((G10:G100<>"")*(F10:F100<>"")*(G10:G100=F10:F100))/SUMPRODUCT(--((G10:G100<>"")+(F10:F100<>"")>0)),"")} -> 0.64705882 | Q6: XML run 2 | R6: {=IFERROR( SUMPRODUCT((C10:C100<>"")*(G10:G100<>"")* ((C10:C100=G10:G100)+((C10:C100=1)*(G10:G100=2))+((C10:C100=2)*(G10:G100=1)))) / SUMPRODUCT(--((C10:C100<>"")+(G10:G100<>"")>0)), "")} -> 0.86666667 | S6: {=IFERROR( SUMPRODUCT((D10:D100<>"")*(G10:G100<>"")* ((D10:D100=G10:G100)+((D10:D100=1)*(G10:G100=2))+((D10:D100=2)*(G10:G100=1)))) / SUMPRODUCT(--((D10:D100<>"")+(G10:G100<>"")>0)), "")} -> 0.8125 | T6: {=IFERROR( SUMPRODUCT((G10:G100<>"")*(E10:E100<>"")* ((G10:G100=E10:E100)+((G10:G100=1)*(E10:E100=2))+((G10:G100=2)*(E10:E100=1)))) / SUMPRODUCT(--((G10:G100<>"")+(E10:E100<>"")>0)), "")} -> 0.86666667 | U6: {=IFERROR( SUMPRODUCT((F10:F100<>"")*(G10:G100<>"")* ((F10:F100=G10:G100)+((F10:F100=1)*(G10:G100=2))+((F10:F100=2)*(G10:G100=1)))) / SUMPRODUCT(--((F10:F100<>"")+(G10:G100<>"")>0)), "")} -> 0.76470588
A7: Semantic FP Loose | C7: =COUNTIF(C20:C56,0) -> 2 | D7: =COUNTIF(D20:D56,0) -> 3 | E7: =COUNTIF(E20:E56,0) -> 2 | F7: =COUNTIF(F20:F56,0) -> 2 | G7: =COUNTIF(G20:G56,0) -> 2 | H7: =COUNTIF(H20:H56,0) -> 1 | J7: XML run 3 | K7: {=IFERROR(SUMPRODUCT((C10:C100<>"")*(H10:H100<>"")*(C10:C100=H10:H100))/SUMPRODUCT(--((C10:C100<>"")+(H10:H100<>"")>0)),"")} -> 0.75 | L7: {=IFERROR(SUMPRODUCT((H10:H100<>"")*(D10:D100<>"")*(H10:H100=D10:D100))/SUMPRODUCT(--((H10:H100<>"")+(D10:D100<>"")>0)),"")} -> 0.70588235 | M7: {=IFERROR(SUMPRODUCT((H10:H100<>"")*(E10:E100<>"")*(H10:H100=E10:E100))/SUMPRODUCT(--((H10:H100<>"")+(E10:E100<>"")>0)),"")} -> 0.75 | N7: {=IFERROR(SUMPRODUCT((F10:F100<>"")*(H10:H100<>"")*(F10:F100=H10:H100))/SUMPRODUCT(--((F10:F100<>"")+(H10:H100<>"")>0)),"")} -> 0.76470588 | O7: {=IFERROR(SUMPRODUCT((G10:G100<>"")*(H10:H100<>"")*(G10:G100=H10:H100))/SUMPRODUCT(--((G10:G100<>"")+(H10:H100<>"")>0)),"")} -> 0.75 | Q7: XML run 3 | R7: {=IFERROR( SUMPRODUCT((C10:C100<>"")*(H10:H100<>"")* ((C10:C100=H10:H100)+((C10:C100=1)*(H10:H100=2))+((C10:C100=2)*(H10:H100=1)))) / SUMPRODUCT(--((C10:C100<>"")+(H10:H100<>"")>0)), "")} -> 0.8125 | S7: {=IFERROR( SUMPRODUCT((H10:H100<>"")*(D10:D100<>"")* ((H10:H100=D10:D100)+((H10:H100=1)*(D10:D100=2))+((H10:H100=2)*(D10:D100=1)))) / SUMPRODUCT(--((H10:H100<>"")+(D10:D100<>"")>0)), "")} -> 0.76470588 | T7: {=IFERROR( SUMPRODUCT((H10:H100<>"")*(E10:E100<>"")* ((H10:H100=E10:E100)+((H10:H100=1)*(E10:E100=2))+((H10:H100=2)*(E10:E100=1)))) / SUMPRODUCT(--((H10:H100<>"")+(E10:E100<>"")>0)), "")} -> 0.8125 | U7: {=IFERROR( SUMPRODUCT((F10:F100<>"")*(H10:H100<>"")* ((F10:F100=H10:H100)+((F10:F100=1)*(H10:H100=2))+((F10:F100=2)*(H10:H100=1)))) / SUMPRODUCT(--((F10:F100<>"")+(H10:H100<>"")>0)), "")} -> 0.82352941 | V7: {=IFERROR( SUMPRODUCT((H10:H100<>"")*(G10:G100<>"")* ((H10:H100=G10:G100)+((H10:H100=1)*(G10:G100=2))+((H10:H100=2)*(G10:G100=1)))) / SUMPRODUCT(--((H10:H100<>"")+(G10:G100<>"")>0)), "")} -> 0.8125
C9: Chatbot run 1 | D9: Chatbot run 2 | E9: Chatbot run 3 | F9: XML run 1 | G9: XML run 2 | H9: XML run 3
A10: Tasks/Messages/Events | B10: Assess Risk | C10: 2 | D10: 2 | E10: 2 | F10: 2 | G10: 2 | H10: 2
B11: Receive Credit Request | C11: 2 | D11: 2 | E11: 2 | F11: 2 | G11: 2 | H11: 2
B12: Carry Out Advanced Risk Assessment | C12: 2 | D12: 2 | E12: 2 | F12: 2 | G12: 2 | H12: 2
B13: Carry Out Simple Risk Assessment | C13: 2 | D13: 2 | E13: 2 | F13: 2 | G13: 2 | H13: 2
B14: Notify Customer of Assessment Result | C14: 2 | D14: 2 | E14: 2 | F14: 2 | G14: 2 | H14: 2
B15: Organize Disbursement | C15: 2 | D15: 2 | E15: 2 | F15: 2 | G15: 2 | H15: 2
A16: Conditions/Loops/Parallel | B16: Is Risk above threshold? | C16: 2 | D16: 2 | E16: 2 | F16: 2 | G16: 2 | H16: 2
A17: Data Objects | B17: Credit Request | C17: 2 | D17: 2 | E17: 2 | F17: 2 | G17: 1 | H17: 1
B18: Assessment Result | C18: 2 | D18: 2 | E18: 2 | F18: 2 | G18: 1 | H18: 2
A20: False Positives | B20: Customer Pool | C20: 1 | D20: 1 | E20: 1 | F20: 1 | G20: 1 | H20: 1
B21: Bank Pool | C21: 1 | D21: 1 | E21: 1 | F21: 1 | G21: 1 | H21: 1
B22: Receive Assesmnet Result | C22: 1 | D22: 1 | E22: 1 | F22: 1 | G22: 1 | H22: 1
B23: Risk Managmnet Lane | C23: 0 | D23: 0 | E23: 0 | F23: 0 | G23: 0 | H23: 0
B24: Distribumnet Lane | C24: 0 | D24: 0 | F24: 0
B25: Credit Department Lane | D25: 0 | E25: 0
B26: Send Credit Request | F26: 1 | H26: 1
B27: Prepare Assessment Result | F27: 1
B28: Processing Department Lane | G28: 0
B29: Operations Lane | H29: 1

Sheet c4
A1: Semantic Percision | C1: =SUM(C3:C4) / (C3+ C4+ C7) * 100 -> 91.666667 | D1: =SUM(D3:D4) / (D3+ D4+ D7) * 100 -> 100 | E1: =SUM(E3:E4) / (E3+ E4+ E7) * 100 -> 100 | F1: =SUM(F3:F4) / (F3+ F4+ F7) * 100 -> 66.666667 | G1: =SUM(G3:G4) / (G3+ G4+ G7) * 100 -> 95.652174 | H1: =SUM(H3:H4) / (H3+ H4+ H7) * 100 -> 95.652174 | J1: Jaccard Strict | K1: Chatbot run 1 | L1: Chatbot run 2 | M1: Chatbot run 3 | N1: XML run 1 | O1: XML run 2 | P1: XML run 3 | Q1: Jaccard Loose | R1: Chatbot run 1 | S1: Chatbot run 2 | T1: Chatbot run 3 | U1: XML run 1 | V1: XML run 2 | W1: XML run 3
A2: Semantic Recall | C2: =SUM(C3:C4) / SUM(C3:C5) *100 -> 100 | D2: =SUM(D3:D4) / SUM(D3:D5) *100 -> 100 | E2: =SUM(E3:E4) / SUM(E3:E5) *100 -> 100 | F2: =SUM(F3:F4) / SUM(F3:F5) *100 -> 100 | G2: =SUM(G3:G4) / SUM(G3:G5) *100 -> 100 | H2: =SUM(H3:H4) / SUM(H3:H5) *100 -> 100 | J2: Chatbot run 1 | Q2: Chatbot run 1
A3: Semantic TP Explicit | C3: =COUNTIF(C10:C31, 2) -> 20 | D3: =COUNTIF(D10:D31, 2) -> 20 | E3: =COUNTIF(E10:E31, 2) -> 20 | F3: =COUNTIF(F10:F31, 2) -> 19 | G3: =COUNTIF(G10:G31, 2) -> 21 | H3: =COUNTIF(H10:H31, 2) -> 19 | J3: Chatbot run 2 | K3: {=IFERROR(SUMPRODUCT((C10:C100<>"")*(D10:D100<>"")*(C10:C100=D10:D100))/SUMPRODUCT(--((C10:C100<>"")+(D10:D100<>"")>0)),"")} -> 0.68965517 | Q3: Chatbot run 2 | R3: {=IFERROR( SUMPRODUCT((C10:C100<>"")*(D10:D100<>"")* ((C10:C100=D10:D100)+((C10:C100=1)*(D10:D100=2))+((C10:C100=2)*(D10:D100=1)))) / SUMPRODUCT(--((C10:C100<>"")+(D10:D100<>"")>0)), "")} -> 0.75862069
A4: Semantic TP Implicit | C4: =COUNTIF(C10:C31, 1) -> 2 | D4: =COUNTIF(D10:D31, 1) -> 2 | E4: =COUNTIF(E10:E31, 1) -> 2 | F4: =COUNTIF(F10:F31, 1) -> 3 | G4: =COUNTIF(G10:G31, 1) -> 1 | H4: =COUNTIF(H10:H31, 1) -> 3 | J4: Chatbot run 3 | K4: {=IFERROR(SUMPRODUCT((C10:C100<>"")*(E10:E100<>"")*(C10:C100=E10:E100))/SUMPRODUCT(--((C10:C100<>"")+(E10:E100<>"")>0)),"")} -> 0.625 | L4: {=IFERROR(SUMPRODUCT((E10:E100<>"")*(D10:D100<>"")*(E10:E100=D10:D100))/SUMPRODUCT(--((E10:E100<>"")+(D10:D100<>"")>0)),"")} -> 0.82758621 | Q4: Chatbot run 3 | R4: {=IFERROR( SUMPRODUCT((C10:C100<>"")*(E10:E100<>"")* ((C10:C100=E10:E100)+((C10:C100=1)*(E10:E100=2))+((C10:C100=2)*(E10:E100=1)))) / SUMPRODUCT(--((C10:C100<>"")+(E10:E100<>"")>0)), "")} -> 0.6875 | S4: {=IFERROR( SUMPRODUCT((E10:E100<>"")*(D10:D100<>"")* ((E10:E100=D10:D100)+((E10:E100=1)*(D10:D100=2))+((E10:E100=2)*(D10:D100=1)))) / SUMPRODUCT(--((E10:E100<>"")+(D10:D100<>"")>0)), "")} -> 0.89655172
A5: Semantic FN | C5: =COUNTIF(C10:C31, 0) -> 0 | D5: =COUNTIF(D10:D31, 0) -> 0 | E5: =COUNTIF(E10:E31, 0) -> 0 | F5: =COUNTIF(F10:F31, 0) -> 0 | G5: =COUNTIF(G10:G31, 0) -> 0 | H5: =COUNTIF(H10:H31, 0) -> 0 | J5: XML run 1 | K5: {=IFERROR(SUMPRODUCT((C10:C100<>"")*(F10:F100<>"")*(C10:C100=F10:F100))/SUMPRODUCT(--((C10:C100<>"")+(F10:F100<>"")>0)),"")} -> 0.62162162 | L5: {=IFERROR(SUMPRODUCT((F10:F100<>"")*(D10:D100<>"")*(F10:F100=D10:D100))/SUMPRODUCT(--((F10:F100<>"")+(D10:D100<>"")>0)),"")} -> 0.51282051 | M5: {=IFERROR(SUMPRODUCT((F10:F100<>"")*(E10:E100<>"")*(F10:F100=E10:E100))/SUMPRODUCT(--((F10:F100<>"")+(E10:E100<>"")>0)),"")} -> 0.47619048 | Q5: XML run 1 | R5: {=IFERROR( SUMPRODUCT((C10:C100<>"")*(F10:F100<>"")* ((C10:C100=F10:F100)+((C10:C100=1)*(F10:F100=2))+((C10:C100=2)*(F10:F100=1)))) / SUMPRODUCT(--((C10:C100<>"")+(F10:F100<>"")>0)), "")} -> 0.64864865 | S5: {=IFERROR( SUMPRODUCT((F10:F100<>"")*(D10:D100<>"")* ((F10:F100=D10:D100)+((F10:F100=1)*(D10:D100=2))+((F10:F100=2)*(D10:D100=1)))) / SUMPRODUCT(--((F10:F100<>"")+(D10:D100<>"")>0)), "")} -> 0.58974359 | T5: {=IFERROR( SUMPRODUCT((F10:F100<>"")*(E10:E100<>"")* ((F10:F100=E10:E100)+((F10:F100=1)*(E10:E100=2))+((F10:F100=2)*(E10:E100=1)))) / SUMPRODUCT(--((F10:F100<>"")+(E10:E100<>"")>0)), "")} -> 0.54761905
A6: Semantic FP Strict | C6: =COUNTIF(C33:C57,0) + COUNTIF(C33:C57,1) -> 3 | D6: =COUNTIF(D33:D57,0) + COUNTIF(D33:D57,1) -> 4 | E6: =COUNTIF(E33:E57,0) + COUNTIF(E33:E57,1) -> 7 | F6: =COUNTIF(F33:F57,0) + COUNTIF(F33:F57,1) -> 14 | G6: =COUNTIF(G33:G57,0) + COUNTIF(G33:G57,1) -> 3 | H6: =COUNTIF(H33:H57,0) + COUNTIF(H33:H57,1) -> 6 | J6: XML run 2 | K6: {=IFERROR(SUMPRODUCT((C10:C100<>"")*(G10:G100<>"")*(C10:C100=G10:G100))/SUMPRODUCT(--((C10:C100<>"")+(G10:G100<>"")>0)),"")} -> 0.75 | L6: {=SUMPRODUCT((D10:D100<>0)*(G10:G100<>0)) / SUMPRODUCT(((D10:D100<>0)+(G10:G100<>0)>0)*1)} -> 0.85185185 | M6: {=IFERROR(SUMPRODUCT((G10:G100<>"")*(E10:E100<>"")*(G10:G100=E10:E100))/SUMPRODUCT(--((G10:G100<>"")+(E10:E100<>"")>0)),"")} -> 0.70967742 | N6: {=IFERROR(SUMPRODUCT((G10:G100<>"")*(F10:F100<>"")*(G10:G100=F10:F100))/SUMPRODUCT(--((G10:G100<>"")+(F10:F100<>"")>0)),"")} -> 0.55263158 | Q6: XML run 2 | R6: {=IFERROR( SUMPRODUCT((C10:C100<>"")*(G10:G100<>"")* ((C10:C100=G10:G100)+((C10:C100=1)*(G10:G100=2))+((C10:C100=2)*(G10:G100=1)))) / SUMPRODUCT(--((C10:C100<>"")+(G10:G100<>"")>0)), "")} -> 0.78571429 | S6: {=IFERROR( SUMPRODUCT((D10:D100<>"")*(G10:G100<>"")* ((D10:D100=G10:G100)+((D10:D100=1)*(G10:G100=2))+((D10:D100=2)*(G10:G100=1)))) / SUMPRODUCT(--((D10:D100<>"")+(G10:G100<>"")>0)), "")} -> 0.82142857 | T6: {=IFERROR( SUMPRODUCT((G10:G100<>"")*(E10:E100<>"")* ((G10:G100=E10:E100)+((G10:G100=1)*(E10:E100=2))+((G10:G100=2)*(E10:E100=1)))) / SUMPRODUCT(--((G10:G100<>"")+(E10:E100<>"")>0)), "")} -> 0.74193548 | U6: {=IFERROR( SUMPRODUCT((F10:F100<>"")*(G10:G100<>"")* ((F10:F100=G10:G100)+((F10:F100=1)*(G10:G100=2))+((F10:F100=2)*(G10:G100=1)))) / SUMPRODUCT(--((F10:F100<>"")+(G10:G100<>"")>0)), "")} -> 0.60526316
A7: Semantic FP Loose | C7: =COUNTIF(C33:C57,0) -> 2 | D7: =COUNTIF(D33:D57,0) -> 0 | E7: =COUNTIF(E33:E57,0) -> 0 | F7: =COUNTIF(F33:F57,0) -> 11 | G7: =COUNTIF(G33:G57,0) -> 1 | H7: =COUNTIF(H33:H57,0) -> 1 | J7: XML run 3 | K7: {=IFERROR(SUMPRODUCT((C10:C100<>"")*(H10:H100<>"")*(C10:C100=H10:H100))/SUMPRODUCT(--((C10:C100<>"")+(H10:H100<>"")>0)),"")} -> 0.61290323 | L7: {=IFERROR(SUMPRODUCT((H10:H100<>"")*(D10:D100<>"")*(H10:H100=D10:D100))/SUMPRODUCT(--((H10:H100<>"")+(D10:D100<>"")>0)),"")} -> 0.64516129 | M7: {=IFERROR(SUMPRODUCT((H10:H100<>"")*(E10:E100<>"")*(H10:H100=E10:E100))/SUMPRODUCT(--((H10:H100<>"")+(E10:E100<>"")>0)),"")} -> 0.6875 | N7: {=IFERROR(SUMPRODUCT((F10:F100<>"")*(H10:H100<>"")*(F10:F100=H10:H100))/SUMPRODUCT(--((F10:F100<>"")+(H10:H100<>"")>0)),"")} -> 0.5 | O7: {=IFERROR(SUMPRODUCT((G10:G100<>"")*(H10:H100<>"")*(G10:G100=H10:H100))/SUMPRODUCT(--((G10:G100<>"")+(H10:H100<>"")>0)),"")} -> 0.7 | Q7: XML run 3 | R7: {=IFERROR( SUMPRODUCT((C10:C100<>"")*(H10:H100<>"")* ((C10:C100=H10:H100)+((C10:C100=1)*(H10:H100=2))+((C10:C100=2)*(H10:H100=1)))) / SUMPRODUCT(--((C10:C100<>"")+(H10:H100<>"")>0)), "")} -> 0.70967742 | S7: {=IFERROR( SUMPRODUCT((H10:H100<>"")*(D10:D100<>"")* ((H10:H100=D10:D100)+((H10:H100=1)*(D10:D100=2))+((H10:H100=2)*(D10:D100=1)))) / SUMPRODUCT(--((H10:H100<>"")+(D10:D100<>"")>0)), "")} -> 0.74193548 | T7: {=IFERROR( SUMPRODUCT((H10:H100<>"")*(E10:E100<>"")* ((H10:H100=E10:E100)+((H10:H100=1)*(E10:E100=2))+((H10:H100=2)*(E10:E100=1)))) / SUMPRODUCT(--((H10:H100<>"")+(E10:E100<>"")>0)), "")} -> 0.78125 | U7: {=IFERROR( SUMPRODUCT((F10:F100<>"")*(H10:H100<>"")* ((F10:F100=H10:H100)+((F10:F100=1)*(H10:H100=2))+((F10:F100=2)*(H10:H100=1)))) / SUMPRODUCT(--((F10:F100<>"")+(H10:H100<>"")>0)), "")} -> 0.6 | V7: {=IFERROR( SUMPRODUCT((H10:H100<>"")*(G10:G100<>"")* ((H10:H100=G10:G100)+((H10:H100=1)*(G10:G100=2))+((H10:H100=2)*(G10:G100=1)))) / SUMPRODUCT(--((H10:H100<>"")+(G10:G100<>"")>0)), "")} -> 0.76666667
C9: Chatbot run 1 | D9: Chatbot run 2 | E9: Chatbot run 3 | F9: XML run 1 | G9: XML run 2 | H9: XML run 3
A10: Tasks/Messages/Events | B10: Read Order | C10: 2 | D10: 2 | E10: 2 | F10: 2 | G10: 2 | H10: 2
B11: Select Next Product from Order | C11: 2 | D11: 2 | E11: 2 | F11: 2 | G11: 2 | H11: 2
B12: Check if Product is in Stock | C12: 1 | D12: 2 | E12: 2 | F12: 1 | G12: 2 | H12: 2
B13: Withdraw Product from Warehouse | C13: 2 | D13: 2 | E13: 2 | F13: 2 | G13: 2 | H13: 2
B14: Reorder Product from Wholesaler | C14: 2 | D14: 2 | E14: 2 | F14: 2 | G14: 2 | H14: 2
B15: Product Arrived | C15: 2 | D15: 1 | E15: 2 | F15: 2 | G15: 2 | H15: 2
B16: Register Product | C16: 2 | D16: 2 | E16: 2 | F16: 2 | G16: 2 | H16: 2
B17: Wait for 10 days | C17: 2 | D17: 2 | E17: 2 | F17: 2 | G17: 2 | H17: 2
B18: Demand Delivery Delay Penalty | C18: 2 | D18: 2 | E18: 2 | F18: 2 | G18: 2 | H18: 2
B19: Check if Whole Order is Ready for Shipment | C19: 2 | D19: 2 | E19: 2 | F19: 2 | G19: 2 | H19: 1
B20: Request Courier | C20: 2 | D20: 2 | E20: 2 | F20: 2 | G20: 2 | H20: 2
B21: Pack Products | C21: 2 | D21: 2 | E21: 2 | F21: 2 | G21: 2 | H21: 2
B22: Ship Order | C22: 2 | D22: 2 | E22: 2 | F22: 2 | G22: 2 | H22: 2
A23: Conditions/Loops/Parallel: | B23: Parallel (Request Courier || Pack Products ) | C23: 2 | D23: 2 | E23: 2 | F23: 2 | G23: 2 | H23: 2
B24: Is product in stock? | C24: 2 | D24: 2 | E24: 2 | F24: 2 | G24: 2 | H24: 2
B25: Did Product Arrived before 10 days? | C25: 2 | D25: 2 | E25: 1 | F25: 2 | G25: 2 | H25: 2
B26: Is order ready for shipment? | C26: 2 | D26: 2 | E26: 2 | F26: 2 | G26: 2 | H26: 2
B27: For Each Product from Order Loop | C27: 2 | D27: 2 | E27: 2 | F27: 2 | G27: 2 | H27: 2
A28: Data Objects | B28: Order Management System | C28: 1 | D28: 1 | E28: 1 | F28: 1 | G28: 1 | H28: 1
B29: Order | C29: 2 | D29: 2 | E29: 2 | F29: 2 | G29: 2 | H29: 2
B30: Product | C30: 2 | D30: 2 | E30: 2 | F30: 2 | G30: 2 | H30: 1
B31: Stock Management System | C31: 2 | D31: 2 | E31: 2 | F31: 1 | G31: 2 | H31: 2
A33: False Positives | B33: Courier Request DO | C33: 1
B34: Pool Retailer | C34: 0 | F34: 0
B35: Lane Order and Inventory Management | C35: 0 | F35: 0
B36: Wholesaler Pool | D36: 1 | E36: 1 | F36: 1 | G36: 1 | H36: 1
B37: Warehouse Record DO | D37: 1 | E37: 1
B38: Courier Request DO | D38: 1 | E38: 1
B39: Packed Products DO | D39: 1 | E39: 1
B40: Warehouse Record DO | E40: 1
B41: Storage Management Lane | E41: 1 | H41: 1
B42: Logistics Lane | E42: 1 | H42: 1
B43: Set Delay Exceeded Flag | F43: 0
B44: Delay Flag DO | F44: 0
B45: Product Arrived DO | F45: 0
B46: Inventory Database DO | F46: 0
B47: Warehouse Lane | F47: 1
B48: Stock Management Lane | F48: 0
B49: Packing Logistics Lane | F49: 0
B50: Shipping Lane | F50: 0
B51: Finance Lane | F51: 0
B52: Courier Pool | F52: 1 | H52: 1
B53: Courier Operations Lane | F53: 0
B54: Product Arrived After Penalty | G54: 0
B55: Packing List DO | G55: 1
B56: Second Reorder from Wholesaler | H56: 0
B57: Courier Accepts Request | H57: 1

Sheet c5
A1: Semantic Percision | C1: =SUM(C3:C4) / (C3+ C4+ C7) * 100 -> 100 | D1: =SUM(D3:D4) / (D3+ D4+ D7) * 100 -> 100 | E1: =SUM(E3:E4) / (E3+ E4+ E7) * 100 -> 100 | F1: =SUM(F3:F4) / (F3+ F4+ F7) * 100 -> 100 | G1: =SUM(G3:G4) / (G3+ G4+ G7) * 100 -> 92.857143 | H1: =SUM(H3:H4) / (H3+ H4+ H7) * 100 -> 92.857143 | J1: Jaccard Strict | K1: Chatbot run 1 | L1: Chatbot run 2 | M1: Chatbot run 3 | N1: XML run 1 | O1: XML run 2 | P1: XML run 3 | Q1: Jaccard Loose | R1: Chatbot run 1 | S1: Chatbot run 2 | T1: Chatbot run 3 | U1: XML run 1 | V1: XML run 2 | W1: XML run 3
A2: Semantic Recall | C2: =SUM(C3:C4) / SUM(C3:C5) *100 -> 100 | D2: =SUM(D3:D4) / SUM(D3:D5) *100 -> 100 | E2: =SUM(E3:E4) / SUM(E3:E5) *100 -> 100 | F2: =SUM(F3:F4) / SUM(F3:F5) *100 -> 100 | G2: =SUM(G3:G4) / SUM(G3:G5) *100 -> 100 | H2: =SUM(H3:H4) / SUM(H3:H5) *100 -> 100 | J2: Chatbot run 1 | Q2: Chatbot run 1
A3: Semantic TP Explicit | C3: =COUNTIF(C10:C22, 2) -> 13 | D3: =COUNTIF(D10:D22, 2) -> 13 | E3: =COUNTIF(E10:E22, 2) -> 13 | F3: =COUNTIF(F10:F22, 2) -> 11 | G3: =COUNTIF(G10:G22, 2) -> 13 | H3: =COUNTIF(H10:H22, 2) -> 13 | J3: Chatbot run 2 | K3: {=IFERROR(SUMPRODUCT((C10:C100<>"")*(D10:D100<>"")*(C10:C100=D10:D100))/SUMPRODUCT(--((C10:C100<>"")+(D10:D100<>"")>0)),"")} -> 0.93333333 | Q3: Chatbot run 2 | R3: {=IFERROR( SUMPRODUCT((C10:C100<>"")*(D10:D100<>"")* ((C10:C100=D10:D100)+((C10:C100=1)*(D10:D100=2))+((C10:C100=2)*(D10:D100=1)))) / SUMPRODUCT(--((C10:C100<>"")+(D10:D100<>"")>0)), "")} -> 0.93333333
A4: Semantic TP Implicit | C4: =COUNTIF(C10:C22, 1) -> 0 | D4: =COUNTIF(D10:D22, 1) -> 0 | E4: =COUNTIF(E10:E22, 1) -> 0 | F4: =COUNTIF(F10:F22, 1) -> 2 | G4: =COUNTIF(G10:G22, 1) -> 0 | H4: =COUNTIF(H10:H22, 1) -> 0 | J4: Chatbot run 3 | K4: {=IFERROR(SUMPRODUCT((C10:C100<>"")*(E10:E100<>"")*(C10:C100=E10:E100))/SUMPRODUCT(--((C10:C100<>"")+(E10:E100<>"")>0)),"")} -> 0.93333333 | L4: {=IFERROR(SUMPRODUCT((E10:E100<>"")*(D10:D100<>"")*(E10:E100=D10:D100))/SUMPRODUCT(--((E10:E100<>"")+(D10:D100<>"")>0)),"")} -> 1 | Q4: Chatbot run 3 | R4: {=IFERROR( SUMPRODUCT((C10:C100<>"")*(E10:E100<>"")* ((C10:C100=E10:E100)+((C10:C100=1)*(E10:E100=2))+((C10:C100=2)*(E10:E100=1)))) / SUMPRODUCT(--((C10:C100<>"")+(E10:E100<>"")>0)), "")} -> 0.93333333 | S4: {=IFERROR( SUMPRODUCT((E10:E100<>"")*(D10:D100<>"")* ((E10:E100=D10:D100)+((E10:E100=1)*(D10:D100=2))+((E10:E100=2)*(D10:D100=1)))) / SUMPRODUCT(--((E10:E100<>"")+(D10:D100<>"")>0)), "")} -> 1
A5: Semantic FN | C5: =COUNTIF(C10:C22, 0) -> 0 | D5: =COUNTIF(D10:D22, 0) -> 0 | E5: =COUNTIF(E10:E22, 0) -> 0 | F5: =COUNTIF(F10:F22, 0) -> 0 | G5: =COUNTIF(G10:G22, 0) -> 0 | H5: =COUNTIF(H10:H22, 0) -> 0 | J5: XML run 1 | K5: {=IFERROR(SUMPRODUCT((C10:C100<>"")*(F10:F100<>"")*(C10:C100=F10:F100))/SUMPRODUCT(--((C10:C100<>"")+(F10:F100<>"")>0)),"")} -> 0.73333333 | L5: {=IFERROR(SUMPRODUCT((F10:F100<>"")*(D10:D100<>"")*(F10:F100=D10:D100))/SUMPRODUCT(--((F10:F100<>"")+(D10:D100<>"")>0)),"")} -> 0.6875 | M5: {=IFERROR(SUMPRODUCT((F10:F100<>"")*(E10:E100<>"")*(F10:F100=E10:E100))/SUMPRODUCT(--((F10:F100<>"")+(E10:E100<>"")>0)),"")} -> 0.6875 | Q5: XML run 1 | R5: {=IFERROR( SUMPRODUCT((C10:C100<>"")*(F10:F100<>"")* ((C10:C100=F10:F100)+((C10:C100=1)*(F10:F100=2))+((C10:C100=2)*(F10:F100=1)))) / SUMPRODUCT(--((C10:C100<>"")+(F10:F100<>"")>0)), "")} -> 0.86666667 | S5: {=IFERROR( SUMPRODUCT((F10:F100<>"")*(D10:D100<>"")* ((F10:F100=D10:D100)+((F10:F100=1)*(D10:D100=2))+((F10:F100=2)*(D10:D100=1)))) / SUMPRODUCT(--((F10:F100<>"")+(D10:D100<>"")>0)), "")} -> 0.8125 | T5: {=IFERROR( SUMPRODUCT((F10:F100<>"")*(E10:E100<>"")* ((F10:F100=E10:E100)+((F10:F100=1)*(E10:E100=2))+((F10:F100=2)*(E10:E100=1)))) / SUMPRODUCT(--((F10:F100<>"")+(E10:E100<>"")>0)), "")} -> 0.8125
A6: Semantic FP Strict | C6: =COUNTIF(C24:C29,0) + COUNTIF(C24:C29,1) -> 1 | D6: =COUNTIF(D24:D29,0) + COUNTIF(D24:D29,1) -> 2 | E6: =COUNTIF(E24:E29,0) + COUNTIF(E24:E29,1) -> 2 | F6: =COUNTIF(F24:F29,0) + COUNTIF(F24:F29,1) -> 1 | G6: =COUNTIF(G24:G29,0) + COUNTIF(G24:G29,1) -> 1 | H6: =COUNTIF(H24:H29,0) + COUNTIF(H24:H29,1) -> 2 | J6: XML run 2 | K6: {=IFERROR(SUMPRODUCT((C10:C100<>"")*(G10:G100<>"")*(C10:C100=G10:G100))/SUMPRODUCT(--((C10:C100<>"")+(G10:G100<>"")>0)),"")} -> 0.86666667 | L6: {=SUMPRODUCT((D10:D100<>0)*(G10:G100<>0)) / SUMPRODUCT(((D10:D100<>0)+(G10:G100<>0)>0)*1)} -> 0.86666667 | M6: {=IFERROR(SUMPRODUCT((G10:G100<>"")*(E10:E100<>"")*(G10:G100=E10:E100))/SUMPRODUCT(--((G10:G100<>"")+(E10:E100<>"")>0)),"")} -> 0.8125 | N6: {=IFERROR(SUMPRODUCT((G10:G100<>"")*(F10:F100<>"")*(G10:G100=F10:F100))/SUMPRODUCT(--((G10:G100<>"")+(F10:F100<>"")>0)),"")} -> 0.73333333 | Q6: XML run 2 | R6: {=IFERROR( SUMPRODUCT((C10:C100<>"")*(G10:G100<>"")* ((C10:C100=G10:G100)+((C10:C100=1)*(G10:G100=2))+((C10:C100=2)*(G10:G100=1)))) / SUMPRODUCT(--((C10:C100<>"")+(G10:G100<>"")>0)), "")} -> 0.86666667 | S6: {=IFERROR( SUMPRODUCT((D10:D100<>"")*(G10:G100<>"")* ((D10:D100=G10:G100)+((D10:D100=1)*(G10:G100=2))+((D10:D100=2)*(G10:G100=1)))) / SUMPRODUCT(--((D10:D100<>"")+(G10:G100<>"")>0)), "")} -> 0.8125 | T6: {=IFERROR( SUMPRODUCT((G10:G100<>"")*(E10:E100<>"")* ((G10:G100=E10:E100)+((G10:G100=1)*(E10:E100=2))+((G10:G100=2)*(E10:E100=1)))) / SUMPRODUCT(--((G10:G100<>"")+(E10:E100<>"")>0)), "")} -> 0.8125 | U6: {=IFERROR( SUMPRODUCT((F10:F100<>"")*(G10:G100<>"")* ((F10:F100=G10:G100)+((F10:F100=1)*(G10:G100=2))+((F10:F100=2)*(G10:G100=1)))) / SUMPRODUCT(--((F10:F100<>"")+(G10:G100<>"")>0)), "")} -> 0.86666667
A7: Semantic FP Loose | C7: =COUNTIF(C24:C29,0) -> 0 | D7: =COUNTIF(D24:D29,0) -> 0 | E7: =COUNTIF(E24:E29,0) -> 0 | F7: =COUNTIF(F24:F29,0) -> 0 | G7: =COUNTIF(G24:G29,0) -> 1 | H7: =COUNTIF(H24:H29,0) -> 1 | J7: XML run 3 | K7: {=IFERROR(SUMPRODUCT((C10:C100<>"")*(H10:H100<>"")*(C10:C100=H10:H100))/SUMPRODUCT(--((C10:C100<>"")+(H10:H100<>"")>0)),"")} -> 0.8125 | L7: {=IFERROR(SUMPRODUCT((H10:H100<>"")*(D10:D100<>"")*(H10:H100=D10:D100))/SUMPRODUCT(--((H10:H100<>"")+(D10:D100<>"")>0)),"")} -> 0.76470588 | M7: {=IFERROR(SUMPRODUCT((H10:H100<>"")*(E10:E100<>"")*(H10:H100=E10:E100))/SUMPRODUCT(--((H10:H100<>"")+(E10:E100<>"")>0)),"")} -> 0.76470588 | N7: {=IFERROR(SUMPRODUCT((F10:F100<>"")*(H10:H100<>"")*(F10:F100=H10:H100))/SUMPRODUCT(--((F10:F100<>"")+(H10:H100<>"")>0)),"")} -> 0.6875 | O7: {=IFERROR(SUMPRODUCT((G10:G100<>"")*(H10:H100<>"")*(G10:G100=H10:H100))/SUMPRODUCT(--((G10:G100<>"")+(H10:H100<>"")>0)),"")} -> 0.8125 | Q7: XML run 3 | R7: {=IFERROR( SUMPRODUCT((C10:C100<>"")*(H10:H100<>"")* ((C10:C100=H10:H100)+((C10:C100=1)*(H10:H100=2))+((C10:C100=2)*(H10:H100=1)))) / SUMPRODUCT(--((C10:C100<>"")+(H10:H100<>"")>0)), "")} -> 0.8125 | S7: {=IFERROR( SUMPRODUCT((H10:H100<>"")*(D10:D100<>"")* ((H10:H100=D10:D100)+((H10:H100=1)*(D10:D100=2))+((H10:H100=2)*(D10:D100=1)))) / SUMPRODUCT(--((H10:H100<>"")+(D10:D100<>"")>0)), "")} -> 0.76470588 | T7: {=IFERROR( SUMPRODUCT((H10:H100<>"")*(E10:E100<>"")* ((H10:H100=E10:E100)+((H10:H100=1)*(E10:E100=2))+((H10:H100=2)*(E10:E100=1)))) / SUMPRODUCT(--((H10:H100<>"")+(E10:E100<>"")>0)), "")} -> 0.76470588 | U7: {=IFERROR( SUMPRODUCT((F10:F100<>"")*(H10:H100<>"")* ((F10:F100=H10:H100)+((F10:F100=1)*(H10:H100=2))+((F10:F100=2)*(H10:H100=1)))) / SUMPRODUCT(--((F10:F100<>"")+(H10:H100<>"")>0)), "")} -> 0.8125 | V7: {=IFERROR( SUMPRODUCT((H10:H100<>"")*(G10:G100<>"")* ((H10:H100=G10:G100)+((H10:H100=1)*(G10:G100=2))+((H10:H100=2)*(G10:G100=1)))) / SUMPRODUCT(--((H10:H100<>"")+(G10:G100<>"")>0)), "")} -> 0.8125
C9: Chatbot run 1 | D9: Chatbot run 2 | E9: Chatbot run 3 | F9: XML run 1 | G9: XML run 2 | H9: XML run 3
A10: Pools | B10: Tribunal | C10: 2 | D10: 2 | E10: 2 | F10: 2 | G10: 2 | H10: 2
B11: Owner | C11: 2 | D11: 2 | E11: 2 | F11: 2 | G11: 2 | H11: 2
A12: Tasks/Messages/Events | B12: Receive Compensation Request from Owner | C12: 2 | D12: 2 | E12: 2 | F12: 2 | G12: 2 | H12: 2
B13: Retrieve Premises File | C13: 2 | D13: 2 | E13: 2 | F13: 2 | G13: 2 | H13: 2
B14: Check Request Acceptability and Compliance | C14: 2 | D14: 2 | E14: 2 | F14: 2 | G14: 2 | H14: 2
B15: Allocate Hearing Date | C15: 2 | D15: 2 | E15: 2 | F15: 2 | G15: 2 | H15: 2
B16: Produce / Send Fees Notice | C16: 2 | D16: 2 | E16: 2 | F16: 2 | G16: 2 | H16: 2
B17: Receive Fees Payment | C17: 2 | D17: 2 | E17: 2 | F17: 2 | G17: 2 | H17: 2
B18: Reassess Document Compliance | C18: 2 | D18: 2 | E18: 2 | F18: 2 | G18: 2 | H18: 2
A19: Conditions/Loops/Parallel: | B19: Fees Paid with Request? | C19: 2 | D19: 2 | E19: 2 | F19: 2 | G19: 2 | H19: 2
A20: Data Objects | B20: Compensation Request | C20: 2 | D20: 2 | E20: 2 | F20: 2 | G20: 2 | H20: 2
B21: Premises File | C21: 2 | D21: 2 | E21: 2 | F21: 1 | G21: 2 | H21: 2
B22: Fees Notice | C22: 2 | D22: 2 | E22: 2 | F22: 1 | G22: 2 | H22: 2
A24: False Positives | B24: Pay Fees | C24: 1 | D24: 1 | E24: 1
B25: Payment Record DO | D25: 1 | E25: 1
B26: Prepare Compensation Request | F26: 1
B27: Owner Lane in Tribunal | G27: 0
B28: Premises File Store | H28: 0
B29: Submit compensation request | H29: 1

Sheet c6
A1: Semantic Percision | C1: =SUM(C3:C4) / (C3+ C4+ C7) * 100 -> 100 | D1: =SUM(D3:D4) / (D3+ D4+ D7) * 100 -> 100 | E1: =SUM(E3:E4) / (E3+ E4+ E7) * 100 -> 92.307692 | F1: =SUM(F3:F4) / (F3+ F4+ F7) * 100 -> 72.222222 | G1: =SUM(G3:G4) / (G3+ G4+ G7) * 100 -> 92.857143 | H1: =SUM(H3:H4) / (H3+ H4+ H7) * 100 -> 86.666667 | J1: Jaccard Strict | K1: Chatbot run 1 | L1: Chatbot run 2 | M1: Chatbot run 3 | N1: XML run 1 | O1: XML run 2 | P1: XML run 3 | Q1: Jaccard Loose | R1: Chatbot run 1 | S1: Chatbot run 2 | T1: Chatbot run 3 | U1: XML run 1 | V1: XML run 2 | W1: XML run 3
A2: Semantic Recall | C2: =SUM(C3:C4) / SUM(C3:C5) *100 -> 85.714286 | D2: =SUM(D3:D4) / SUM(D3:D5) *100 -> 85.714286 | E2: =SUM(E3:E4) / SUM(E3:E5) *100 -> 85.714286 | F2: =SUM(F3:F4) / SUM(F3:F5) *100 -> 92.857143 | G2: =SUM(G3:G4) / SUM(G3:G5) *100 -> 92.857143 | H2: =SUM(H3:H4) / SUM(H3:H5) *100 -> 92.857143 | J2: Chatbot run 1 | Q2: Chatbot run 1
A3: Semantic TP Explicit | C3: =COUNTIF(C10:C23, 2) -> 11 | D3: =COUNTIF(D10:D23, 2) -> 11 | E3: =COUNTIF(E10:E23, 2) -> 10 | F3: =COUNTIF(F10:F23, 2) -> 12 | G3: =COUNTIF(G10:G23, 2) -> 12 | H3: =COUNTIF(H10:H23, 2) -> 11 | J3: Chatbot run 2 | K3: {=IFERROR(SUMPRODUCT((C10:C100<>"")*(D10:D100<>"")*(C10:C100=D10:D100))/SUMPRODUCT(--((C10:C100<>"")+(D10:D100<>"")>0)),"")} -> 0.91666667 | Q3: Chatbot run 2 | R3: {=IFERROR( SUMPRODUCT((C10:C100<>"")*(D10:D100<>"")* ((C10:C100=D10:D100)+((C10:C100=1)*(D10:D100=2))+((C10:C100=2)*(D10:D100=1)))) / SUMPRODUCT(--((C10:C100<>"")+(D10:D100<>"")>0)), "")} -> 0.91666667
A4: Semantic TP Implicit | C4: =COUNTIF(C10:C23, 1) -> 1 | D4: =COUNTIF(D10:D23, 1) -> 1 | E4: =COUNTIF(E10:E23, 1) -> 2 | F4: =COUNTIF(F10:F23, 1) -> 1 | G4: =COUNTIF(G10:G23, 1) -> 1 | H4: =COUNTIF(H10:H23, 1) -> 2 | J4: Chatbot run 3 | K4: {=IFERROR(SUMPRODUCT((C10:C100<>"")*(E10:E100<>"")*(C10:C100=E10:E100))/SUMPRODUCT(--((C10:C100<>"")+(E10:E100<>"")>0)),"")} -> 0.88 | L4: {=IFERROR(SUMPRODUCT((E10:E100<>"")*(D10:D100<>"")*(E10:E100=D10:D100))/SUMPRODUCT(--((E10:E100<>"")+(D10:D100<>"")>0)),"")} -> 0.80769231 | Q4: Chatbot run 3 | R4: {=IFERROR( SUMPRODUCT((C10:C100<>"")*(E10:E100<>"")* ((C10:C100=E10:E100)+((C10:C100=1)*(E10:E100=2))+((C10:C100=2)*(E10:E100=1)))) / SUMPRODUCT(--((C10:C100<>"")+(E10:E100<>"")>0)), "")} -> 0.92 | S4: {=IFERROR( SUMPRODUCT((E10:E100<>"")*(D10:D100<>"")* ((E10:E100=D10:D100)+((E10:E100=1)*(D10:D100=2))+((E10:E100=2)*(D10:D100=1)))) / SUMPRODUCT(--((E10:E100<>"")+(D10:D100<>"")>0)), "")} -> 0.84615385
A5: Semantic FN | C5: =COUNTIF(C10:C23, 0) -> 2 | D5: =COUNTIF(D10:D23, 0) -> 2 | E5: =COUNTIF(E10:E23, 0) -> 2 | F5: =COUNTIF(F10:F23, 0) -> 1 | G5: =COUNTIF(G10:G23, 0) -> 1 | H5: =COUNTIF(H10:H23, 0) -> 1 | J5: XML run 1 | K5: {=IFERROR(SUMPRODUCT((C10:C100<>"")*(F10:F100<>"")*(C10:C100=F10:F100))/SUMPRODUCT(--((C10:C100<>"")+(F10:F100<>"")>0)),"")} -> 0.35416667 | L5: {=IFERROR(SUMPRODUCT((F10:F100<>"")*(D10:D100<>"")*(F10:F100=D10:D100))/SUMPRODUCT(--((F10:F100<>"")+(D10:D100<>"")>0)),"")} -> 0.32653061 | M5: {=IFERROR(SUMPRODUCT((F10:F100<>"")*(E10:E100<>"")*(F10:F100=E10:E100))/SUMPRODUCT(--((F10:F100<>"")+(E10:E100<>"")>0)),"")} -> 0.3877551 | Q5: XML run 1 | R5: {=IFERROR( SUMPRODUCT((C10:C100<>"")*(F10:F100<>"")* ((C10:C100=F10:F100)+((C10:C100=1)*(F10:F100=2))+((C10:C100=2)*(F10:F100=1)))) / SUMPRODUCT(--((C10:C100<>"")+(F10:F100<>"")>0)), "")} -> 0.39583333 | S5: {=IFERROR( SUMPRODUCT((F10:F100<>"")*(D10:D100<>"")* ((F10:F100=D10:D100)+((F10:F100=1)*(D10:D100=2))+((F10:F100=2)*(D10:D100=1)))) / SUMPRODUCT(--((F10:F100<>"")+(D10:D100<>"")>0)), "")} -> 0.36734694 | T5: {=IFERROR( SUMPRODUCT((F10:F100<>"")*(E10:E100<>"")* ((F10:F100=E10:E100)+((F10:F100=1)*(E10:E100=2))+((F10:F100=2)*(E10:E100=1)))) / SUMPRODUCT(--((F10:F100<>"")+(E10:E100<>"")>0)), "")} -> 0.40816327
A6: Semantic FP Strict | C6: =COUNTIF(C25:C67,0) + COUNTIF(C25:C67,1) -> 9 | D6: =COUNTIF(D25:D67,0) + COUNTIF(D25:D67,1) -> 9 | E6: =COUNTIF(E25:E67,0) + COUNTIF(E25:E67,1) -> 11 | F6: =COUNTIF(F25:F67,0) + COUNTIF(F25:F67,1) -> 31 | G6: =COUNTIF(G25:G67,0) + COUNTIF(G25:G67,1) -> 13 | H6: =COUNTIF(H25:H67,0) + COUNTIF(H25:H67,1) -> 15 | J6: XML run 2 | K6: {=IFERROR(SUMPRODUCT((C10:C100<>"")*(G10:G100<>"")*(C10:C100=G10:G100))/SUMPRODUCT(--((C10:C100<>"")+(G10:G100<>"")>0)),"")} -> 0.34285714 | L6: {=SUMPRODUCT((D10:D100<>0)*(G10:G100<>0)) / SUMPRODUCT(((D10:D100<>0)+(G10:G100<>0)>0)*1)} -> 0.39393939 | M6: {=IFERROR(SUMPRODUCT((G10:G100<>"")*(E10:E100<>"")*(G10:G100=E10:E100))/SUMPRODUCT(--((G10:G100<>"")+(E10:E100<>"")>0)),"")} -> 0.35135135 | N6: {=IFERROR(SUMPRODUCT((G10:G100<>"")*(F10:F100<>"")*(G10:G100=F10:F100))/SUMPRODUCT(--((G10:G100<>"")+(F10:F100<>"")>0)),"")} -> 0.5 | Q6: XML run 2 | R6: {=IFERROR( SUMPRODUCT((C10:C100<>"")*(G10:G100<>"")* ((C10:C100=G10:G100)+((C10:C100=1)*(G10:G100=2))+((C10:C100=2)*(G10:G100=1)))) / SUMPRODUCT(--((C10:C100<>"")+(G10:G100<>"")>0)), "")} -> 0.4 | S6: {=IFERROR( SUMPRODUCT((D10:D100<>"")*(G10:G100<>"")* ((D10:D100=G10:G100)+((D10:D100=1)*(G10:G100=2))+((D10:D100=2)*(G10:G100=1)))) / SUMPRODUCT(--((D10:D100<>"")+(G10:G100<>"")>0)), "")} -> 0.4 | T6: {=IFERROR( SUMPRODUCT((G10:G100<>"")*(E10:E100<>"")* ((G10:G100=E10:E100)+((G10:G100=1)*(E10:E100=2))+((G10:G100=2)*(E10:E100=1)))) / SUMPRODUCT(--((G10:G100<>"")+(E10:E100<>"")>0)), "")} -> 0.37837838 | U6: {=IFERROR( SUMPRODUCT((F10:F100<>"")*(G10:G100<>"")* ((F10:F100=G10:G100)+((F10:F100=1)*(G10:G100=2))+((F10:F100=2)*(G10:G100=1)))) / SUMPRODUCT(--((F10:F100<>"")+(G10:G100<>"")>0)), "")} -> 0.5
A7: Semantic FP Loose | C7: =COUNTIF(C25:C67,0) -> 0 | D7: =COUNTIF(D25:D67,0) -> 0 | E7: =COUNTIF(E25:E67,0) -> 1 | F7: =COUNTIF(F25:F67,0) -> 5 | G7: =COUNTIF(G25:G67,0) -> 1 | H7: =COUNTIF(H25:H67,0) -> 2 | J7: XML run 3 | K7: {=IFERROR(SUMPRODUCT((C10:C100<>"")*(H10:H100<>"")*(C10:C100=H10:H100))/SUMPRODUCT(--((C10:C100<>"")+(H10:H100<>"")>0)),"")} -> 0.4 | L7: {=IFERROR(SUMPRODUCT((H10:H100<>"")*(D10:D100<>"")*(H10:H100=D10:D100))/SUMPRODUCT(--((H10:H100<>"")+(D10:D100<>"")>0)),"")} -> 0.4 | M7: {=IFERROR(SUMPRODUCT((H10:H100<>"")*(E10:E100<>"")*(H10:H100=E10:E100))/SUMPRODUCT(--((H10:H100<>"")+(E10:E100<>"")>0)),"")} -> 0.40540541 | N7: {=IFERROR(SUMPRODUCT((F10:F100<>"")*(H10:H100<>"")*(F10:F100=H10:H100))/SUMPRODUCT(--((F10:F100<>"")+(H10:H100<>"")>0)),"")} -> 0.46 | O7: {=IFERROR(SUMPRODUCT((G10:G100<>"")*(H10:H100<>"")*(G10:G100=H10:H100))/SUMPRODUCT(--((G10:G100<>"")+(H10:H100<>"")>0)),"")} -> 0.48648649 | Q7: XML run 3 | R7: {=IFERROR( SUMPRODUCT((C10:C100<>"")*(H10:H100<>"")* ((C10:C100=H10:H100)+((C10:C100=1)*(H10:H100=2))+((C10:C100=2)*(H10:H100=1)))) / SUMPRODUCT(--((C10:C100<>"")+(H10:H100<>"")>0)), "")} -> 0.45714286 | S7: {=IFERROR( SUMPRODUCT((H10:H100<>"")*(D10:D100<>"")* ((H10:H100=D10:D100)+((H10:H100=1)*(D10:D100=2))+((H10:H100=2)*(D10:D100=1)))) / SUMPRODUCT(--((H10:H100<>"")+(D10:D100<>"")>0)), "")} -> 0.45714286 | T7: {=IFERROR( SUMPRODUCT((H10:H100<>"")*(E10:E100<>"")* ((H10:H100=E10:E100)+((H10:H100=1)*(E10:E100=2))+((H10:H100=2)*(E10:E100=1)))) / SUMPRODUCT(--((H10:H100<>"")+(E10:E100<>"")>0)), "")} -> 0.43243243 | U7: {=IFERROR( SUMPRODUCT((F10:F100<>"")*(H10:H100<>"")* ((F10:F100=H10:H100)+((F10:F100=1)*(H10:H100=2))+((F10:F100=2)*(H10:H100=1)))) / SUMPRODUCT(--((F10:F100<>"")+(H10:H100<>"")>0)), "")} -> 0.48 | V7: {=IFERROR( SUMPRODUCT((H10:H100<>"")*(G10:G100<>"")* ((H10:H100=G10:G100)+((H10:H100=1)*(G10:G100=2))+((H10:H100=2)*(G10:G100=1)))) / SUMPRODUCT(--((H10:H100<>"")+(G10:G100<>"")>0)), "")} -> 0.51351351
C9: Chatbot run 1 | D9: Chatbot run 2 | E9: Chatbot run 3 | F9: XML run 1 | G9: XML run 2 | H9: XML run 3
A10: Tasks/Messages/Events | B10: Select Course to register | C10: 0 | D10: 0 | E10: 0 | F10: 2 | G10: 2 | H10: 1
B11: View Available Courses and Dates from System | C11: 2 | D11: 2 | E11: 1 | F11: 1 | G11: 1 | H11: 1
B12: Select Course and Date | C12: 2 | D12: 2 | E12: 2 | F12: 2 | G12: 2 | H12: 2
B13: Register Account | C13: 2 | D13: 2 | E13: 2 | F13: 2 | G13: 2 | H13: 2
B14: Request Activation | C14: 2 | D14: 2 | E14: 2 | F14: 2 | G14: 2 | H14: 2
B15: Receive Activation Response | C15: 1 | D15: 1 | E15: 1 | F15: 2 | G15: 2 | H15: 2
B16: Log Into Account | C16: 2 | D16: 2 | E16: 2 | F16: 2 | G16: 2 | H16: 2
B17: Tweet to Friends | C17: 2 | D17: 2 | E17: 2 | F17: 2 | G17: 2 | H17: 2
B18: Complete Course Registration | C18: 2 | D18: 2 | E18: 2 | F18: 2 | G18: 2 | H18: 2
B19: Provide Payment Information | C19: 2 | D19: 2 | E19: 2 | F19: 2 | G19: 2 | H19: 2
B20: Receive Course Ticket | C20: 2 | D20: 2 | E20: 2 | F20: 2 | G20: 2 | H20: 2
A21: Conditions/Loops/Parallel | B21: Are Slots Free? | C21: 0 | D21: 0 | E21: 0 | F21: 0 | G21: 0 | H21: 0
B22: Have an Account? | C22: 2 | D22: 2 | E22: 2 | F22: 2 | G22: 2 | H22: 2
B23: Is Registered at Eligible University? | C23: 2 | D23: 2 | E23: 2 | F23: 2 | G23: 2 | H23: 2
A25: False Positives | B25: Wait for Activation Response | C25: 1 | D25: 1 | E25: 1
B26: Course List DO | C26: 1 | E26: 1 | F26: 1
B27: Selected Course DO | C27: 1 | D27: 1 | E27: 1 | H27: 1
B28: Account DO | C28: 1 | D28: 1 | E28: 1 | F28: 1 | H28: 1
B29: University Registeration DO | C29: 1 | D29: 1 | E29: 1
B30: Activation Request DO | C30: 1 | D30: 1 | E30: 1 | F30: 1
B31: Payment Info DO | C31: 1 | D31: 1 | E31: 1 | F31: 1
B32: Course TicketDO | C32: 1 | D32: 1 | E32: 1 | F32: 1
B33: Applicant Pool/Lane | C33: 1 | D33: 1 | E33: 1 | F33: 1 | G33: 1 | H33: 1
B34: Course Registeration | D34: 1
B35: Check Account Existence | E35: 0 | F35: 0
B36: Activation Response | E36: 1
B37: Request Available Courses | F37: 1 | G37: 1
B38: Receive Available Courses | F38: 1 | G38: 1
B39: Check University Eligibility | F39: 0
B40: University Eligibility DO | F40: 1
B41: Send Registration Request | F41: 1
B42: User lane | F42: 1 | G42: 1
B43: Twitter lane | F43: 0
B44: Sports Institute Pool | F44: 1 | H44: 1
B45: Registration System Lane | F45: 1
B46: Administration Lane in Sport Institute | F46: 0
B47: Wait for Applicant Message | F47: 1
B48: Receive Request for Courses | F48: 1
B49: Check Available Course Slots | F49: 1 | G49: 1 | H49: 1
B50: Send Courses Dates | F50: 1 | H50: 1
B51: Course Slots Database | F51: 1 | H51: 1
B52: Receive Registration Request | F52: 1 | G52: 1
B53: Receive Activation Request | F53: 1 | G53: 1 | H53: 1
B54: Admin Reviews Activation Request | F54: 0
B55: Process Registration Request | F55: 1 | H55: 1
B56: Send Activation Response | F56: 1 | G56: 1
B57: Registration Request DO | F57: 1
B58: Save Registration | F58: 1
B59: Generate Course Ticket | F59: 1 | G59: 1 | H59: 1
B60: Send Course Ticket | F60: 1 | G60: 1 | H60: 1
B61: Sports Institute lane | G61: 0
B62: Create Account | G62: 1
B63: Proceed to Registration | G63: 1
B64: Course Management lane | H64: 1
B65: Account Services Lane | H65: 0
B66: Receive Course Info Request | H66: 1
B67: Validate Payment | H67: 0

Sheet c7
A1: Semantic Percision | C1: =SUM(C3:C4) / (C3+ C4+ C7) * 100 -> 100 | D1: =SUM(D3:D4) / (D3+ D4+ D7) * 100 -> 100 | E1: =SUM(E3:E4) / (E3+ E4+ E7) * 100 -> 96.296296 | F1: =SUM(F3:F4) / (F3+ F4+ F7) * 100 -> 95.652174 | G1: =SUM(G3:G4) / (G3+ G4+ G7) * 100 -> 100 | H1: =SUM(H3:H4) / (H3+ H4+ H7) * 100 -> 100 | J1: Jaccard Strict | K1: Chatbot run 1 | L1: Chatbot run 2 | M1: Chatbot run 3 | N1: XML run 1 | O1: XML run 2 | P1: XML run 3 | Q1: Jaccard Loose | R1: Chatbot run 1 | S1: Chatbot run 2 | T1: Chatbot run 3 | U1: XML run 1 | V1: XML run 2 | W1: XML run 3
A2: Semantic Recall | C2: =SUM(C3:C4) / SUM(C3:C5) *100 -> 96.428571 | D2: =SUM(D3:D4) / SUM(D3:D5) *100 -> 96.428571 | E2: =SUM(E3:E4) / SUM(E3:E5) *100 -> 92.857143 | F2: =SUM(F3:F4) / SUM(F3:F5) *100 -> 78.571429 | G2: =SUM(G3:G4) / SUM(G3:G5) *100 -> 67.857143 | H2: =SUM(H3:H4) / SUM(H3:H5) *100 -> 75 | J2: Chatbot run 1 | Q2: Chatbot run 1
A3: Semantic TP Explicit | C3: =COUNTIF(C10:C37, 2) -> 23 | D3: =COUNTIF(D10:D37, 2) -> 22 | E3: =COUNTIF(E10:E37, 2) -> 21 | F3: =COUNTIF(F10:F37, 2) -> 19 | G3: =COUNTIF(G10:G37, 2) -> 14 | H3: =COUNTIF(H10:H37, 2) -> 16 | J3: Chatbot run 2 | K3: {=IFERROR(SUMPRODUCT((C10:C100<>"")*(D10:D100<>"")*(C10:C100=D10:D100))/SUMPRODUCT(--((C10:C100<>"")+(D10:D100<>"")>0)),"")} -> 0.61702128 | Q3: Chatbot run 2 | R3: {=IFERROR( SUMPRODUCT((C10:C100<>"")*(D10:D100<>"")* ((C10:C100=D10:D100)+((C10:C100=1)*(D10:D100=2))+((C10:C100=2)*(D10:D100=1)))) / SUMPRODUCT(--((C10:C100<>"")+(D10:D100<>"")>0)), "")} -> 0.68085106
A4: Semantic TP Implicit | C4: =COUNTIF(C10:C37, 1) -> 4 | D4: =COUNTIF(D10:D37, 1) -> 5 | E4: =COUNTIF(E10:E37, 1) -> 5 | F4: =COUNTIF(F10:F37, 1) -> 3 | G4: =COUNTIF(G10:G37, 1) -> 5 | H4: =COUNTIF(H10:H37, 1) -> 5 | J4: Chatbot run 3 | K4: {=IFERROR(SUMPRODUCT((C10:C100<>"")*(E10:E100<>"")*(C10:C100=E10:E100))/SUMPRODUCT(--((C10:C100<>"")+(E10:E100<>"")>0)),"")} -> 0.65306122 | L4: {=IFERROR(SUMPRODUCT((E10:E100<>"")*(D10:D100<>"")*(E10:E100=D10:D100))/SUMPRODUCT(--((E10:E100<>"")+(D10:D100<>"")>0)),"")} -> 0.66666667 | Q4: Chatbot run 3 | R4: {=IFERROR( SUMPRODUCT((C10:C100<>"")*(E10:E100<>"")* ((C10:C100=E10:E100)+((C10:C100=1)*(E10:E100=2))+((C10:C100=2)*(E10:E100=1)))) / SUMPRODUCT(--((C10:C100<>"")+(E10:E100<>"")>0)), "")} -> 0.69387755 | S4: {=IFERROR( SUMPRODUCT((E10:E100<>"")*(D10:D100<>"")* ((E10:E100=D10:D100)+((E10:E100=1)*(D10:D100=2))+((E10:E100=2)*(D10:D100=1)))) / SUMPRODUCT(--((E10:E100<>"")+(D10:D100<>"")>0)), "")} -> 0.70833333
A5: Semantic FN | C5: =COUNTIF(C10:C37, 0) -> 1 | D5: =COUNTIF(D10:D37, 0) -> 1 | E5: =COUNTIF(E10:E37, 0) -> 2 | F5: =COUNTIF(F10:F37, 0) -> 6 | G5: =COUNTIF(G10:G37, 0) -> 9 | H5: =COUNTIF(H10:H37, 0) -> 7 | J5: XML run 1 | K5: {=IFERROR(SUMPRODUCT((C10:C100<>"")*(F10:F100<>"")*(C10:C100=F10:F100))/SUMPRODUCT(--((C10:C100<>"")+(F10:F100<>"")>0)),"")} -> 0.54545455 | L5: {=IFERROR(SUMPRODUCT((F10:F100<>"")*(D10:D100<>"")*(F10:F100=D10:D100))/SUMPRODUCT(--((F10:F100<>"")+(D10:D100<>"")>0)),"")} -> 0.46666667 | M5: {=IFERROR(SUMPRODUCT((F10:F100<>"")*(E10:E100<>"")*(F10:F100=E10:E100))/SUMPRODUCT(--((F10:F100<>"")+(E10:E100<>"")>0)),"")} -> 0.46938776 | Q5: XML run 1 | R5: {=IFERROR( SUMPRODUCT((C10:C100<>"")*(F10:F100<>"")* ((C10:C100=F10:F100)+((C10:C100=1)*(F10:F100=2))+((C10:C100=2)*(F10:F100=1)))) / SUMPRODUCT(--((C10:C100<>"")+(F10:F100<>"")>0)), "")} -> 0.61363636 | S5: {=IFERROR( SUMPRODUCT((F10:F100<>"")*(D10:D100<>"")* ((F10:F100=D10:D100)+((F10:F100=1)*(D10:D100=2))+((F10:F100=2)*(D10:D100=1)))) / SUMPRODUCT(--((F10:F100<>"")+(D10:D100<>"")>0)), "")} -> 0.55555556 | T5: {=IFERROR( SUMPRODUCT((F10:F100<>"")*(E10:E100<>"")* ((F10:F100=E10:E100)+((F10:F100=1)*(E10:E100=2))+((F10:F100=2)*(E10:E100=1)))) / SUMPRODUCT(--((F10:F100<>"")+(E10:E100<>"")>0)), "")} -> 0.55102041
A6: Semantic FP Strict | C6: =COUNTIF(C39:C68,0) + COUNTIF(C39:C68,1) -> 12 | D6: =COUNTIF(D39:D68,0) + COUNTIF(D39:D68,1) -> 11 | E6: =COUNTIF(E39:E68,0) + COUNTIF(E39:E68,1) -> 16 | F6: =COUNTIF(F39:F68,0) + COUNTIF(F39:F68,1) -> 8 | G6: =COUNTIF(G39:G68,0) + COUNTIF(G39:G68,1) -> 0 | H6: =COUNTIF(H39:H68,0) + COUNTIF(H39:H68,1) -> 7 | J6: XML run 2 | K6: {=IFERROR(SUMPRODUCT((C10:C100<>"")*(G10:G100<>"")*(C10:C100=G10:G100))/SUMPRODUCT(--((C10:C100<>"")+(G10:G100<>"")>0)),"")} -> 0.425 | L6: {=SUMPRODUCT((D10:D100<>0)*(G10:G100<>0)) / SUMPRODUCT(((D10:D100<>0)+(G10:G100<>0)>0)*1)} -> 0.5 | M6: {=IFERROR(SUMPRODUCT((G10:G100<>"")*(E10:E100<>"")*(G10:G100=E10:E100))/SUMPRODUCT(--((G10:G100<>"")+(E10:E100<>"")>0)),"")} -> 0.43181818 | N6: {=IFERROR(SUMPRODUCT((G10:G100<>"")*(F10:F100<>"")*(G10:G100=F10:F100))/SUMPRODUCT(--((G10:G100<>"")+(F10:F100<>"")>0)),"")} -> 0.55555556 | Q6: XML run 2 | R6: {=IFERROR( SUMPRODUCT((C10:C100<>"")*(G10:G100<>"")* ((C10:C100=G10:G100)+((C10:C100=1)*(G10:G100=2))+((C10:C100=2)*(G10:G100=1)))) / SUMPRODUCT(--((C10:C100<>"")+(G10:G100<>"")>0)), "")} -> 0.5 | S6: {=IFERROR( SUMPRODUCT((D10:D100<>"")*(G10:G100<>"")* ((D10:D100=G10:G100)+((D10:D100=1)*(G10:G100=2))+((D10:D100=2)*(G10:G100=1)))) / SUMPRODUCT(--((D10:D100<>"")+(G10:G100<>"")>0)), "")} -> 0.51282051 | T6: {=IFERROR( SUMPRODUCT((G10:G100<>"")*(E10:E100<>"")* ((G10:G100=E10:E100)+((G10:G100=1)*(E10:E100=2))+((G10:G100=2)*(E10:E100=1)))) / SUMPRODUCT(--((G10:G100<>"")+(E10:E100<>"")>0)), "")} -> 0.47727273 | U6: {=IFERROR( SUMPRODUCT((F10:F100<>"")*(G10:G100<>"")* ((F10:F100=G10:G100)+((F10:F100=1)*(G10:G100=2))+((F10:F100=2)*(G10:G100=1)))) / SUMPRODUCT(--((F10:F100<>"")+(G10:G100<>"")>0)), "")} -> 0.63888889
A7: Semantic FP Loose | C7: =COUNTIF(C39:C68,0) -> 0 | D7: =COUNTIF(D39:D68,0) -> 0 | E7: =COUNTIF(E39:E68,0) -> 1 | F7: =COUNTIF(F39:F68,0) -> 1 | G7: =COUNTIF(G39:G68,0) -> 0 | H7: =COUNTIF(H39:H68,0) -> 0 | J7: XML run 3 | K7: {=IFERROR(SUMPRODUCT((C10:C100<>"")*(H10:H100<>"")*(C10:C100=H10:H100))/SUMPRODUCT(--((C10:C100<>"")+(H10:H100<>"")>0)),"")} -> 0.47727273 | L7: {=IFERROR(SUMPRODUCT((H10:H100<>"")*(D10:D100<>"")*(H10:H100=D10:D100))/SUMPRODUCT(--((H10:H100<>"")+(D10:D100<>"")>0)),"")} -> 0.52380952 | M7: {=IFERROR(SUMPRODUCT((H10:H100<>"")*(E10:E100<>"")*(H10:H100=E10:E100))/SUMPRODUCT(--((H10:H100<>"")+(E10:E100<>"")>0)),"")} -> 0.45833333 | N7: {=IFERROR(SUMPRODUCT((F10:F100<>"")*(H10:H100<>"")*(F10:F100=H10:H100))/SUMPRODUCT(--((F10:F100<>"")+(H10:H100<>"")>0)),"")} -> 0.56097561 | O7: {=IFERROR(SUMPRODUCT((G10:G100<>"")*(H10:H100<>"")*(G10:G100=H10:H100))/SUMPRODUCT(--((G10:G100<>"")+(H10:H100<>"")>0)),"")} -> 0.6 | Q7: XML run 3 | R7: {=IFERROR( SUMPRODUCT((C10:C100<>"")*(H10:H100<>"")* ((C10:C100=H10:H100)+((C10:C100=1)*(H10:H100=2))+((C10:C100=2)*(H10:H100=1)))) / SUMPRODUCT(--((C10:C100<>"")+(H10:H100<>"")>0)), "")} -> 0.56818182 | S7: {=IFERROR( SUMPRODUCT((H10:H100<>"")*(D10:D100<>"")* ((H10:H100=D10:D100)+((H10:H100=1)*(D10:D100=2))+((H10:H100=2)*(D10:D100=1)))) / SUMPRODUCT(--((H10:H100<>"")+(D10:D100<>"")>0)), "")} -> 0.61904762 | T7: {=IFERROR( SUMPRODUCT((H10:H100<>"")*(E10:E100<>"")* ((H10:H100=E10:E100)+((H10:H100=1)*(E10:E100=2))+((H10:H100=2)*(E10:E100=1)))) / SUMPRODUCT(--((H10:H100<>"")+(E10:E100<>"")>0)), "")} -> 0.54166667 | U7: {=IFERROR( SUMPRODUCT((F10:F100<>"")*(H10:H100<>"")* ((F10:F100=H10:H100)+((F10:F100=1)*(H10:H100=2))+((F10:F100=2)*(H10:H100=1)))) / SUMPRODUCT(--((F10:F100<>"")+(H10:H100<>"")>0)), "")} -> 0.6097561 | V7: {=IFERROR( SUMPRODUCT((H10:H100<>"")*(G10:G100<>"")* ((H10:H100=G10:G100)+((H10:H100=1)*(G10:G100=2))+((H10:H100=2)*(G10:G100=1)))) / SUMPRODUCT(--((H10:H100<>"")+(G10:G100<>"")>0)), "")} -> 0.68571429
C9: Chatbot run 1 | D9: Chatbot run 2 | E9: Chatbot run 3 | F9: XML run 1 | G9: XML run 2 | H9: XML run 3
A10: Pools | B10: Police App | C10: 2 | D10: 2 | E10: 2 | F10: 2 | G10: 2 | H10: 2
B11: Car Owner | C11: 2 | D11: 2 | E11: 2 | F11: 2 | G11: 0 | H11: 0
B12: Car Service Facility | C12: 2 | D12: 2 | E12: 2 | F12: 2 | G12: 2 | H12: 0
A13: Lanes | B13: Mechanic | C13: 2 | D13: 2 | E13: 2 | F13: 2 | G13: 2 | H13: 2
A14: Tasks/Messages/Events | B14: Receive Successful Service Notification | C14: 2 | D14: 2 | E14: 2 | F14: 1 | G14: 1 | H14: 1
B15: Time for Necessary Service | C15: 2 | D15: 2 | E15: 2 | F15: 2 | G15: 2 | H15: 2
B16: Check Car Registration | C16: 2 | D16: 2 | E16: 2 | F16: 2 | G16: 2 | H16: 2
B17: Send Notification to Owner | C17: 2 | D17: 2 | E17: 2 | F17: 2 | G17: 2 | H17: 2
B18: Receive Going to Service Confirmation | C18: 1 | D18: 1 | E18: 1 | F18: 2 | G18: 0 | H18: 2
B19: Wait 30 days | C19: 2 | D19: 2 | E19: 2 | F19: 2 | G19: 2 | H19: 2
B20: Send Fine to Owner | C20: 2 | D20: 2 | E20: 2 | F20: 1 | G20: 2 | H20: 2
B21: Receive Notification from Police App | C21: 2 | D21: 2 | E21: 2 | F21: 2 | G21: 0 | H21: 2
B22: Go to Service Facility | C22: 2 | D22: 2 | E22: 1 | F22: 2 | G22: 1 | H22: 2
B23: Pay Fine | C23: 1 | D23: 2 | E23: 0 | F23: 0 | G23: 0 | H23: 0
B24: Pay through App | C24: 1 | D24: 1 | E24: 1 | F24: 0 | G24: 1 | H24: 1
B25: Get Pickerl | C25: 1 | D25: 1 | E25: 1 | F25: 1 | G25: 1 | H25: 1
B26: Receive Car for Service | C26: 2 | D26: 1 | E26: 2 | F26: 2 | G26: 2 | H26: 2
... B33: Notify Police App of Service Success | C33: 2 | D33: 2 | E33: 2 | F33: 0 | G33: 0 | H33: 0
A34: Conditions/Loops/Parallel: | B34: Is Car Registered? | C34: 2 | D34: 2 | E34: 2 | F34: 2 | G34: 1 | H34: 2
B35: Did owner go to service? | C35: 2 | D35: 2 | E35: 2 | F35: 2 | G35: 0 | H35: 0
B36: Send Status Loop | C36: 2 | D36: 2 | E36: 2 | F36: 0 | G36: 0 | H36: 0
B37: Parallel ( Send Status || Repair Car ) | C37: 0 | D37: 0 | E37: 0 | F37: 0 | G37: 0 | H37: 0
A39: False Positives | B39: Create Notification | C39: 1
B40: Create/Issue Fine | C40: 1 | D40: 1 | E40: 1
B41: Service Reminder DO | C41: 1 | F41: 1
B42: Car Registration Database DO | C42: 1 | D42: 1 | E42: 1 | H42: 1
B43: Notification DO | C43: 1 | E43: 1
B44: Fine DO | C44: 1 | E44: 1 | F44: 1
B45: Payment DO | C45: 1 | E45: 1
B46: Service Report DO | C46: 1
B47: Car Problems DO | C47: 1 | D47: 1 | E47: 1 | H47: 1
B48: Status Update DO | C48: 1
B49: Pickerl DO | C49: 1 | E49: 1 | F49: 1
B50: Next Service Date DO | C50: 1 | D50: 1 | F50: 1 | H50: 1
B51: Customer Service Lane | D51: 1 | E51: 1
B52: Service Reminder DO | D52: 1 | E52: 1
B53: Fine Notice DO | D53: 1
B54: Payment Confirmation DO | D54: 1
B55: Repair Status DO | D55: 1 | E55: 1 | F55: 1 | H55: 1
B56: Service Completion DO | D56: 1
B57: Update Repair Status | D57: 1 | E57: 1
B58: Double Notify Car Owner Task and Event | E58: 0
B59: Service Confirmation DO | E59: 1
B60: Service Request DO | E60: 1
B61: Service Success DO | E61: 1
B62: Send Service Request to Mechanic | E62: 1
B63: Fines Department Lane | F63: 0
B64: Registration Record DO | F64: 1
B65: Problem Report DO | F65: 1
B66: Wait During Repair | H66: 1
B67: Inform Service Visit | H67: 1
B68: Repair Complete E | H68: 1

Sheet c8
A1: Semantic Percision | C1: =SUM(C3:C4) / (C3+ C4+ C7) * 100 -> 96.551724 | D1: =SUM(D3:D4) / (D3+ D4+ D7) * 100 -> 92 | E1: =SUM(E3:E4) / (E3+ E4+ E7) * 100 -> 96.551724 | F1: =SUM(F3:F4) / (F3+ F4+ F7) * 100 -> 82.857143 | G1: =SUM(G3:G4) / (G3+ G4+ G7) * 100 -> 96.774194 | H1: =SUM(H3:H4) / (H3+ H4+ H7) * 100 -> 87.878788 | J1: Jaccard Strict | K1: Chatbot run 1 | L1: Chatbot run 2 | M1: Chatbot run 3 | N1: XML run 1 | O1: XML run 2 | P1: XML run 3 | Q1: Jaccard Loose | R1: Chatbot run 1 | S1: Chatbot run 2 | T1: Chatbot run 3 | U1: XML run 1 | V1: XML run 2 | W1: XML run 3
A2: Semantic Recall | C2: =SUM(C3:C4) / SUM(C3:C5) *100 -> 93.333333 | D2: =SUM(D3:D4) / SUM(D3:D5) *100 -> 76.666667 | E2: =SUM(E3:E4) / SUM(E3:E5) *100 -> 93.333333 | F2: =SUM(F3:F4) / SUM(F3:F5) *100 -> 96.666667 | G2: =SUM(G3:G4) / SUM(G3:G5) *100 -> 100 | H2: =SUM(H3:H4) / SUM(H3:H5) *100 -> 96.666667 | J2: Chatbot run 1 | Q2: Chatbot run 1
A3: Semantic TP Explicit | C3: =COUNTIF(C10:C39, 2) -> 28 | D3: =COUNTIF(D10:D39, 2) -> 22 | E3: =COUNTIF(E10:E39, 2) -> 23 | F3: =COUNTIF(F10:F39, 2) -> 28 | G3: =COUNTIF(G10:G39, 2) -> 22 | H3: =COUNTIF(H10:H39, 2) -> 19 | J3: Chatbot run 2 | K3: {=IFERROR(SUMPRODUCT((C10:C100<>"")*(D10:D100<>"")*(C10:C100=D10:D100))/SUMPRODUCT(--((C10:C100<>"")+(D10:D100<>"")>0)),"")} -> 0.59090909 | Q3: Chatbot run 2 | R3: {=IFERROR( SUMPRODUCT((C10:C100<>"")*(D10:D100<>"")* ((C10:C100=D10:D100)+((C10:C100=1)*(D10:D100=2))+((C10:C100=2)*(D10:D100=1)))) / SUMPRODUCT(--((C10:C100<>"")+(D10:D100<>"")>0)), "")} -> 0.61363636
A4: Semantic TP Implicit | C4: =COUNTIF(C10:C39, 1) -> 0 | D4: =COUNTIF(D10:D39, 1) -> 1 | E4: =COUNTIF(E10:E39, 1) -> 5 | F4: =COUNTIF(F10:F39, 1) -> 1 | G4: =COUNTIF(G10:G39, 1) -> 8 | H4: =COUNTIF(H10:H39, 1) -> 10 | J4: Chatbot run 3 | K4: {=IFERROR(SUMPRODUCT((C10:C100<>"")*(E10:E100<>"")*(C10:C100=E10:E100))/SUMPRODUCT(--((C10:C100<>"")+(E10:E100<>"")>0)),"")} -> 0.7027027 | L4: {=IFERROR(SUMPRODUCT((E10:E100<>"")*(D10:D100<>"")*(E10:E100=D10:D100))/SUMPRODUCT(--((E10:E100<>"")+(D10:D100<>"")>0)),"")} -> 0.6097561 | Q4: Chatbot run 3 | R4: {=IFERROR( SUMPRODUCT((C10:C100<>"")*(E10:E100<>"")* ((C10:C100=E10:E100)+((C10:C100=1)*(E10:E100=2))+((C10:C100=2)*(E10:E100=1)))) / SUMPRODUCT(--((C10:C100<>"")+(E10:E100<>"")>0)), "")} -> 0.81081081 | S4: {=IFERROR( SUMPRODUCT((E10:E100<>"")*(D10:D100<>"")* ((E10:E100=D10:D100)+((E10:E100=1)*(D10:D100=2))+((E10:E100=2)*(D10:D100=1)))) / SUMPRODUCT(--((E10:E100<>"")+(D10:D100<>"")>0)), "")} -> 0.65853659
A5: Semantic FN | C5: =COUNTIF(C10:C39, 0) -> 2 | D5: =COUNTIF(D10:D39, 0) -> 7 | E5: =COUNTIF(E10:E39, 0) -> 2 | F5: =COUNTIF(F10:F39, 0) -> 1 | G5: =COUNTIF(G10:G39, 0) -> 0 | H5: =COUNTIF(H10:H39, 0) -> 1 | J5: XML run 1 | K5: {=IFERROR(SUMPRODUCT((C10:C100<>"")*(F10:F100<>"")*(C10:C100=F10:F100))/SUMPRODUCT(--((C10:C100<>"")+(F10:F100<>"")>0)),"")} -> 0.65909091 | L5: {=IFERROR(SUMPRODUCT((F10:F100<>"")*(D10:D100<>"")*(F10:F100=D10:D100))/SUMPRODUCT(--((F10:F100<>"")+(D10:D100<>"")>0)),"")} -> 0.46 | M5: {=IFERROR(SUMPRODUCT((F10:F100<>"")*(E10:E100<>"")*(F10:F100=E10:E100))/SUMPRODUCT(--((F10:F100<>"")+(E10:E100<>"")>0)),"")} -> 0.53488372 | Q5: XML run 1 | R5: {=IFERROR( SUMPRODUCT((C10:C100<>"")*(F10:F100<>"")* ((C10:C100=F10:F100)+((C10:C100=1)*(F10:F100=2))+((C10:C100=2)*(F10:F100=1)))) / SUMPRODUCT(--((C10:C100<>"")+(F10:F100<>"")>0)), "")} -> 0.68181818 | S5: {=IFERROR( SUMPRODUCT((F10:F100<>"")*(D10:D100<>"")* ((F10:F100=D10:D100)+((F10:F100=1)*(D10:D100=2))+((F10:F100=2)*(D10:D100=1)))) / SUMPRODUCT(--((F10:F100<>"")+(D10:D100<>"")>0)), "")} -> 0.5 | T5: {=IFERROR( SUMPRODUCT((F10:F100<>"")*(E10:E100<>"")* ((F10:F100=E10:E100)+((F10:F100=1)*(E10:E100=2))+((F10:F100=2)*(E10:E100=1)))) / SUMPRODUCT(--((F10:F100<>"")+(E10:E100<>"")>0)), "")} -> 0.65116279
A6: Semantic FP Strict | C6: =COUNTIF(C41:C76,0) + COUNTIF(C41:C76,1) -> 5 | D6: =COUNTIF(D41:D76,0) + COUNTIF(D41:D76,1) -> 11 | E6: =COUNTIF(E41:E76,0) + COUNTIF(E41:E76,1) -> 4 | F6: =COUNTIF(F41:F76,0) + COUNTIF(F41:F76,1) -> 10 | G6: =COUNTIF(G41:G76,0) + COUNTIF(G41:G76,1) -> 11 | H6: =COUNTIF(H41:H76,0) + COUNTIF(H41:H76,1) -> 7 | J6: XML run 2 | K6: {=IFERROR(SUMPRODUCT((C10:C100<>"")*(G10:G100<>"")*(C10:C100=G10:G100))/SUMPRODUCT(--((C10:C100<>"")+(G10:G100<>"")>0)),"")} -> 0.51111111 | L6: {=SUMPRODUCT((D10:D100<>0)*(G10:G100<>0)) / SUMPRODUCT(((D10:D100<>0)+(G10:G100<>0)>0)*1)} -> 0.6 | M6: {=IFERROR(SUMPRODUCT((G10:G100<>"")*(E10:E100<>"")*(G10:G100=E10:E100))/SUMPRODUCT(--((G10:G100<>"")+(E10:E100<>"")>0)),"")} -> 0.56818182 | N6: {=IFERROR(SUMPRODUCT((G10:G100<>"")*(F10:F100<>"")*(G10:G100=F10:F100))/SUMPRODUCT(--((G10:G100<>"")+(F10:F100<>"")>0)),"")} -> 0.44 | Q6: XML run 2 | R6: {=IFERROR( SUMPRODUCT((C10:C100<>"")*(G10:G100<>"")* ((C10:C100=G10:G100)+((C10:C100=1)*(G10:G100=2))+((C10:C100=2)*(G10:G100=1)))) / SUMPRODUCT(--((C10:C100<>"")+(G10:G100<>"")>0)), "")} -> 0.64444444 | S6: {=IFERROR( SUMPRODUCT((D10:D100<>"")*(G10:G100<>"")* ((D10:D100=G10:G100)+((D10:D100=1)*(G10:G100=2))+((D10:D100=2)*(G10:G100=1)))) / SUMPRODUCT(--((D10:D100<>"")+(G10:G100<>"")>0)), "")} -> 0.5625 | T6: {=IFERROR( SUMPRODUCT((G10:G100<>"")*(E10:E100<>"")* ((G10:G100=E10:E100)+((G10:G100=1)*(E10:E100=2))+((G10:G100=2)*(E10:E100=1)))) / SUMPRODUCT(--((G10:G100<>"")+(E10:E100<>"")>0)), "")} -> 0.65909091 | U6: {=IFERROR( SUMPRODUCT((F10:F100<>"")*(G10:G100<>"")* ((F10:F100=G10:G100)+((F10:F100=1)*(G10:G100=2))+((F10:F100=2)*(G10:G100=1)))) / SUMPRODUCT(--((F10:F100<>"")+(G10:G100<>"")>0)), "")} -> 0.6
A7: Semantic FP Loose | C7: =COUNTIF(C41:C76,0) -> 1 | D7: =COUNTIF(D41:D76,0) -> 2 | E7: =COUNTIF(E41:E76,0) -> 1 | F7: =COUNTIF(F41:F76,0) -> 6 | G7: =COUNTIF(G41:G76,0) -> 1 | H7: =COUNTIF(H41:H76,0) -> 4 | J7: XML run 3 | K7: {=IFERROR(SUMPRODUCT((C10:C100<>"")*(H10:H100<>"")*(C10:C100=H10:H100))/SUMPRODUCT(--((C10:C100<>"")+(H10:H100<>"")>0)),"")} -> 0.45238095 | L7: {=IFERROR(SUMPRODUCT((H10:H100<>"")*(D10:D100<>"")*(H10:H100=D10:D100))/SUMPRODUCT(--((H10:H100<>"")+(D10:D100<>"")>0)),"")} -> 0.41666667 | M7: {=IFERROR(SUMPRODUCT((H10:H100<>"")*(E10:E100<>"")*(H10:H100=E10:E100))/SUMPRODUCT(--((H10:H100<>"")+(E10:E100<>"")>0)),"")} -> 0.51219512 | N7: {=IFERROR(SUMPRODUCT((F10:F100<>"")*(H10:H100<>"")*(F10:F100=H10:H100))/SUMPRODUCT(--((F10:F100<>"")+(H10:H100<>"")>0)),"")} -> 0.41304348 | O7: {=IFERROR(SUMPRODUCT((G10:G100<>"")*(H10:H100<>"")*(G10:G100=H10:H100))/SUMPRODUCT(--((G10:G100<>"")+(H10:H100<>"")>0)),"")} -> 0.5625 | Q7: XML run 3 | R7: {=IFERROR( SUMPRODUCT((C10:C100<>"")*(H10:H100<>"")* ((C10:C100=H10:H100)+((C10:C100=1)*(H10:H100=2))+((C10:C100=2)*(H10:H100=1)))) / SUMPRODUCT(--((C10:C100<>"")+(H10:H100<>"")>0)), "")} -> 0.64285714 | S7: {=IFERROR( SUMPRODUCT((H10:H100<>"")*(D10:D100<>"")* ((H10:H100=D10:D100)+((H10:H100=1)*(D10:D100=2))+((H10:H100=2)*(D10:D100=1)))) / SUMPRODUCT(--((H10:H100<>"")+(D10:D100<>"")>0)), "")} -> 0.45833333 | T7: {=IFERROR( SUMPRODUCT((H10:H100<>"")*(E10:E100<>"")* ((H10:H100=E10:E100)+((H10:H100=1)*(E10:E100=2))+((H10:H100=2)*(E10:E100=1)))) / SUMPRODUCT(--((H10:H100<>"")+(E10:E100<>"")>0)), "")} -> 0.65853659 | U7: {=IFERROR( SUMPRODUCT((F10:F100<>"")*(H10:H100<>"")* ((F10:F100=H10:H100)+((F10:F100=1)*(H10:H100=2))+((F10:F100=2)*(H10:H100=1)))) / SUMPRODUCT(--((F10:F100<>"")+(H10:H100<>"")>0)), "")} -> 0.63043478 | V7: {=IFERROR( SUMPRODUCT((H10:H100<>"")*(G10:G100<>"")* ((H10:H100=G10:G100)+((H10:H100=1)*(G10:G100=2))+((H10:H100=2)*(G10:G100=1)))) / SUMPRODUCT(--((H10:H100<>"")+(G10:G100<>"")>0)), "")} -> 0.60416667
C9: Chatbot run 1 | D9: Chatbot run 2 | E9: Chatbot run 3 | F9: XML run 1 | G9: XML run 2 | H9: XML run 3
A10: Pools | B10: Beneficiary | C10: 2 | D10: 2 | E10: 2 | F10: 2 | G10: 2 | H10: 2
B11: Insurance Agent | C11: 2 | D11: 2 | E11: 2 | F11: 2 | G11: 2 | H11: 2
B12: Insurance Company | C12: 2 | D12: 2 | E12: 2 | F12: 2 | G12: 2 | H12: 2
A13: Lanes | B13: Clerk | C13: 2 | D13: 2 | E13: 2 | F13: 2 | G13: 2 | H13: 2
B14: Regulator | C14: 2 | D14: 2 | E14: 2 | F14: 2 | G14: 2 | H14: 2
A15: Tasks/Messages/Events | B15: Accident Occurs | C15: 2 | D15: 2 | E15: 2 | F15: 2 | G15: 2 | H15: 2
B16: Call Insurance Agent | C16: 2 | D16: 2 | E16: 2 | F16: 2 | G16: 2 | H16: 2
B17: Receive Call from Beneficiary | C17: 2 | D17: 2 | E17: 2 | F17: 2 | G17: 2 | H17: 2
B18: Send Claim Notification to Insurance Company | C18: 2 | D18: 2 | E18: 2 | F18: 2 | G18: 2 | H18: 2
B19: Receive Claim Notification from Agent | C19: 2 | D19: 2 | E19: 2 | F19: 2 | G19: 2 | H19: 2
B20: Claim Processed or Closed | C20: 2 | D20: 2 | E20: 2 | F20: 2 | G20: 2 | H20: 2
B21: Enter Claim Notification | C21: 2 | D21: 2 | E21: 2 | F21: 2 | G21: 2 | H21: 2
B22: Assign Clerk | C22: 2 | D22: 2 | E22: 2 | F22: 2 | G22: 2 | H22: 2
B23: Check Policy Validity | C23: 2 | D23: 2 | E23: 2 | F23: 2 | G23: 2 | H23: 2
B24: Contact Doctors and Injured Parties | C24: 2 | D24: 0 | E24: 2 | F24: 2 | G24: 1 | H24: 1
B25: Prepare Repair Quote | C25: 2 | D25: 1 | E25: 2 | F25: 2 | G25: 2 | H25: 1
B26: Call the beneficiary | C26: 2 | D26: 0 | E26: 1 | F26: 2 | G26: 1 | H26: 1
B27: Call other injured persons | C27: 0 | D27: 0 | E27: 1 | F27: 0 | G27: 1 | H27: 1
... B34: Initiate Legal Measures | C34: 2 | D34: 2 | E34: 2 | F34: 2 | G34: 2 | H34: 2
A35: Conditions/Loops/Parallel: | B35: Was policy valid? | C35: 2 | D35: 2 | E35: 2 | F35: 2 | G35: 2 | H35: 2
B36: All parties satisfied? | C36: 2 | D36: 2 | E36: 2 | F36: 1 | G36: 2 | H36: 2
A37: Data Objects | B37: Claim Notification | C37: 2 | D37: 2 | E37: 2 | F37: 2 | G37: 1 | H37: 1
B38: Policy | C38: 2 | D38: 2 | E38: 2 | F38: 2 | G38: 1 | H38: 1
B39: Case File | C39: 2 | D39: 2 | E39: 1 | F39: 2 | G39: 2 | H39: 2
A41: False Positives | B41: Double task and event notify insurance agent | C41: 0 | D41: 0 | E41: 0
B42: Gather Medical and Repair Information | C42: 1
B43: Gather Additional Information (Parts, Treatments, etc.) | C43: 1
B44: Parallel GW | C44: 1 | D44: 1 | E44: 1 | F44: 1 | G44: 1
B45: Compensation Decision DO | C45: 1
B46: Double task and event notify insurance company | D46: 0
B47: Repair Quote DO | D47: 1 | G47: 1
B48: Medical Estimate DO | D48: 1
B49: Liability Assessment DO | D49: 1
B50: Compensation Decision DO | D50: 1 | E50: 1
B51: Estimate Repair Costs | D51: 1 | G51: 1
B52: Estimate Medical Costs | D52: 1 | G52: 1
B53: Assess Liability | D53: 1
B54: Gather Information (35 days) | D54: 1 | E54: 1
B55: Notify agent (second time) | F55: 0
B56: Notify insurance company (second time) | F56: 0
B57: Notify Parties about Compensation | F57: 1
B58: Legal Measures Initiated (Message Catch Event) | F58: 0
B59: Parties Satisfied | F59: 1
B60: 40 days passed | F60: 0
B61: Process Lawsuit (may take years) | F61: 1
B62: Pay Compensation | F62: 0 | H62: 0
B63: Payments Database DO | F63: 0
B64: Wait up to 3 Days | G64: 1
B65: Determine Who Pays | G65: 1
B66: Collect Further Information | G66: 1
B67: Contact All Parties | G67: 1
B68: Collected Information DO | G68: 1
B69: Obligation Status DO | G69: 0
B70: Medical Details DO | G70: 1
B71: Collect Claim Information | H71: 0
B72: Up to 3 days delay | H72: 1
B73: Accumulate Internal Costs (500€ avg) | H73: 0
B74: Cost Estimation DO | H74: 1
B75: Liability Assessment DO | H75: 1
B76: Decide on Compensation GW | H76: 0

Sheet c9
A1: Semantic Percision | C1: =SUM(C3:C4) / (C3+ C4+ C7) * 100 -> 100 | D1: =SUM(D3:D4) / (D3+ D4+ D7) * 100 -> 100 | E1: =SUM(E3:E4) / (E3+ E4+ E7) * 100 -> 100 | F1: =SUM(F3:F4) / (F3+ F4+ F7) * 100 -> 94.117647 | G1: =SUM(G3:G4) / (G3+ G4+ G7) * 100 -> 87.5 | H1: =SUM(H3:H4) / (H3+ H4+ H7) * 100 -> 94.117647 | J1: Jaccard Strict | K1: Chatbot run 1 | L1: Chatbot run 2 | M1: Chatbot run 3 | N1: XML run 1 | O1: XML run 2 | P1: XML run 3 | Q1: Jaccard Loose | R1: Chatbot run 1 | S1: Chatbot run 2 | T1: Chatbot run 3 | U1: XML run 1 | V1: XML run 2 | W1: XML run 3
A2: Semantic Recall | C2: =SUM(C3:C4) / SUM(C3:C5) *100 -> 100 | D2: =SUM(D3:D4) / SUM(D3:D5) *100 -> 100 | E2: =SUM(E3:E4) / SUM(E3:E5) *100 -> 100 | F2: =SUM(F3:F4) / SUM(F3:F5) *100 -> 100 | G2: =SUM(G3:G4) / SUM(G3:G5) *100 -> 87.5 | H2: =SUM(H3:H4) / SUM(H3:H5) *100 -> 100 | J2: Chatbot run 1 | Q2: Chatbot run 1
A3: Semantic TP Explicit | C3: =COUNTIF(C10:C25, 2) -> 16 | D3: =COUNTIF(D10:D25, 2) -> 16 | E3: =COUNTIF(E10:E25, 2) -> 16 | F3: =COUNTIF(F10:F25, 2) -> 14 | G3: =COUNTIF(G10:G25, 2) -> 13 | H3: =COUNTIF(H10:H25, 2) -> 15 | J3: Chatbot run 2 | K3: {=IFERROR(SUMPRODUCT((C10:C100<>"")*(D10:D100<>"")*(C10:C100=D10:D100))/SUMPRODUCT(--((C10:C100<>"")+(D10:D100<>"")>0)),"")} -> 0.9047619 | Q3: Chatbot run 2 | R3: {=IFERROR( SUMPRODUCT((C10:C100<>"")*(D10:D100<>"")* ((C10:C100=D10:D100)+((C10:C100=1)*(D10:D100=2))+((C10:C100=2)*(D10:D100=1)))) / SUMPRODUCT(--((C10:C100<>"")+(D10:D100<>"")>0)), "")} -> 0.9047619
A4: Semantic TP Implicit | C4: =COUNTIF(C10:C25, 1) -> 0 | D4: =COUNTIF(D10:D25, 1) -> 0 | E4: =COUNTIF(E10:E25, 1) -> 0 | F4: =COUNTIF(F10:F25, 1) -> 2 | G4: =COUNTIF(G10:G25, 1) -> 1 | H4: =COUNTIF(H10:H25, 1) -> 1 | J4: Chatbot run 3 | K4: {=IFERROR(SUMPRODUCT((C10:C100<>"")*(E10:E100<>"")*(C10:C100=E10:E100))/SUMPRODUCT(--((C10:C100<>"")+(E10:E100<>"")>0)),"")} -> 0.7037037 | L4: {=IFERROR(SUMPRODUCT((E10:E100<>"")*(D10:D100<>"")*(E10:E100=D10:D100))/SUMPRODUCT(--((E10:E100<>"")+(D10:D100<>"")>0)),"")} -> 0.77777778 | Q4: Chatbot run 3 | R4: {=IFERROR( SUMPRODUCT((C10:C100<>"")*(E10:E100<>"")* ((C10:C100=E10:E100)+((C10:C100=1)*(E10:E100=2))+((C10:C100=2)*(E10:E100=1)))) / SUMPRODUCT(--((C10:C100<>"")+(E10:E100<>"")>0)), "")} -> 0.7037037 | S4: {=IFERROR( SUMPRODUCT((E10:E100<>"")*(D10:D100<>"")* ((E10:E100=D10:D100)+((E10:E100=1)*(D10:D100=2))+((E10:E100=2)*(D10:D100=1)))) / SUMPRODUCT(--((E10:E100<>"")+(D10:D100<>"")>0)), "")} -> 0.77777778
A5: Semantic FN | C5: =COUNTIF(C10:C25, 0) -> 0 | D5: =COUNTIF(D10:D25, 0) -> 0 | E5: =COUNTIF(E10:E25, 0) -> 0 | F5: =COUNTIF(F10:F25, 0) -> 0 | G5: =COUNTIF(G10:G25, 0) -> 2 | H5: =COUNTIF(H10:H25, 0) -> 0 | J5: XML run 1 | K5: {=IFERROR(SUMPRODUCT((C10:C100<>"")*(F10:F100<>"")*(C10:C100=F10:F100))/SUMPRODUCT(--((C10:C100<>"")+(F10:F100<>"")>0)),"")} -> 0.80952381 | L5: {=IFERROR(SUMPRODUCT((F10:F100<>"")*(D10:D100<>"")*(F10:F100=D10:D100))/SUMPRODUCT(--((F10:F100<>"")+(D10:D100<>"")>0)),"")} -> 0.81818182 | M5: {=IFERROR(SUMPRODUCT((F10:F100<>"")*(E10:E100<>"")*(F10:F100=E10:E100))/SUMPRODUCT(--((F10:F100<>"")+(E10:E100<>"")>0)),"")} -> 0.64285714 | Q5: XML run 1 | R5: {=IFERROR( SUMPRODUCT((C10:C100<>"")*(F10:F100<>"")* ((C10:C100=F10:F100)+((C10:C100=1)*(F10:F100=2))+((C10:C100=2)*(F10:F100=1)))) / SUMPRODUCT(--((C10:C100<>"")+(F10:F100<>"")>0)), "")} -> 0.9047619 | S5: {=IFERROR( SUMPRODUCT((F10:F100<>"")*(D10:D100<>"")* ((F10:F100=D10:D100)+((F10:F100=1)*(D10:D100=2))+((F10:F100=2)*(D10:D100=1)))) / SUMPRODUCT(--((F10:F100<>"")+(D10:D100<>"")>0)), "")} -> 0.90909091 | T5: {=IFERROR( SUMPRODUCT((F10:F100<>"")*(E10:E100<>"")* ((F10:F100=E10:E100)+((F10:F100=1)*(E10:E100=2))+((F10:F100=2)*(E10:E100=1)))) / SUMPRODUCT(--((F10:F100<>"")+(E10:E100<>"")>0)), "")} -> 0.71428571
A6: Semantic FP Strict | C6: =COUNTIF(C27:C59,0) + COUNTIF(C27:C59,1) -> 3 | D6: =COUNTIF(D27:D59,0) + COUNTIF(D27:D59,1) -> 5 | E6: =COUNTIF(E27:E59,0) + COUNTIF(E27:E59,1) -> 11 | F6: =COUNTIF(F27:F59,0) + COUNTIF(F27:F59,1) -> 5 | G6: =COUNTIF(G27:G59,0) + COUNTIF(G27:G59,1) -> 7 | H6: =COUNTIF(H27:H59,0) + COUNTIF(H27:H59,1) -> 6 | J6: XML run 2 | K6: {=IFERROR(SUMPRODUCT((C10:C100<>"")*(G10:G100<>"")*(C10:C100=G10:G100))/SUMPRODUCT(--((C10:C100<>"")+(G10:G100<>"")>0)),"")} -> 0.69565217 | L6: {=SUMPRODUCT((D10:D100<>0)*(G10:G100<>0)) / SUMPRODUCT(((D10:D100<>0)+(G10:G100<>0)>0)*1)} -> 0.81818182 | M6: {=IFERROR(SUMPRODUCT((G10:G100<>"")*(E10:E100<>"")*(G10:G100=E10:E100))/SUMPRODUCT(--((G10:G100<>"")+(E10:E100<>"")>0)),"")} -> 0.62068966 | N6: {=IFERROR(SUMPRODUCT((G10:G100<>"")*(F10:F100<>"")*(G10:G100=F10:F100))/SUMPRODUCT(--((G10:G100<>"")+(F10:F100<>"")>0)),"")} -> 0.70833333 | Q6: XML run 2 | R6: {=IFERROR( SUMPRODUCT((C10:C100<>"")*(G10:G100<>"")* ((C10:C100=G10:G100)+((C10:C100=1)*(G10:G100=2))+((C10:C100=2)*(G10:G100=1)))) / SUMPRODUCT(--((C10:C100<>"")+(G10:G100<>"")>0)), "")} -> 0.73913043 | S6: {=IFERROR( SUMPRODUCT((D10:D100<>"")*(G10:G100<>"")* ((D10:D100=G10:G100)+((D10:D100=1)*(G10:G100=2))+((D10:D100=2)*(G10:G100=1)))) / SUMPRODUCT(--((D10:D100<>"")+(G10:G100<>"")>0)), "")} -> 0.75 | T6: {=IFERROR( SUMPRODUCT((G10:G100<>"")*(E10:E100<>"")* ((G10:G100=E10:E100)+((G10:G100=1)*(E10:E100=2))+((G10:G100=2)*(E10:E100=1)))) / SUMPRODUCT(--((G10:G100<>"")+(E10:E100<>"")>0)), "")} -> 0.65517241 | U6: {=IFERROR( SUMPRODUCT((F10:F100<>"")*(G10:G100<>"")* ((F10:F100=G10:G100)+((F10:F100=1)*(G10:G100=2))+((F10:F100=2)*(G10:G100=1)))) / SUMPRODUCT(--((F10:F100<>"")+(G10:G100<>"")>0)), "")} -> 0.75
A7: Semantic FP Loose | C7: =COUNTIF(C27:C59,0) -> 0 | D7: =COUNTIF(D27:D59,0) -> 0 | E7: =COUNTIF(E27:E59,0) -> 0 | F7: =COUNTIF(F27:F59,0) -> 1 | G7: =COUNTIF(G27:G59,0) -> 2 | H7: =COUNTIF(H27:H59,0) -> 1 | J7: XML run 3 | K7: {=IFERROR(SUMPRODUCT((C10:C100<>"")*(H10:H100<>"")*(C10:C100=H10:H100))/SUMPRODUCT(--((C10:C100<>"")+(H10:H100<>"")>0)),"")} -> 0.81818182 | L7: {=IFERROR(SUMPRODUCT((H10:H100<>"")*(D10:D100<>"")*(H10:H100=D10:D100))/SUMPRODUCT(--((H10:H100<>"")+(D10:D100<>"")>0)),"")} -> 0.82608696 | M7: {=IFERROR(SUMPRODUCT((H10:H100<>"")*(E10:E100<>"")*(H10:H100=E10:E100))/SUMPRODUCT(--((H10:H100<>"")+(E10:E100<>"")>0)),"")} -> 0.71428571 | N7: {=IFERROR(SUMPRODUCT((F10:F100<>"")*(H10:H100<>"")*(F10:F100=H10:H100))/SUMPRODUCT(--((F10:F100<>"")+(H10:H100<>"")>0)),"")} -> 0.75 | O7: {=IFERROR(SUMPRODUCT((G10:G100<>"")*(H10:H100<>"")*(G10:G100=H10:H100))/SUMPRODUCT(--((G10:G100<>"")+(H10:H100<>"")>0)),"")} -> 0.86956522 | Q7: XML run 3 | R7: {=IFERROR( SUMPRODUCT((C10:C100<>"")*(H10:H100<>"")* ((C10:C100=H10:H100)+((C10:C100=1)*(H10:H100=2))+((C10:C100=2)*(H10:H100=1)))) / SUMPRODUCT(--((C10:C100<>"")+(H10:H100<>"")>0)), "")} -> 0.86363636 | S7: {=IFERROR( SUMPRODUCT((H10:H100<>"")*(D10:D100<>"")* ((H10:H100=D10:D100)+((H10:H100=1)*(D10:D100=2))+((H10:H100=2)*(D10:D100=1)))) / SUMPRODUCT(--((H10:H100<>"")+(D10:D100<>"")>0)), "")} -> 0.86956522 | T7: {=IFERROR( SUMPRODUCT((H10:H100<>"")*(E10:E100<>"")* ((H10:H100=E10:E100)+((H10:H100=1)*(E10:E100=2))+((H10:H100=2)*(E10:E100=1)))) / SUMPRODUCT(--((H10:H100<>"")+(E10:E100<>"")>0)), "")} -> 0.75 | U7: {=IFERROR( SUMPRODUCT((F10:F100<>"")*(H10:H100<>"")* ((F10:F100=H10:H100)+((F10:F100=1)*(H10:H100=2))+((F10:F100=2)*(H10:H100=1)))) / SUMPRODUCT(--((F10:F100<>"")+(H10:H100<>"")>0)), "")} -> 0.79166667 | V7: {=IFERROR( SUMPRODUCT((H10:H100<>"")*(G10:G100<>"")* ((H10:H100=G10:G100)+((H10:H100=1)*(G10:G100=2))+((H10:H100=2)*(G10:G100=1)))) / SUMPRODUCT(--((H10:H100<>"")+(G10:G100<>"")>0)), "")} -> 0.86956522
C9: Chatbot run 1 | D9: Chatbot run 2 | E9: Chatbot run 3 | F9: XML run 1 | G9: XML run 2 | H9: XML run 3
A10: Pools | B10: Car Insurer | C10: 2 | D10: 2 | E10: 2 | F10: 2 | G10: 0 | H10: 2
B11: Customer | C11: 2 | D11: 2 | E11: 2 | F11: 2 | G11: 0 | H11: 2
A12: Lanes | B12: Notification Department | C12: 2 | D12: 2 | E12: 2 | F12: 2 | G12: 2 | H12: 2
B13: Handling Department | C13: 2 | D13: 2 | E13: 2 | F13: 2 | G13: 2 | H13: 2
A14: Tasks/Messages/Events | B14: Receive Claim and Documentation | C14: 2 | D14: 2 | E14: 2 | F14: 1 | G14: 2 | H14: 2
B15: Register Claim | C15: 2 | D15: 2 | E15: 2 | F15: 2 | G15: 2 | H15: 2
B16: Check Insurance | C16: 2 | D16: 2 | E16: 2 | F16: 2 | G16: 2 | H16: 2
B17: Perform Assessment | C17: 2 | D17: 2 | E17: 2 | F17: 2 | G17: 2 | H17: 2
B18: Phone Garage to Authorize Repairs | C18: 2 | D18: 2 | E18: 2 | F18: 2 | G18: 2 | H18: 2
B19: Schedule Payment | C19: 2 | D19: 2 | E19: 2 | F19: 2 | G19: 2 | H19: 2
B20: Reject Claim | C20: 2 | D20: 2 | E20: 2 | F20: 2 | G20: 2 | H20: 2
B21: Send Letter to Customer | C21: 2 | D21: 2 | E21: 2 | F21: 2 | G21: 2 | H21: 2
A22: Conditions/Loops/Parallel | B22: Is Insurance Valid? | C22: 2 | D22: 2 | E22: 2 | F22: 2 | G22: 2 | H22: 2
B23: Is Assessment Positive? | C23: 2 | D23: 2 | E23: 2 | F23: 2 | G23: 2 | H23: 2
A24: Data Objects | B24: Claim | C24: 2 | D24: 2 | E24: 2 | F24: 2 | G24: 2 | H24: 2
B25: Letter | C25: 2 | D25: 2 | E25: 2 | F25: 1 | G25: 1 | H25: 1
B27: Check Documents for Completeness | C27: 1 | D27: 1 | E27: 1 | F27: 1 | G27: 1 | H27: 1
B28: Documents Complete? X | C28: 1 | D28: 1 | E28: 1 | F28: 1 | G28: 1 | H28: 1
B29: Submit Claim to Insurer | C29: 1 | D29: 1 | E29: 1 | F29: 1 | G29: 1 | H29: 1
B30: Prepare Claim and Documntation | D30: 1 | E30: 1 | F30: 1
B31: Receive Letter from Insurer | D31: 1 | E31: 1 | G31: 1 | H31: 1
B32: Prepare Rejection Letter | E32: 1
B33: Prepare Approval Letter | E33: 1
B34: Claim Submission DO | E34: 1
B35: Registered Claim DO | E35: 1
B36: Assesment Result DO | E36: 1
B37: Claim Documnts DO | E37: 1 | G37: 1 | H37: 1
B38: Submit Claim Double | F38: 0 | G38: 0
B39: Send Letter to Customer Double | G39: 0 | H39: 0

Sheet c10
A1: Semantic Percision | C1: =SUM(C3:C4) / (C3+ C4+ C7) * 100 -> 84.210526 | D1: =SUM(D3:D4) / (D3+ D4+ D7) * 100 -> 88.888889 | E1: =SUM(E3:E4) / (E3+ E4+ E7) * 100 -> 80 | F1: =SUM(F3:F4) / (F3+ F4+ F7) * 100 -> 83.333333 | G1: =SUM(G3:G4) / (G3+ G4+ G7) * 100 -> 80 | H1: =SUM(H3:H4) / (H3+ H4+ H7) * 100 -> 88.235294 | J1: Jaccard Strict | K1: Chatbot run 1 | L1: Chatbot run 2 | M1: Chatbot run 3 | N1: XML run 1 | O1: XML run 2 | P1: XML run 3 | Q1: Jaccard Loose | R1: Chatbot run 1 | S1: Chatbot run 2 | T1: Chatbot run 3 | U1: XML run 1 | V1: XML run 2 | W1: XML run 3
A2: Semantic Recall | C2: =SUM(C3:C4) / SUM(C3:C5) *100 -> 100 | D2: =SUM(D3:D4) / SUM(D3:D5) *100 -> 100 | E2: =SUM(E3:E4) / SUM(E3:E5) *100 -> 100 | F2: =SUM(F3:F4) / SUM(F3:F5) *100 -> 93.75 | G2: =SUM(G3:G4) / SUM(G3:G5) *100 -> 100 | H2: =SUM(H3:H4) / SUM(H3:H5) *100 -> 93.75 | J2: Chatbot run 1 | Q2: Chatbot run 1
A3: Semantic TP Explicit | C3: =COUNTIF(C10:C25, 2) -> 15 | D3: =COUNTIF(D10:D25, 2) -> 16 | E3: =COUNTIF(E10:E25, 2) -> 15 | F3: =COUNTIF(F10:F25, 2) -> 14 | G3: =COUNTIF(G10:G25, 2) -> 14 | H3: =COUNTIF(H10:H25, 2) -> 15 | J3: Chatbot run 2 | K3: {=IFERROR(SUMPRODUCT((C10:C100<>"")*(D10:D100<>"")*(C10:C100=D10:D100))/SUMPRODUCT(--((C10:C100<>"")+(D10:D100<>"")>0)),"")} -> 0.89655172 | Q3: Chatbot run 2 | R3: {=IFERROR( SUMPRODUCT((C10:C100<>"")*(D10:D100<>"")* ((C10:C100=D10:D100)+((C10:C100=1)*(D10:D100=2))+((C10:C100=2)*(D10:D100=1)))) / SUMPRODUCT(--((C10:C100<>"")+(D10:D100<>"")>0)), "")} -> 0.93103448
A4: Semantic TP Implicit | C4: =COUNTIF(C10:C25, 1) -> 1 | D4: =COUNTIF(D10:D25, 1) -> 0 | E4: =COUNTIF(E10:E25, 1) -> 1 | F4: =COUNTIF(F10:F25, 1) -> 1 | G4: =COUNTIF(G10:G25, 1) -> 2 | H4: =COUNTIF(H10:H25, 1) -> 0 | J4: Chatbot run 3 | K4: {=IFERROR(SUMPRODUCT((C10:C100<>"")*(E10:E100<>"")*(C10:C100=E10:E100))/SUMPRODUCT(--((C10:C100<>"")+(E10:E100<>"")>0)),"")} -> 0.84375 | L4: {=IFERROR(SUMPRODUCT((E10:E100<>"")*(D10:D100<>"")*(E10:E100=D10:D100))/SUMPRODUCT(--((E10:E100<>"")+(D10:D100<>"")>0)),"")} -> 0.87096774 | Q4: Chatbot run 3 | R4: {=IFERROR( SUMPRODUCT((C10:C100<>"")*(E10:E100<>"")* ((C10:C100=E10:E100)+((C10:C100=1)*(E10:E100=2))+((C10:C100=2)*(E10:E100=1)))) / SUMPRODUCT(--((C10:C100<>"")+(E10:E100<>"")>0)), "")} -> 0.84375 | S4: {=IFERROR( SUMPRODUCT((E10:E100<>"")*(D10:D100<>"")* ((E10:E100=D10:D100)+((E10:E100=1)*(D10:D100=2))+((E10:E100=2)*(D10:D100=1)))) / SUMPRODUCT(--((E10:E100<>"")+(D10:D100<>"")>0)), "")} -> 0.90322581
A5: Semantic FN | C5: =COUNTIF(C10:C25, 0) -> 0 | D5: =COUNTIF(D10:D25, 0) -> 0 | E5: =COUNTIF(E10:E25, 0) -> 0 | F5: =COUNTIF(F10:F25, 0) -> 1 | G5: =COUNTIF(G10:G25, 0) -> 0 | H5: =COUNTIF(H10:H25, 0) -> 1 | J5: XML run 1 | K5: {=IFERROR(SUMPRODUCT((C10:C100<>"")*(F10:F100<>"")*(C10:C100=F10:F100))/SUMPRODUCT(--((C10:C100<>"")+(F10:F100<>"")>0)),"")} -> 0.75 | L5: {=IFERROR(SUMPRODUCT((F10:F100<>"")*(D10:D100<>"")*(F10:F100=D10:D100))/SUMPRODUCT(--((F10:F100<>"")+(D10:D100<>"")>0)),"")} -> 0.71875 | M5: {=IFERROR(SUMPRODUCT((F10:F100<>"")*(E10:E100<>"")*(F10:F100=E10:E100))/SUMPRODUCT(--((F10:F100<>"")+(E10:E100<>"")>0)),"")} -> 0.68571429 | Q5: XML run 1 | R5: {=IFERROR( SUMPRODUCT((C10:C100<>"")*(F10:F100<>"")* ((C10:C100=F10:F100)+((C10:C100=1)*(F10:F100=2))+((C10:C100=2)*(F10:F100=1)))) / SUMPRODUCT(--((C10:C100<>"")+(F10:F100<>"")>0)), "")} -> 0.75 | S5: {=IFERROR( SUMPRODUCT((F10:F100<>"")*(D10:D100<>"")* ((F10:F100=D10:D100)+((F10:F100=1)*(D10:D100=2))+((F10:F100=2)*(D10:D100=1)))) / SUMPRODUCT(--((F10:F100<>"")+(D10:D100<>"")>0)), "")} -> 0.75 | T5: {=IFERROR( SUMPRODUCT((F10:F100<>"")*(E10:E100<>"")* ((F10:F100=E10:E100)+((F10:F100=1)*(E10:E100=2))+((F10:F100=2)*(E10:E100=1)))) / SUMPRODUCT(--((F10:F100<>"")+(E10:E100<>"")>0)), "")} -> 0.68571429
A6: Semantic FP Strict | C6: =COUNTIF(C27:C59,0) + COUNTIF(C27:C59,1) -> 12 | D6: =COUNTIF(D27:D59,0) + COUNTIF(D27:D59,1) -> 12 | E6: =COUNTIF(E27:E59,0) + COUNTIF(E27:E59,1) -> 15 | F6: =COUNTIF(F27:F59,0) + COUNTIF(F27:F59,1) -> 13 | G6: =COUNTIF(G27:G59,0) + COUNTIF(G27:G59,1) -> 13 | H6: =COUNTIF(H27:H59,0) + COUNTIF(H27:H59,1) -> 8 | J6: XML run 2 | K6: {=IFERROR(SUMPRODUCT((C10:C100<>"")*(G10:G100<>"")*(C10:C100=G10:G100))/SUMPRODUCT(--((C10:C100<>"")+(G10:G100<>"")>0)),"")} -> 0.75 | L6: {=SUMPRODUCT((D10:D100<>0)*(G10:G100<>0)) / SUMPRODUCT(((D10:D100<>0)+(G10:G100<>0)>0)*1)} -> 0.82142857 | M6: {=IFERROR(SUMPRODUCT((G10:G100<>"")*(E10:E100<>"")*(G10:G100=E10:E100))/SUMPRODUCT(--((G10:G100<>"")+(E10:E100<>"")>0)),"")} -> 0.68571429 | N6: {=IFERROR(SUMPRODUCT((G10:G100<>"")*(F10:F100<>"")*(G10:G100=F10:F100))/SUMPRODUCT(--((G10:G100<>"")+(F10:F100<>"")>0)),"")} -> 0.75 | Q6: XML run 2 | R6: {=IFERROR( SUMPRODUCT((C10:C100<>"")*(G10:G100<>"")* ((C10:C100=G10:G100)+((C10:C100=1)*(G10:G100=2))+((C10:C100=2)*(G10:G100=1)))) / SUMPRODUCT(--((C10:C100<>"")+(G10:G100<>"")>0)), "")} -> 0.78125 | S6: {=IFERROR( SUMPRODUCT((D10:D100<>"")*(G10:G100<>"")* ((D10:D100=G10:G100)+((D10:D100=1)*(G10:G100=2))+((D10:D100=2)*(G10:G100=1)))) / SUMPRODUCT(--((D10:D100<>"")+(G10:G100<>"")>0)), "")} -> 0.78125 | T6: {=IFERROR( SUMPRODUCT((G10:G100<>"")*(E10:E100<>"")* ((G10:G100=E10:E100)+((G10:G100=1)*(E10:E100=2))+((G10:G100=2)*(E10:E100=1)))) / SUMPRODUCT(--((G10:G100<>"")+(E10:E100<>"")>0)), "")} -> 0.71428571 | U6: {=IFERROR( SUMPRODUCT((F10:F100<>"")*(G10:G100<>"")* ((F10:F100=G10:G100)+((F10:F100=1)*(G10:G100=2))+((F10:F100=2)*(G10:G100=1)))) / SUMPRODUCT(--((F10:F100<>"")+(G10:G100<>"")>0)), "")} -> 0.78125
A7: Semantic FP Loose | C7: =COUNTIF(C27:C59,0) -> 3 | D7: =COUNTIF(D27:D59,0) -> 2 | E7: =COUNTIF(E27:E59,0) -> 4 | F7: =COUNTIF(F27:F59,0) -> 3 | G7: =COUNTIF(G27:G59,0) -> 4 | H7: =COUNTIF(H27:H59,0) -> 2 | J7: XML run 3 | K7: {=IFERROR(SUMPRODUCT((C10:C100<>"")*(H10:H100<>"")*(C10:C100=H10:H100))/SUMPRODUCT(--((C10:C100<>"")+(H10:H100<>"")>0)),"")} -> 0.66666667 | L7: {=IFERROR(SUMPRODUCT((H10:H100<>"")*(D10:D100<>"")*(H10:H100=D10:D100))/SUMPRODUCT(--((H10:H100<>"")+(D10:D100<>"")>0)),"")} -> 0.7 | M7: {=IFERROR(SUMPRODUCT((H10:H100<>"")*(E10:E100<>"")*(H10:H100=E10:E100))/SUMPRODUCT(--((H10:H100<>"")+(E10:E100<>"")>0)),"")} -> 0.60606061 | N7: {=IFERROR(SUMPRODUCT((F10:F100<>"")*(H10:H100<>"")*(F10:F100=H10:H100))/SUMPRODUCT(--((F10:F100<>"")+(H10:H100<>"")>0)),"")} -> 0.73333333 | O7: {=IFERROR(SUMPRODUCT((G10:G100<>"")*(H10:H100<>"")*(G10:G100=H10:H100))/SUMPRODUCT(--((G10:G100<>"")+(H10:H100<>"")>0)),"")} -> 0.72413793 | Q7: XML run 3 | R7: {=IFERROR( SUMPRODUCT((C10:C100<>"")*(H10:H100<>"")* ((C10:C100=H10:H100)+((C10:C100=1)*(H10:H100=2))+((C10:C100=2)*(H10:H100=1)))) / SUMPRODUCT(--((C10:C100<>"")+(H10:H100<>"")>0)), "")} -> 0.7 | S7: {=IFERROR( SUMPRODUCT((H10:H100<>"")*(D10:D100<>"")* ((H10:H100=D10:D100)+((H10:H100=1)*(D10:D100=2))+((H10:H100=2)*(D10:D100=1)))) / SUMPRODUCT(--((H10:H100<>"")+(D10:D100<>"")>0)), "")} -> 0.7 | T7: {=IFERROR( SUMPRODUCT((H10:H100<>"")*(E10:E100<>"")* ((H10:H100=E10:E100)+((H10:H100=1)*(E10:E100=2))+((H10:H100=2)*(E10:E100=1)))) / SUMPRODUCT(--((H10:H100<>"")+(E10:E100<>"")>0)), "")} -> 0.63636364 | U7: {=IFERROR( SUMPRODUCT((F10:F100<>"")*(H10:H100<>"")* ((F10:F100=H10:H100)+((F10:F100=1)*(H10:H100=2))+((F10:F100=2)*(H10:H100=1)))) / SUMPRODUCT(--((F10:F100<>"")+(H10:H100<>"")>0)), "")} -> 0.76666667 | V7: {=IFERROR( SUMPRODUCT((H10:H100<>"")*(G10:G100<>"")* ((H10:H100=G10:G100)+((H10:H100=1)*(G10:G100=2))+((H10:H100=2)*(G10:G100=1)))) / SUMPRODUCT(--((H10:H100<>"")+(G10:G100<>"")>0)), "")} -> 0.79310345
C9: Chatbot run 1 | D9: Chatbot run 2 | E9: Chatbot run 3 | F9: XML run 1 | G9: XML run 2 | H9: XML run 3
A10: Pools | B10: You | C10: 2 | D10: 2 | E10: 2 | F10: 2 | G10: 2 | H10: 2
B11: Central Fridge Service Center | C11: 2 | D11: 2 | E11: 2 | F11: 2 | G11: 2 | H11: 2
B12: Service Facility | C12: 2 | D12: 2 | E12: 2 | F12: 2 | G12: 2 | H12: 2
A13: Tasks/Messages/Events | B13: Fridge produced strange noises | C13: 2 | D13: 2 | E13: 2 | F13: 0 | G13: 2 | H13: 0
B14: Describe Symptoms and Type | C14: 2 | D14: 2 | E14: 2 | F14: 2 | G14: 2 | H14: 2
B15: Send Request to Service Center | C15: 2 | D15: 2 | E15: 2 | F15: 2 | G15: 2 | H15: 2
B16: Select Local Service Facility | C16: 2 | D16: 2 | E16: 2 | F16: 2 | G16: 2 | H16: 2
B17: Make Appointment | C17: 2 | D17: 2 | E17: 2 | F17: 2 | G17: 2 | H17: 2
B18: Visit Customer | C18: 2 | D18: 2 | E18: 2 | F18: 2 | G18: 2 | H18: 2
B19: Get additional parts | C19: 2 | D19: 2 | E19: 2 | F19: 2 | G19: 2 | H19: 2
B20: Do repair | C20: 2 | D20: 2 | E20: 2 | F20: 2 | G20: 2 | H20: 2
B21: Confirm repair | C21: 2 | D21: 2 | E21: 2 | F21: 2 | G21: 2 | H21: 2
B22: rate the service facility | C22: 2 | D22: 2 | E22: 2 | F22: 2 | G22: 2 | H22: 2
A23: Conditions/Loops/Parallel | B23: Have all parts? | C23: 1 | D23: 2 | E23: 1 | F23: 1 | G23: 1 | H23: 2
A24: Data Objects/ Messages | B24: Symptoms Description | C24: 2 | D24: 2 | E24: 2 | F24: 2 | G24: 2 | H24: 2
B25: Fridge Type | C25: 2 | D25: 2 | E25: 2 | F25: 2 | G25: 1 | H25: 2
B27: Send Appointment to Customer | C27: 0 | D27: 0 | E27: 0 | F27: 0 | G27: 0 | H27: 0
B28: Receive Appointment from Service Facility | C28: 0 | D28: 0 | E28: 0 | F28: 0 | G28: 0 | H28: 0
B29: Receive Request from Customer | C29: 1 | D29: 1 | E29: 1 | F29: 1 | G29: 1 | H29: 1
B30: Forward Request to Service Facility | C30: 1 | D30: 1 | E30: 1 | F30: 1 | G30: 1 | H30: 1
B31: Receive Request from Service Center | C31: 1 | D31: 1 | E31: 1 | F31: 1 | G31: 1
B32: Reschedule | C32: 0
B33: Send Confirmation to Service Facility | C33: 1 | D33: 1 | E33: 1 | F33: 1 | G33: 1
B34: Receive Repair Confirmation from Customer | C34: 1 | D34: 1 | E34: 1 | F34: 1 | G34: 1
B35: Notify Customer of Repair Completion | C35: 1 | D35: 1 | E35: 1 | F35: 1 | G35: 1 | H35: 1
B36: Receive Repair Completion Notification | C36: 1 | D36: 1 | E36: 1 | F36: 1 | G36: 1 | H36: 1
B37: Repair Confirmation DO | C37: 1 | D37: 1 | E37: 1
B38: Service Rating DO | C38: 1 | D38: 1 | E38: 1
B39: Fridge Not yet Repaired Loop | D39: 1 | E39: 1
B40: Repair Status DO | E40: 0
B41: Set Repair Status to Complete | E41: 0
B42: Appointment DO | E42: 1
B43: Wait for Repair Visit | F43: 1
B44: Fridge Repaired Task | F44: 0
B45: Wait for Next Repair Attempt | F45: 1
B46: Repair Outcome x in Customer | F46: 1 | G46: 1 | H46: 1
B47: Receive not OK from Customer | G47: 0
B48: Report not OK to Service Facility | G48: 0
B49: Complete Repair | G49: 1 | H49: 1

Sheet c11
A1: Semantic Percision | C1: =SUM(C3:C4) / (C3+ C4+ C7) * 100 -> 100 | D1: =SUM(D3:D4) / (D3+ D4+ D7) * 100 -> 100 | E1: =SUM(E3:E4) / (E3+ E4+ E7) * 100 -> 100 | F1: =SUM(F3:F4) / (F3+ F4+ F7) * 100 -> 92.857143 | G1: =SUM(G3:G4) / (G3+ G4+ G7) * 100 -> 86.666667 | H1: =SUM(H3:H4) / (H3+ H4+ H7) * 100 -> 100 | J1: Jaccard Strict | K1: Chatbot run 1 | L1: Chatbot run 2 | M1: Chatbot run 3 | N1: XML run 1 | O1: XML run 2 | P1: XML run 3 | Q1: Jaccard Loose | R1: Chatbot run 1 | S1: Chatbot run 2 | T1: Chatbot run 3 | U1: XML run 1 | V1: XML run 2 | W1: XML run 3
A2: Semantic Recall | C2: =SUM(C3:C4) / SUM(C3:C5) *100 -> 93.75 | D2: =SUM(D3:D4) / SUM(D3:D5) *100 -> 93.75 | E2: =SUM(E3:E4) / SUM(E3:E5) *100 -> 93.75 | F2: =SUM(F3:F4) / SUM(F3:F5) *100 -> 81.25 | G2: =SUM(G3:G4) / SUM(G3:G5) *100 -> 81.25 | H2: =SUM(H3:H4) / SUM(H3:H5) *100 -> 81.25 | J2: Chatbot run 1 | Q2: Chatbot run 1
A3: Semantic TP Explicit | C3: =COUNTIF(C10:C25, 2) -> 15 | D3: =COUNTIF(D10:D25, 2) -> 15 | E3: =COUNTIF(E10:E25, 2) -> 15 | F3: =COUNTIF(F10:F25, 2) -> 13 | G3: =COUNTIF(G10:G25, 2) -> 13 | H3: =COUNTIF(H10:H25, 2) -> 13 | J3: Chatbot run 2 | K3: {=IFERROR(SUMPRODUCT((C10:C100<>"")*(D10:D100<>"")*(C10:C100=D10:D100))/SUMPRODUCT(--((C10:C100<>"")+(D10:D100<>"")>0)),"")} -> 1 | Q3: Chatbot run 2 | R3: {=IFERROR( SUMPRODUCT((C10:C100<>"")*(D10:D100<>"")* ((C10:C100=D10:D100)+((C10:C100=1)*(D10:D100=2))+((C10:C100=2)*(D10:D100=1)))) / SUMPRODUCT(--((C10:C100<>"")+(D10:D100<>"")>0)), "")} -> 1
A4: Semantic TP Implicit | C4: =COUNTIF(C10:C25, 1) -> 0 | D4: =COUNTIF(D10:D25, 1) -> 0 | E4: =COUNTIF(E10:E25, 1) -> 0 | F4: =COUNTIF(F10:F25, 1) -> 0 | G4: =COUNTIF(G10:G25, 1) -> 0 | H4: =COUNTIF(H10:H25, 1) -> 0 | J4: Chatbot run 3 | K4: {=IFERROR(SUMPRODUCT((C10:C100<>"")*(E10:E100<>"")*(C10:C100=E10:E100))/SUMPRODUCT(--((C10:C100<>"")+(E10:E100<>"")>0)),"")} -> 0.95238095 | L4: {=IFERROR(SUMPRODUCT((E10:E100<>"")*(D10:D100<>"")*(E10:E100=D10:D100))/SUMPRODUCT(--((E10:E100<>"")+(D10:D100<>"")>0)),"")} -> 0.95238095 | Q4: Chatbot run 3 | R4: {=IFERROR( SUMPRODUCT((C10:C100<>"")*(E10:E100<>"")* ((C10:C100=E10:E100)+((C10:C100=1)*(E10:E100=2))+((C10:C100=2)*(E10:E100=1)))) / SUMPRODUCT(--((C10:C100<>"")+(E10:E100<>"")>0)), "")} -> 0.95238095 | S4: {=IFERROR( SUMPRODUCT((E10:E100<>"")*(D10:D100<>"")* ((E10:E100=D10:D100)+((E10:E100=1)*(D10:D100=2))+((E10:E100=2)*(D10:D100=1)))) / SUMPRODUCT(--((E10:E100<>"")+(D10:D100<>"")>0)), "")} -> 0.95238095
A5: Semantic FN | C5: =COUNTIF(C10:C25, 0) -> 1 | D5: =COUNTIF(D10:D25, 0) -> 1 | E5: =COUNTIF(E10:E25, 0) -> 1 | F5: =COUNTIF(F10:F25, 0) -> 3 | G5: =COUNTIF(G10:G25, 0) -> 3 | H5: =COUNTIF(H10:H25, 0) -> 3 | J5: XML run 1 | K5: {=IFERROR(SUMPRODUCT((C10:C100<>"")*(F10:F100<>"")*(C10:C100=F10:F100))/SUMPRODUCT(--((C10:C100<>"")+(F10:F100<>"")>0)),"")} -> 0.58333333 | L5: {=IFERROR(SUMPRODUCT((F10:F100<>"")*(D10:D100<>"")*(F10:F100=D10:D100))/SUMPRODUCT(--((F10:F100<>"")+(D10:D100<>"")>0)),"")} -> 0.58333333 | M5: {=IFERROR(SUMPRODUCT((F10:F100<>"")*(E10:E100<>"")*(F10:F100=E10:E100))/SUMPRODUCT(--((F10:F100<>"")+(E10:E100<>"")>0)),"")} -> 0.60869565 | Q5: XML run 1 | R5: {=IFERROR( SUMPRODUCT((C10:C100<>"")*(F10:F100<>"")* ((C10:C100=F10:F100)+((C10:C100=1)*(F10:F100=2))+((C10:C100=2)*(F10:F100=1)))) / SUMPRODUCT(--((C10:C100<>"")+(F10:F100<>"")>0)), "")} -> 0.58333333 | S5: {=IFERROR( SUMPRODUCT((F10:F100<>"")*(D10:D100<>"")* ((F10:F100=D10:D100)+((F10:F100=1)*(D10:D100=2))+((F10:F100=2)*(D10:D100=1)))) / SUMPRODUCT(--((F10:F100<>"")+(D10:D100<>"")>0)), "")} -> 0.58333333 | T5: {=IFERROR( SUMPRODUCT((F10:F100<>"")*(E10:E100<>"")* ((F10:F100=E10:E100)+((F10:F100=1)*(E10:E100=2))+((F10:F100=2)*(E10:E100=1)))) / SUMPRODUCT(--((F10:F100<>"")+(E10:E100<>"")>0)), "")} -> 0.60869565
A6: Semantic FP Strict | C6: =COUNTIF(C27:C58,0) + COUNTIF(C27:C58,1) -> 5 | D6: =COUNTIF(D27:D58,0) + COUNTIF(D27:D58,1) -> 5 | E6: =COUNTIF(E27:E58,0) + COUNTIF(E27:E58,1) -> 4 | F6: =COUNTIF(F27:F58,0) + COUNTIF(F27:F58,1) -> 3 | G6: =COUNTIF(G27:G58,0) + COUNTIF(G27:G58,1) -> 7 | H6: =COUNTIF(H27:H58,0) + COUNTIF(H27:H58,1) -> 0 | J6: XML run 2 | K6: {=IFERROR(SUMPRODUCT((C10:C100<>"")*(G10:G100<>"")*(C10:C100=G10:G100))/SUMPRODUCT(--((C10:C100<>"")+(G10:G100<>"")>0)),"")} -> 0.5 | L6: {=SUMPRODUCT((D10:D100<>0)*(G10:G100<>0)) / SUMPRODUCT(((D10:D100<>0)+(G10:G100<>0)>0)*1)} -> 0.52 | M6: {=IFERROR(SUMPRODUCT((G10:G100<>"")*(E10:E100<>"")*(G10:G100=E10:E100))/SUMPRODUCT(--((G10:G100<>"")+(E10:E100<>"")>0)),"")} -> 0.51851852 | N6: {=IFERROR(SUMPRODUCT((G10:G100<>"")*(F10:F100<>"")*(G10:G100=F10:F100))/SUMPRODUCT(--((G10:G100<>"")+(F10:F100<>"")>0)),"")} -> 0.75 | Q6: XML run 2 | R6: {=IFERROR( SUMPRODUCT((C10:C100<>"")*(G10:G100<>"")* ((C10:C100=G10:G100)+((C10:C100=1)*(G10:G100=2))+((C10:C100=2)*(G10:G100=1)))) / SUMPRODUCT(--((C10:C100<>"")+(G10:G100<>"")>0)), "")} -> 0.5 | S6: {=IFERROR( SUMPRODUCT((D10:D100<>"")*(G10:G100<>"")* ((D10:D100=G10:G100)+((D10:D100=1)*(G10:G100=2))+((D10:D100=2)*(G10:G100=1)))) / SUMPRODUCT(--((D10:D100<>"")+(G10:G100<>"")>0)), "")} -> 0.5 | T6: {=IFERROR( SUMPRODUCT((G10:G100<>"")*(E10:E100<>"")* ((G10:G100=E10:E100)+((G10:G100=1)*(E10:E100=2))+((G10:G100=2)*(E10:E100=1)))) / SUMPRODUCT(--((G10:G100<>"")+(E10:E100<>"")>0)), "")} -> 0.51851852 | U6: {=IFERROR( SUMPRODUCT((F10:F100<>"")*(G10:G100<>"")* ((F10:F100=G10:G100)+((F10:F100=1)*(G10:G100=2))+((F10:F100=2)*(G10:G100=1)))) / SUMPRODUCT(--((F10:F100<>"")+(G10:G100<>"")>0)), "")} -> 0.75
A7: Semantic FP Loose | C7: =COUNTIF(C27:C58,0) -> 0 | D7: =COUNTIF(D27:D58,0) -> 0 | E7: =COUNTIF(E27:E58,0) -> 0 | F7: =COUNTIF(F27:F58,0) -> 1 | G7: =COUNTIF(G27:G58,0) -> 2 | H7: =COUNTIF(H27:H58,0) -> 0 | J7: XML run 3 | K7: {=IFERROR(SUMPRODUCT((C10:C100<>"")*(H10:H100<>"")*(C10:C100=H10:H100))/SUMPRODUCT(--((C10:C100<>"")+(H10:H100<>"")>0)),"")} -> 0.66666667 | L7: {=IFERROR(SUMPRODUCT((H10:H100<>"")*(D10:D100<>"")*(H10:H100=D10:D100))/SUMPRODUCT(--((H10:H100<>"")+(D10:D100<>"")>0)),"")} -> 0.66666667 | M7: {=IFERROR(SUMPRODUCT((H10:H100<>"")*(E10:E100<>"")*(H10:H100=E10:E100))/SUMPRODUCT(--((H10:H100<>"")+(E10:E100<>"")>0)),"")} -> 0.7 | N7: {=IFERROR(SUMPRODUCT((F10:F100<>"")*(H10:H100<>"")*(F10:F100=H10:H100))/SUMPRODUCT(--((F10:F100<>"")+(H10:H100<>"")>0)),"")} -> 0.84210526 | O7: {=IFERROR(SUMPRODUCT((G10:G100<>"")*(H10:H100<>"")*(G10:G100=H10:H100))/SUMPRODUCT(--((G10:G100<>"")+(H10:H100<>"")>0)),"")} -> 0.69565217 | Q7: XML run 3 | R7: {=IFERROR( SUMPRODUCT((C10:C100<>"")*(H10:H100<>"")* ((C10:C100=H10:H100)+((C10:C100=1)*(H10:H100=2))+((C10:C100=2)*(H10:H100=1)))) / SUMPRODUCT(--((C10:C100<>"")+(H10:H100<>"")>0)), "")} -> 0.66666667 | S7: {=IFERROR( SUMPRODUCT((H10:H100<>"")*(D10:D100<>"")* ((H10:H100=D10:D100)+((H10:H100=1)*(D10:D100=2))+((H10:H100=2)*(D10:D100=1)))) / SUMPRODUCT(--((H10:H100<>"")+(D10:D100<>"")>0)), "")} -> 0.66666667 | T7: {=IFERROR( SUMPRODUCT((H10:H100<>"")*(E10:E100<>"")* ((H10:H100=E10:E100)+((H10:H100=1)*(E10:E100=2))+((H10:H100=2)*(E10:E100=1)))) / SUMPRODUCT(--((H10:H100<>"")+(E10:E100<>"")>0)), "")} -> 0.7 | U7: {=IFERROR( SUMPRODUCT((F10:F100<>"")*(H10:H100<>"")* ((F10:F100=H10:H100)+((F10:F100=1)*(H10:H100=2))+((F10:F100=2)*(H10:H100=1)))) / SUMPRODUCT(--((F10:F100<>"")+(H10:H100<>"")>0)), "")} -> 0.84210526 | V7: {=IFERROR( SUMPRODUCT((H10:H100<>"")*(G10:G100<>"")* ((H10:H100=G10:G100)+((H10:H100=1)*(G10:G100=2))+((H10:H100=2)*(G10:G100=1)))) / SUMPRODUCT(--((H10:H100<>"")+(G10:G100<>"")>0)), "")} -> 0.69565217
C9: Chatbot run 1 | D9: Chatbot run 2 | E9: Chatbot run 3 | F9: XML run 1 | G9: XML run 2 | H9: XML run 3
A10: Pools | B10: Company | C10: 2 | D10: 2 | E10: 2 | F10: 2 | G10: 2 | H10: 2
A11: Lane | B11: Secretary | C11: 2 | D11: 2 | E11: 2 | F11: 2 | G11: 2 | H11: 2
B12: Logistics Department Head | C12: 2 | D12: 2 | E12: 2 | F12: 2 | G12: 2 | H12: 2
B13: Warehouseman | C13: 2 | D13: 2 | E13: 2 | F13: 2 | G13: 2 | H13: 2
A14: Tasks/Messages/Events | B14: Clarify Shipping Type | C14: 2 | D14: 2 | E14: 2 | F14: 2 | G14: 2 | H14: 2
B15: Invite 3 Logistic Companies for Offers | C15: 2 | D15: 2 | E15: 2 | F15: 2 | G15: 2 | H15: 2
B16: Select Logistics Company | C16: 2 | D16: 2 | E16: 2 | F16: 2 | G16: 2 | H16: 2
B17: Write Package Label | C17: 2 | D17: 2 | E17: 2 | F17: 2 | G17: 2 | H17: 2
B18: Take Parcel Insurance | C18: 2 | D18: 2 | E18: 2 | F18: 2 | G18: 2 | H18: 2
B19: Package Goods | C19: 2 | D19: 2 | E19: 2 | F19: 2 | G19: 2 | H19: 2
B20: Prepare Packaged Goods for Pickup | C20: 2 | D20: 2 | E20: 2 | F20: 2 | G20: 2 | H20: 2
A21: Conditions/Loops/Parallel | B21: Large or Small Amounts? | C21: 2 | D21: 2 | E21: 2 | F21: 2 | G21: 2 | H21: 2
B22: Parcel Insurance necessary? | C22: 2 | D22: 2 | E22: 2 | F22: 2 | G22: 2 | H22: 2
B23: Write Package Label || Packing | C23: 0 | D23: 0 | E23: 0 | F23: 0 | G23: 0 | H23: 0
A24: Data Objects/ Messages | B24: Logistics Offers | C24: 2 | D24: 2 | E24: 2 | F24: 0 | G24: 0 | H24: 0
B25: Package Label | C25: 2 | D25: 2 | E25: 2 | F25: 0 | G25: 0 | H25: 0
B27: Shipping Type DO | C27: 1 | D27: 1 | E27: 1
B28: Selected Logistics Company DO | C28: 1 | D28: 1 | E28: 1
B29: Parcel Insurance DO | C29: 1 | D29: 1 | E29: 1
B30: Packaged Goods DO | C30: 1 | D30: 1
B31: Goods DO | C31: 1 | D31: 1 | E31: 1
B32: Logistics Company Pool | F32: 1 | G32: 1
B33: Send pickup request | F33: 1 | G33: 1
B34: Send pickup request to post | F34: 0
B35: Goods picked up Event | G35: 1
B36: Packaging || Pickup | G36: 0
B37: Pick up goods | G37: 1
B38: Receive pickup request | G38: 1
B39: Send pickup confirmation | G39: 0

Sheet c12
A1: Semantic Percision | C1: =SUM(C3:C4) / (C3+ C4+ C7) * 100 -> 93.333333 | D1: =SUM(D3:D4) / (D3+ D4+ D7) * 100 -> 100 | E1: =SUM(E3:E4) / (E3+ E4+ E7) * 100 -> 100 | F1: =SUM(F3:F4) / (F3+ F4+ F7) * 100 -> 100 | G1: =SUM(G3:G4) / (G3+ G4+ G7) * 100 -> 94.444444 | H1: =SUM(H3:H4) / (H3+ H4+ H7) * 100 -> 100 | J1: Jaccard Strict | K1: Chatbot run 1 | L1: Chatbot run 2 | M1: Chatbot run 3 | N1: XML run 1 | O1: XML run 2 | P1: XML run 3 | Q1: Jaccard Loose | R1: Chatbot run 1 | S1: Chatbot run 2 | T1: Chatbot run 3 | U1: XML run 1 | V1: XML run 2 | W1: XML run 3
A2: Semantic Recall | C2: =SUM(C3:C4) / SUM(C3:C5) *100 -> 96.551724 | D2: =SUM(D3:D4) / SUM(D3:D5) *100 -> 93.103448 | E2: =SUM(E3:E4) / SUM(E3:E5) *100 -> 93.103448 | F2: =SUM(F3:F4) / SUM(F3:F5) *100 -> 79.310345 | G2: =SUM(G3:G4) / SUM(G3:G5) *100 -> 58.62069 | H2: =SUM(H3:H4) / SUM(H3:H5) *100 -> 48.275862 | J2: Chatbot run 1 | Q2: Chatbot run 1
A3: Semantic TP Explicit | C3: =COUNTIF(C10:C38, 2) -> 28 | D3: =COUNTIF(D10:D38, 2) -> 26 | E3: =COUNTIF(E10:E38, 2) -> 26 | F3: =COUNTIF(F10:F38, 2) -> 22 | G3: =COUNTIF(G10:G38, 2) -> 15 | H3: =COUNTIF(H10:H38, 2) -> 14 | J3: Chatbot run 2 | K3: {=IFERROR(SUMPRODUCT((C10:C100<>"")*(D10:D100<>"")*(C10:C100=D10:D100))/SUMPRODUCT(--((C10:C100<>"")+(D10:D100<>"")>0)),"")} -> 0.70731707 | Q3: Chatbot run 2 | R3: {=IFERROR( SUMPRODUCT((C10:C100<>"")*(D10:D100<>"")* ((C10:C100=D10:D100)+((C10:C100=1)*(D10:D100=2))+((C10:C100=2)*(D10:D100=1)))) / SUMPRODUCT(--((C10:C100<>"")+(D10:D100<>"")>0)), "")} -> 0.73170732
A4: Semantic TP Implicit | C4: =COUNTIF(C10:C38, 1) -> 0 | D4: =COUNTIF(D10:D38, 1) -> 1 | E4: =COUNTIF(E10:E38, 1) -> 1 | F4: =COUNTIF(F10:F38, 1) -> 1 | G4: =COUNTIF(G10:G38, 1) -> 2 | H4: =COUNTIF(H10:H38, 1) -> 0 | J4: Chatbot run 3 | K4: {=IFERROR(SUMPRODUCT((C10:C100<>"")*(E10:E100<>"")*(C10:C100=E10:E100))/SUMPRODUCT(--((C10:C100<>"")+(E10:E100<>"")>0)),"")} -> 0.7 | L4: {=IFERROR(SUMPRODUCT((E10:E100<>"")*(D10:D100<>"")*(E10:E100=D10:D100))/SUMPRODUCT(--((E10:E100<>"")+(D10:D100<>"")>0)),"")} -> 0.89189189 | Q4: Chatbot run 3 | R4: {=IFERROR( SUMPRODUCT((C10:C100<>"")*(E10:E100<>"")* ((C10:C100=E10:E100)+((C10:C100=1)*(E10:E100=2))+((C10:C100=2)*(E10:E100=1)))) / SUMPRODUCT(--((C10:C100<>"")+(E10:E100<>"")>0)), "")} -> 0.725 | S4: {=IFERROR( SUMPRODUCT((E10:E100<>"")*(D10:D100<>"")* ((E10:E100=D10:D100)+((E10:E100=1)*(D10:D100=2))+((E10:E100=2)*(D10:D100=1)))) / SUMPRODUCT(--((E10:E100<>"")+(D10:D100<>"")>0)), "")} -> 0.89189189
A5: Semantic FN | C5: =COUNTIF(C10:C38, 0) -> 1 | D5: =COUNTIF(D10:D38, 0) -> 2 | E5: =COUNTIF(E10:E38, 0) -> 2 | F5: =COUNTIF(F10:F38, 0) -> 6 | G5: =COUNTIF(G10:G38, 0) -> 12 | H5: =COUNTIF(H10:H38, 0) -> 15 | J5: XML run 1 | K5: {=IFERROR(SUMPRODUCT((C10:C100<>"")*(F10:F100<>"")*(C10:C100=F10:F100))/SUMPRODUCT(--((C10:C100<>"")+(F10:F100<>"")>0)),"")} -> 0.61538462 | L5: {=IFERROR(SUMPRODUCT((F10:F100<>"")*(D10:D100<>"")*(F10:F100=D10:D100))/SUMPRODUCT(--((F10:F100<>"")+(D10:D100<>"")>0)),"")} -> 0.65789474 | M5: {=IFERROR(SUMPRODUCT((F10:F100<>"")*(E10:E100<>"")*(F10:F100=E10:E100))/SUMPRODUCT(--((F10:F100<>"")+(E10:E100<>"")>0)),"")} -> 0.60526316 | Q5: XML run 1 | R5: {=IFERROR( SUMPRODUCT((C10:C100<>"")*(F10:F100<>"")* ((C10:C100=F10:F100)+((C10:C100=1)*(F10:F100=2))+((C10:C100=2)*(F10:F100=1)))) / SUMPRODUCT(--((C10:C100<>"")+(F10:F100<>"")>0)), "")} -> 0.64102564 | S5: {=IFERROR( SUMPRODUCT((F10:F100<>"")*(D10:D100<>"")* ((F10:F100=D10:D100)+((F10:F100=1)*(D10:D100=2))+((F10:F100=2)*(D10:D100=1)))) / SUMPRODUCT(--((F10:F100<>"")+(D10:D100<>"")>0)), "")} -> 0.71052632 | T5: {=IFERROR( SUMPRODUCT((F10:F100<>"")*(E10:E100<>"")* ((F10:F100=E10:E100)+((F10:F100=1)*(E10:E100=2))+((F10:F100=2)*(E10:E100=1)))) / SUMPRODUCT(--((F10:F100<>"")+(E10:E100<>"")>0)), "")} -> 0.65789474
A6: Semantic FP Strict | C6: =COUNTIF(C40:C72,0) + COUNTIF(C40:C72,1) -> 7 | D6: =COUNTIF(D40:D72,0) + COUNTIF(D40:D72,1) -> 7 | E6: =COUNTIF(E40:E72,0) + COUNTIF(E40:E72,1) -> 5 | F6: =COUNTIF(F40:F72,0) + COUNTIF(F40:F72,1) -> 4 | G6: =COUNTIF(G40:G72,0) + COUNTIF(G40:G72,1) -> 5 | H6: =COUNTIF(H40:H72,0) + COUNTIF(H40:H72,1) -> 3 | J6: XML run 2 | K6: {=IFERROR(SUMPRODUCT((C10:C100<>"")*(G10:G100<>"")*(C10:C100=G10:G100))/SUMPRODUCT(--((C10:C100<>"")+(G10:G100<>"")>0)),"")} -> 0.46153846 | L6: {=SUMPRODUCT((D10:D100<>0)*(G10:G100<>0)) / SUMPRODUCT(((D10:D100<>0)+(G10:G100<>0)>0)*1)} -> 0.52777778 | M6: {=IFERROR(SUMPRODUCT((G10:G100<>"")*(E10:E100<>"")*(G10:G100=E10:E100))/SUMPRODUCT(--((G10:G100<>"")+(E10:E100<>"")>0)),"")} -> 0.48648649 | N6: {=IFERROR(SUMPRODUCT((G10:G100<>"")*(F10:F100<>"")*(G10:G100=F10:F100))/SUMPRODUCT(--((G10:G100<>"")+(F10:F100<>"")>0)),"")} -> 0.66666667 | Q6: XML run 2 | R6: {=IFERROR( SUMPRODUCT((C10:C100<>"")*(G10:G100<>"")* ((C10:C100=G10:G100)+((C10:C100=1)*(G10:G100=2))+((C10:C100=2)*(G10:G100=1)))) / SUMPRODUCT(--((C10:C100<>"")+(G10:G100<>"")>0)), "")} -> 0.51282051 | S6: {=IFERROR( SUMPRODUCT((D10:D100<>"")*(G10:G100<>"")* ((D10:D100=G10:G100)+((D10:D100=1)*(G10:G100=2))+((D10:D100=2)*(G10:G100=1)))) / SUMPRODUCT(--((D10:D100<>"")+(G10:G100<>"")>0)), "")} -> 0.53846154 | T6: {=IFERROR( SUMPRODUCT((G10:G100<>"")*(E10:E100<>"")* ((G10:G100=E10:E100)+((G10:G100=1)*(E10:E100=2))+((G10:G100=2)*(E10:E100=1)))) / SUMPRODUCT(--((G10:G100<>"")+(E10:E100<>"")>0)), "")} -> 0.56756757 | U6: {=IFERROR( SUMPRODUCT((F10:F100<>"")*(G10:G100<>"")* ((F10:F100=G10:G100)+((F10:F100=1)*(G10:G100=2))+((F10:F100=2)*(G10:G100=1)))) / SUMPRODUCT(--((F10:F100<>"")+(G10:G100<>"")>0)), "")} -> 0.69444444
A7: Semantic FP Loose | C7: =COUNTIF(C40:C72,0) -> 2 | D7: =COUNTIF(D40:D72,0) -> 0 | E7: =COUNTIF(E40:E72,0) -> 0 | F7: =COUNTIF(F40:F72,0) -> 0 | G7: =COUNTIF(G40:G72,0) -> 1 | H7: =COUNTIF(H40:H72,0) -> 0 | J7: XML run 3 | K7: {=IFERROR(SUMPRODUCT((C10:C100<>"")*(H10:H100<>"")*(C10:C100=H10:H100))/SUMPRODUCT(--((C10:C100<>"")+(H10:H100<>"")>0)),"")} -> 0.42105263 | L7: {=IFERROR(SUMPRODUCT((H10:H100<>"")*(D10:D100<>"")*(H10:H100=D10:D100))/SUMPRODUCT(--((H10:H100<>"")+(D10:D100<>"")>0)),"")} -> 0.45945946 | M7: {=IFERROR(SUMPRODUCT((H10:H100<>"")*(E10:E100<>"")*(H10:H100=E10:E100))/SUMPRODUCT(--((H10:H100<>"")+(E10:E100<>"")>0)),"")} -> 0.44444444 | N7: {=IFERROR(SUMPRODUCT((F10:F100<>"")*(H10:H100<>"")*(F10:F100=H10:H100))/SUMPRODUCT(--((F10:F100<>"")+(H10:H100<>"")>0)),"")} -> 0.64705882 | O7: {=IFERROR(SUMPRODUCT((G10:G100<>"")*(H10:H100<>"")*(G10:G100=H10:H100))/SUMPRODUCT(--((G10:G100<>"")+(H10:H100<>"")>0)),"")} -> 0.8 | Q7: XML run 3 | R7: {=IFERROR( SUMPRODUCT((C10:C100<>"")*(H10:H100<>"")* ((C10:C100=H10:H100)+((C10:C100=1)*(H10:H100=2))+((C10:C100=2)*(H10:H100=1)))) / SUMPRODUCT(--((C10:C100<>"")+(H10:H100<>"")>0)), "")} -> 0.42105263 | S7: {=IFERROR( SUMPRODUCT((H10:H100<>"")*(D10:D100<>"")* ((H10:H100=D10:D100)+((H10:H100=1)*(D10:D100=2))+((H10:H100=2)*(D10:D100=1)))) / SUMPRODUCT(--((H10:H100<>"")+(D10:D100<>"")>0)), "")} -> 0.48648649 | T7: {=IFERROR( SUMPRODUCT((H10:H100<>"")*(E10:E100<>"")* ((H10:H100=E10:E100)+((H10:H100=1)*(E10:E100=2))+((H10:H100=2)*(E10:E100=1)))) / SUMPRODUCT(--((H10:H100<>"")+(E10:E100<>"")>0)), "")} -> 0.47222222 | U7: {=IFERROR( SUMPRODUCT((F10:F100<>"")*(H10:H100<>"")* ((F10:F100=H10:H100)+((F10:F100=1)*(H10:H100=2))+((F10:F100=2)*(H10:H100=1)))) / SUMPRODUCT(--((F10:F100<>"")+(H10:H100<>"")>0)), "")} -> 0.64705882 | V7: {=IFERROR( SUMPRODUCT((H10:H100<>"")*(G10:G100<>"")* ((H10:H100=G10:G100)+((H10:H100=1)*(G10:G100=2))+((H10:H100=2)*(G10:G100=1)))) / SUMPRODUCT(--((H10:H100<>"")+(G10:G100<>"")>0)), "")} -> 0.8
C9: Chatbot run 1 | D9: Chatbot run 2 | E9: Chatbot run 3 | F9: XML run 1 | G9: XML run 2 | H9: XML run 3
A10: Pools / Lanes | B10: Student | C10: 2 | D10: 2 | E10: 2 | F10: 0 | G10: 0 | H10: 0
B11: University | C11: 2 | D11: 2 | E11: 2 | F11: 0 | G11: 0 | H11: 0
B12: Academic Committee (Pool or lane) | C12: 2 | D12: 2 | E12: 2 | F12: 2 | G12: 0 | H12: 0
B13: Officer | C13: 2 | D13: 2 | E13: 2 | F13: 2 | G13: 0 | H13: 0
B14: Committee Members | C14: 2 | D14: 2 | E14: 2 | F14: 0 | G14: 0 | H14: 0
B15: Committee Chair | C15: 2 | D15: 0 | E15: 0 | F15: 0 | G15: 0 | H15: 0
A16: Tasks/Messages/Events | B16: Fill Online Application Form | C16: 2 | D16: 2 | E16: 2 | F16: 2 | G16: 2 | H16: 2
B17: Submit Online Application Form | C17: 2 | D17: 2 | E17: 2 | F17: 0 | G17: 0 | H17: 0
B18: Record Online Application in Admission Information System | C18: 2 | D18: 2 | E18: 2 | F18: 2 | G18: 2 | H18: 0
B19: Download Generated PDF | C19: 2 | D19: 2 | E19: 2 | F19: 2 | G19: 2 | H19: 2
B20: Sign PDF | C20: 2 | D20: 2 | E20: 2 | F20: 2 | G20: 2 | H20: 2
B21: Send Documents by Post | C21: 2 | D21: 2 | E21: 2 | F21: 2 | G21: 2 | H21: 2
B22: Receive Documents | C22: 2 | D22: 2 | E22: 2 | F22: 2 | G22: 2 | H22: 2
B23: Reject Application | C23: 2 | D23: 2 | E23: 2 | F23: 2 | G23: 2 | H23: 2
B24: Forward Documents to Academic Committee | C24: 2 | D24: 2 | E24: 2 | F24: 2 | G24: 2 | H24: 2
B25: Once a month timer | C25: 2 | D25: 2 | E25: 2 | F25: 2 | G25: 2 | H25: 2
B26: Meet to Assess Applications | C26: 2 | D26: 2 | E26: 2 | F26: 2 | G26: 2 | H26: 2
B27: Notify Admissions Office of Selection Outcomes | C27: 2 | D27: 2 | E27: 2 | F27: 2 | G27: 2 | H27: 2
B28: Wait a few days | C28: 0 | D28: 0 | E28: 0 | F28: 0 | G28: 0 | H28: 0
... B31: Send Rejection Email | C31: 2 | D31: 2 | E31: 2 | F31: 2 | G31: 2 | H31: 2
A32: Conditions/Loops/Parallel | B32: Sufficient Grades? | C32: 2 | D32: 2 | E32: 2 | F32: 2 | G32: 2 | H32: 2
B33: If admitted? | C33: 2 | D33: 2 | E33: 2 | F33: 2 | G33: 0 | H33: 0
A34: Data Objects/ Messages | B34: Admission Information System | C34: 2 | D34: 1 | E34: 1 | F34: 2 | G34: 2 | H34: 2
B35: Letter of Motivation | C35: 2 | D35: 2 | E35: 2 | F35: 2 | G35: 0 | H35: 0
B36: Transcript of Grades | C36: 2 | D36: 2 | E36: 2 | F36: 2 | G36: 0 | H36: 0
B37: Selection Outcomes | C37: 2 | D37: 2 | E37: 2 | F37: 1 | G37: 1 | H37: 0
B38: Application PDF | C38: 2 | D38: 2 | E38: 2 | F38: 2 | G38: 1 | H38: 0
B40: Prepare Transcript and Motivation Letter | C40: 1
B41: Notify Academic Committee of Application Ready | C41: 0
B42: Receive Notification of Application Ready (start event) | C42: 0
B43: Send Selection Outcomes to Admissions Office | C43: 1
B44: Receive Selection Outcomes from Committee Chair | C44: 1 | D44: 1 | F44: 1 | G44: 1 | H44: 1
B45: Decide on Admission | C45: 1
B46: Online Application DO | C46: 1 | D46: 1 | E46: 1 | G46: 1
B47: Initial Assessment | D47: 1 | F47: 1 | H47: 1
B48: PersonalDataObj | F48: 1
B49: StudentDocuments | F49: 1 | G49: 1
B50: SupportingDocs | G50: 0
B51: Receive Documents from Admissions | E51: 1 | G51: 1 | H51: 1
B52: Prepare Rejection Notification | D52: 1 | E52: 1
B53: Record Selection Outcomes | D53: 1
B54: Prepare Rejection Email | D54: 1 | E54: 1
B55: Prepare Admission Email | D55: 1 | E55: 1

Sheet c13
A1: Semantic Percision | C1: =SUM(C3:C4) / (C3+ C4+ C7) * 100 -> 100 | D1: =SUM(D3:D4) / (D3+ D4+ D7) * 100 -> 85.714286 | E1: =SUM(E3:E4) / (E3+ E4+ E7) * 100 -> 100 | F1: =SUM(F3:F4) / (F3+ F4+ F7) * 100 -> 75 | G1: =SUM(G3:G4) / (G3+ G4+ G7) * 100 -> 92.307692 | H1: =SUM(H3:H4) / (H3+ H4+ H7) * 100 -> 100 | J1: Jaccard Strict | K1: Chatbot run 1 | L1: Chatbot run 2 | M1: Chatbot run 3 | N1: XML run 1 | O1: XML run 2 | P1: XML run 3 | Q1: Jaccard Loose | R1: Chatbot run 1 | S1: Chatbot run 2 | T1: Chatbot run 3 | U1: XML run 1 | V1: XML run 2 | W1: XML run 3
A2: Semantic Recall | C2: =SUM(C3:C4) / SUM(C3:C5) *100 -> 76.470588 | D2: =SUM(D3:D4) / SUM(D3:D5) *100 -> 70.588235 | E2: =SUM(E3:E4) / SUM(E3:E5) *100 -> 64.705882 | F2: =SUM(F3:F4) / SUM(F3:F5) *100 -> 70.588235 | G2: =SUM(G3:G4) / SUM(G3:G5) *100 -> 70.588235 | H2: =SUM(H3:H4) / SUM(H3:H5) *100 -> 70.588235 | J2: Chatbot run 1 | Q2: Chatbot run 1
A3: Semantic TP Explicit | C3: =COUNTIF(C10:C26, 2) -> 12 | D3: =COUNTIF(D10:D26, 2) -> 12 | E3: =COUNTIF(E10:E26, 2) -> 11 | F3: =COUNTIF(F10:F26, 2) -> 11 | G3: =COUNTIF(G10:G26, 2) -> 8 | H3: =COUNTIF(H10:H26, 2) -> 10 | J3: Chatbot run 2 | K3: {=IFERROR(SUMPRODUCT((C10:C86<>"")*(D10:D86<>"")*(C10:C86=D10:D86))/SUMPRODUCT(--((C10:C86<>"")+(D10:D86<>"")>0)),"")} -> 0.63636364 | Q3: Chatbot run 2 | R3: {=IFERROR( SUMPRODUCT((C10:C86<>"")*(D10:D86<>"")* ((C10:C86=D10:D86)+((C10:C86=1)*(D10:D86=2))+((C10:C86=2)*(D10:D86=1)))) / SUMPRODUCT(--((C10:C86<>"")+(D10:D86<>"")>0)), "")} -> 0.63636364
A4: Semantic TP Implicit | C4: =COUNTIF(C10:C26, 1) -> 1 | D4: =COUNTIF(D10:D26, 1) -> 0 | E4: =COUNTIF(E10:E26, 1) -> 0 | F4: =COUNTIF(F10:F26, 1) -> 1 | G4: =COUNTIF(G10:G26, 1) -> 4 | H4: =COUNTIF(H10:H26, 1) -> 2 | J4: Chatbot run 3 | K4: {=IFERROR(SUMPRODUCT((C10:C86<>"")*(E10:E86<>"")*(C10:C86=E10:E86))/SUMPRODUCT(--((C10:C86<>"")+(E10:E86<>"")>0)),"")} -> 0.51724138 | L4: {=IFERROR(SUMPRODUCT((E10:E86<>"")*(D10:D86<>"")*(E10:E86=D10:D86))/SUMPRODUCT(--((E10:E86<>"")+(D10:D86<>"")>0)),"")} -> 0.42857143 | Q4: Chatbot run 3 | R4: {=IFERROR( SUMPRODUCT((C10:C86<>"")*(E10:E86<>"")* ((C10:C86=E10:E86)+((C10:C86=1)*(E10:E86=2))+((C10:C86=2)*(E10:E86=1)))) / SUMPRODUCT(--((C10:C86<>"")+(E10:E86<>"")>0)), "")} -> 0.51724138 | S4: {=IFERROR( SUMPRODUCT((E10:E86<>"")*(D10:D86<>"")* ((E10:E86=D10:D86)+((E10:E86=1)*(D10:D86=2))+((E10:E86=2)*(D10:D86=1)))) / SUMPRODUCT(--((E10:E86<>"")+(D10:D86<>"")>0)), "")} -> 0.42857143
A5: Semantic FN | C5: =COUNTIF(C10:C26, 0) -> 4 | D5: =COUNTIF(D10:D26, 0) -> 5 | E5: =COUNTIF(E10:E26, 0) -> 6 | F5: =COUNTIF(F10:F26, 0) -> 5 | G5: =COUNTIF(G10:G26, 0) -> 5 | H5: =COUNTIF(H10:H26, 0) -> 5 | J5: XML run 1 | K5: {=IFERROR(SUMPRODUCT((C10:C86<>"")*(F10:F86<>"")*(C10:C86=F10:F86))/SUMPRODUCT(--((C10:C86<>"")+(F10:F86<>"")>0)),"")} -> 0.53125 | L5: {=IFERROR(SUMPRODUCT((F10:F86<>"")*(D10:D86<>"")*(F10:F86=D10:D86))/SUMPRODUCT(--((F10:F86<>"")+(D10:D86<>"")>0)),"")} -> 0.57142857 | M5: {=IFERROR(SUMPRODUCT((F10:F86<>"")*(E10:E86<>"")*(F10:F86=E10:E86))/SUMPRODUCT(--((F10:F86<>"")+(E10:E86<>"")>0)),"")} -> 0.36363636 | Q5: XML run 1 | R5: {=IFERROR( SUMPRODUCT((C10:C86<>"")*(F10:F86<>"")* ((C10:C86=F10:F86)+((C10:C86=1)*(F10:F86=2))+((C10:C86=2)*(F10:F86=1)))) / SUMPRODUCT(--((C10:C86<>"")+(F10:F86<>"")>0)), "")} -> 0.5625 | S5: {=IFERROR( SUMPRODUCT((F10:F86<>"")*(D10:D86<>"")* ((F10:F86=D10:D86)+((F10:F86=1)*(D10:D86=2))+((F10:F86=2)*(D10:D86=1)))) / SUMPRODUCT(--((F10:F86<>"")+(D10:D86<>"")>0)), "")} -> 0.6 | T5: {=IFERROR( SUMPRODUCT((F10:F86<>"")*(E10:E86<>"")* ((F10:F86=E10:E86)+((F10:F86=1)*(E10:E86=2))+((F10:F86=2)*(E10:E86=1)))) / SUMPRODUCT(--((F10:F86<>"")+(E10:E86<>"")>0)), "")} -> 0.39393939
A6: Semantic FP Strict | C6: =COUNTIF(C28:C59,0) + COUNTIF(C28:C59,1) -> 8 | D6: =COUNTIF(D28:D59,0) + COUNTIF(D28:D59,1) -> 13 | E6: =COUNTIF(E28:E59,0) + COUNTIF(E28:E59,1) -> 8 | F6: =COUNTIF(F28:F59,0) + COUNTIF(F28:F59,1) -> 9 | G6: =COUNTIF(G28:G59,0) + COUNTIF(G28:G59,1) -> 9 | H6: =COUNTIF(H28:H59,0) + COUNTIF(H28:H59,1) -> 12 | J6: XML run 2 | K6: {=IFERROR(SUMPRODUCT((C10:C86<>"")*(G10:G86<>"")*(C10:C86=G10:G86))/SUMPRODUCT(--((C10:C86<>"")+(G10:G86<>"")>0)),"")} -> 0.34375 | L6: {=SUMPRODUCT((D10:D86<>0)*(G10:G86<>0)) / SUMPRODUCT(((D10:D86<>0)+(G10:G86<>0)>0)*1)} -> 0.38709677 | M6: {=IFERROR(SUMPRODUCT((G10:G86<>"")*(E10:E86<>"")*(G10:G86=E10:E86))/SUMPRODUCT(--((G10:G86<>"")+(E10:E86<>"")>0)),"")} -> 0.62068966 | N6: {=IFERROR(SUMPRODUCT((G10:G86<>"")*(F10:F86<>"")*(G10:G86=F10:F86))/SUMPRODUCT(--((G10:G86<>"")+(F10:F86<>"")>0)),"")} -> 0.41935484 | Q6: XML run 2 | R6: {=IFERROR( SUMPRODUCT((C10:C86<>"")*(G10:G86<>"")* ((C10:C86=G10:G86)+((C10:C86=1)*(G10:G86=2))+((C10:C86=2)*(G10:G86=1)))) / SUMPRODUCT(--((C10:C86<>"")+(G10:G86<>"")>0)), "")} -> 0.375 | S6: {=IFERROR( SUMPRODUCT((D10:D86<>"")*(G10:G86<>"")* ((D10:D86=G10:G86)+((D10:D86=1)*(G10:G86=2))+((D10:D86=2)*(G10:G86=1)))) / SUMPRODUCT(--((D10:D86<>"")+(G10:G86<>"")>0)), "")} -> 0.38888889 | T6: {=IFERROR( SUMPRODUCT((G10:G86<>"")*(E10:E86<>"")* ((G10:G86=E10:E86)+((G10:G86=1)*(E10:E86=2))+((G10:G86=2)*(E10:E86=1)))) / SUMPRODUCT(--((G10:G86<>"")+(E10:E86<>"")>0)), "")} -> 0.72413793 | U6: {=IFERROR( SUMPRODUCT((F10:F86<>"")*(G10:G86<>"")* ((F10:F86=G10:G86)+((F10:F86=1)*(G10:G86=2))+((F10:F86=2)*(G10:G86=1)))) / SUMPRODUCT(--((F10:F86<>"")+(G10:G86<>"")>0)), "")} -> 0.48387097
A7: Semantic FP Loose | C7: =COUNTIF(C28:C59,0) -> 0 | D7: =COUNTIF(D28:D59,0) -> 2 | E7: =COUNTIF(E28:E59,0) -> 0 | F7: =COUNTIF(F28:F59,0) -> 4 | G7: =COUNTIF(G28:G59,0) -> 1 | H7: =COUNTIF(H28:H59,0) -> 0 | J7: XML run 3 | K7: {=IFERROR(SUMPRODUCT((C10:C86<>"")*(H10:H86<>"")*(C10:C86=H10:H86))/SUMPRODUCT(--((C10:C86<>"")+(H10:H86<>"")>0)),"")} -> 0.41176471 | L7: {=IFERROR(SUMPRODUCT((H10:H86<>"")*(D10:D86<>"")*(H10:H86=D10:D86))/SUMPRODUCT(--((H10:H86<>"")+(D10:D86<>"")>0)),"")} -> 0.325 | M7: {=IFERROR(SUMPRODUCT((H10:H86<>"")*(E10:E86<>"")*(H10:H86=E10:E86))/SUMPRODUCT(--((H10:H86<>"")+(E10:E86<>"")>0)),"")} -> 0.42857143 | N7: {=IFERROR(SUMPRODUCT((F10:F86<>"")*(H10:H86<>"")*(F10:F86=H10:H86))/SUMPRODUCT(--((F10:F86<>"")+(H10:H86<>"")>0)),"")} -> 0.33333333 | O7: {=IFERROR(SUMPRODUCT((G10:G86<>"")*(H10:H86<>"")*(G10:G86=H10:H86))/SUMPRODUCT(--((G10:G86<>"")+(H10:H86<>"")>0)),"")} -> 0.44444444 | Q7: XML run 3 | R7: {=IFERROR( SUMPRODUCT((C10:C86<>"")*(H10:H86<>"")* ((C10:C86=H10:H86)+((C10:C86=1)*(H10:H86=2))+((C10:C86=2)*(H10:H86=1)))) / SUMPRODUCT(--((C10:C86<>"")+(H10:H86<>"")>0)), "")} -> 0.44117647 | S7: {=IFERROR( SUMPRODUCT((H10:H86<>"")*(D10:D86<>"")* ((H10:H86=D10:D86)+((H10:H86=1)*(D10:D86=2))+((H10:H86=2)*(D10:D86=1)))) / SUMPRODUCT(--((H10:H86<>"")+(D10:D86<>"")>0)), "")} -> 0.325 | T7: {=IFERROR( SUMPRODUCT((H10:H86<>"")*(E10:E86<>"")* ((H10:H86=E10:E86)+((H10:H86=1)*(E10:E86=2))+((H10:H86=2)*(E10:E86=1)))) / SUMPRODUCT(--((H10:H86<>"")+(E10:E86<>"")>0)), "")} -> 0.45714286 | U7: {=IFERROR( SUMPRODUCT((F10:F86<>"")*(H10:H86<>"")* ((F10:F86=H10:H86)+((F10:F86=1)*(H10:H86=2))+((F10:F86=2)*(H10:H86=1)))) / SUMPRODUCT(--((F10:F86<>"")+(H10:H86<>"")>0)), "")} -> 0.36111111 | V7: {=IFERROR( SUMPRODUCT((H10:H86<>"")*(G10:G86<>"")* ((H10:H86=G10:G86)+((H10:H86=1)*(G10:G86=2))+((H10:H86=2)*(G10:G86=1)))) / SUMPRODUCT(--((H10:H86<>"")+(G10:G86<>"")>0)), "")} -> 0.47222222
C9: Chatbot run 1 | D9: Chatbot run 2 | E9: Chatbot run 3 | F9: XML run 1 | G9: XML run 2 | H9: XML run 3
A10: Pools / Lanes | B10: Employer | C10: 2 | D10: 2 | E10: 2 | F10: 2 | G10: 2 | H10: 2
B11: Employee | C11: 2 | D11: 2 | E11: 2 | F11: 2 | G11: 2 | H11: 2
B12: Accident Insurance Provider | C12: 2 | D12: 2 | E12: 2 | F12: 2 | G12: 1 | H12: 2
A13: Tasks/Messages/Events | B13: Inform the employer of work accident | C13: 2 | D13: 2 | E13: 2 | F13: 2 | G13: 2 | H13: 2
B14: Inform the employer of incident that would almost have led to an accident | C14: 2 | D14: 2 | E14: 0 | F14: 2 | G14: 0 | H14: 0
B15: Inform the employer of serious and immediate risk to safety and health that they discover | C15: 2 | D15: 2 | E15: 0 | F15: 2 | G15: 0 | H15: 0
B16: Inform the employer of defect discovered in protection systems. | C16: 2 | D16: 2 | E16: 0 | F16: 2 | G16: 0 | H16: 0
B17: Report to Labour Inspectorate | C17: 2 | D17: 2 | E17: 2 | F17: 2 | G17: 2 | H17: 2
B18: Reported to the responsible accident insurance provider | C18: 2 | D18: 2 | E18: 2 | F18: 2 | G18: 2 | H18: 2
B19: Report accidents to directorate. | C19: 2 | D19: 2 | E19: 2 | F19: 1 | G19: 2 | H19: 2
B20: Write immediately in line with the conditions. | C20: 0 | D20: 0 | E20: 2 | F20: 0 | G20: 1 | H20: 0
A21: Conditions/Loops/Parallel | B21: Has not been reported to the emergency services? | C21: 1 | D21: 0 | E21: 0 | F21: 0 | G21: 0 | H21: 2
B22: leads to a fatality or serious injury ? | C22: 2 | D22: 2 | E22: 2 | F22: 2 | G22: 2 | H22: 2
B23: private insurance? | C23: 0 | D23: 0 | E23: 0 | F23: 0 | G23: 1 | H23: 1
B24: Type of employee is student? | C24: 0 | D24: 0 | E24: 2 | F24: 0 | G24: 1 | H24: 1
B25: Inform Labour Inspectorate || Inform accident insurance provider | C25: 0 | D25: 0 | E25: 0 | F25: 0 | G25: 0 | H25: 0
A26: Data Objects/ Messages | B26: Accident Report DO | C26: 2 | D26: 2 | E26: 2 | F26: 2 | G26: 2 | H26: 2
B28: Type of Incident? | C28: 1 | D28: 1 | F28: 1 | H28: 1
B29: Receive Report from Employee/Insured Person | C29: 1 | D29: 1 | E29: 1 | F29: 1 | G29: 1
B30: School | C30: 1 | E30: 1
B31: Near Miss Report DO | C31: 1 | D31: 1
B32: Safety Risk Report DO | C32: 1 | D32: 1
B33: Defect Report DO | C33: 1 | D33: 1
B34: Notify/ Send to Employer | F34: 1 | G34: 1
B35: Record Incident | F35: 1 | G35: 1
B36: Process Accident Claim | D36: 0 | F36: 0
B37: Investigate Accident | F37: 0
B38: Labour Inspectorate | D38: 1 | F38: 1 | G38: 1 | H38: 1
B39: HR/Management | F39: 0
B40: Safety Officer | F40: 0
B41: Employee: Report Work Accident to Insurance Provider | C41: 1 | E41: 1 | H41: 1
B42: Employee: Send Accident Report to Employer | D42: 1 | E42: 1 | G42: 1
B43: Employee: Send Accident Report to Directorate | D43: 1 | E43: 1
B44: Send Near Miss Report to Employer | D44: 1
B45: Send Safety Risk Report to Employer | D45: 1
B46: Send Defect Report to Employer | D46: 1
B47: Review Accident Report | D47: 0
B48: Insurance Clerk | G48: 0
B49: Student | E49: 1 | G49: 1
B50: Directorate | C50: 1 | E50: 1 | G50: 1 | H50: 1
B51: Self-Employed/Private Insured | E51: 1 | G51: 1
B52: Emergency Services | H52: 1
B53: Private Insurance | H53: 1
B54: Assess Report | H54: 1
B55: Emergency Services Needed? | H55: 1
B56: Insured Reports Accident to Private Insurance | H56: 1
B57: PrivateInsurance_Store | H57: 1
B58: School_Store | H58: 1
B59: AIP_Store | H59: 1

Sheet c14
A1: Semantic Percision | C1: =SUM(C3:C4) / (C3+ C4+ C7) * 100 -> 79.166667 | D1: =SUM(D3:D4) / (D3+ D4+ D7) * 100 -> 90.47619 | E1: =SUM(E3:E4) / (E3+ E4+ E7) * 100 -> 76 | F1: =SUM(F3:F4) / (F3+ F4+ F7) * 100 -> 84.615385 | G1: =SUM(G3:G4) / (G3+ G4+ G7) * 100 -> 100 | H1: =SUM(H3:H4) / (H3+ H4+ H7) * 100 -> 95 | J1: Jaccard Strict | K1: Chatbot run 1 | L1: Chatbot run 2 | M1: Chatbot run 3 | N1: XML run 1 | O1: XML run 2 | P1: XML run 3 | Q1: Jaccard Loose | R1: Chatbot run 1 | S1: Chatbot run 2 | T1: Chatbot run 3 | U1: XML run 1 | V1: XML run 2 | W1: XML run 3
A2: Semantic Recall | C2: =SUM(C3:C4) / SUM(C3:C5) *100 -> 100 | D2: =SUM(D3:D4) / SUM(D3:D5) *100 -> 100 | E2: =SUM(E3:E4) / SUM(E3:E5) *100 -> 100 | F2: =SUM(F3:F4) / SUM(F3:F5) *100 -> 57.894737 | G2: =SUM(G3:G4) / SUM(G3:G5) *100 -> 52.631579 | H2: =SUM(H3:H4) / SUM(H3:H5) *100 -> 100 | J2: Chatbot run 1 | Q2: Chatbot run 1
A3: Semantic TP Explicit | C3: =COUNTIF(C10:C28, 2) -> 19 | D3: =COUNTIF(D10:D28, 2) -> 19 | E3: =COUNTIF(E10:E28, 2) -> 19 | F3: =COUNTIF(F10:F28, 2) -> 6 | G3: =COUNTIF(G10:G28, 2) -> 7 | H3: =COUNTIF(H10:H28, 2) -> 13 | J3: Chatbot run 2 | K3: {=IFERROR(SUMPRODUCT((C10:C82<>"")*(D10:D82<>"")*(C10:C82=D10:D82))/SUMPRODUCT(--((C10:C82<>"")+(D10:D82<>"")>0)),"")} -> 0.74285714 | Q3: Chatbot run 2 | R3: {=IFERROR( SUMPRODUCT((C10:C82<>"")*(D10:D82<>"")* ((C10:C82=D10:D82)+((C10:C82=1)*(D10:D82=2))+((C10:C82=2)*(D10:D82=1)))) / SUMPRODUCT(--((C10:C82<>"")+(D10:D82<>"")>0)), "")} -> 0.74285714
A4: Semantic TP Implicit | C4: =COUNTIF(C10:C28, 1) -> 0 | D4: =COUNTIF(D10:D28, 1) -> 0 | E4: =COUNTIF(E10:E28, 1) -> 0 | F4: =COUNTIF(F10:F28, 1) -> 5 | G4: =COUNTIF(G10:G28, 1) -> 3 | H4: =COUNTIF(H10:H28, 1) -> 6 | J4: Chatbot run 3 | K4: {=IFERROR(SUMPRODUCT((C10:C82<>"")*(E10:E82<>"")*(C10:C82=E10:E82))/SUMPRODUCT(--((C10:C82<>"")+(E10:E82<>"")>0)),"")} -> 0.88235294 | L4: {=IFERROR(SUMPRODUCT((E10:E82<>"")*(D10:D82<>"")*(E10:E82=D10:D82))/SUMPRODUCT(--((E10:E82<>"")+(D10:D82<>"")>0)),"")} -> 0.74285714 | Q4: Chatbot run 3 | R4: {=IFERROR( SUMPRODUCT((C10:C82<>"")*(E10:E82<>"")* ((C10:C82=E10:E82)+((C10:C82=1)*(E10:E82=2))+((C10:C82=2)*(E10:E82=1)))) / SUMPRODUCT(--((C10:C82<>"")+(E10:E82<>"")>0)), "")} -> 0.88235294 | S4: {=IFERROR( SUMPRODUCT((E10:E82<>"")*(D10:D82<>"")* ((E10:E82=D10:D82)+((E10:E82=1)*(D10:D82=2))+((E10:E82=2)*(D10:D82=1)))) / SUMPRODUCT(--((E10:E82<>"")+(D10:D82<>"")>0)), "")} -> 0.74285714
A5: Semantic FN | C5: =COUNTIF(C10:C28, 0) -> 0 | D5: =COUNTIF(D10:D28, 0) -> 0 | E5: =COUNTIF(E10:E28, 0) -> 0 | F5: =COUNTIF(F10:F28, 0) -> 8 | G5: =COUNTIF(G10:G28, 0) -> 9 | H5: =COUNTIF(H10:H28, 0) -> 0 | J5: XML run 1 | K5: {=IFERROR(SUMPRODUCT((C10:C82<>"")*(F10:F82<>"")*(C10:C82=F10:F82))/SUMPRODUCT(--((C10:C82<>"")+(F10:F82<>"")>0)),"")} -> 0.21428571 | L5: {=IFERROR(SUMPRODUCT((F10:F82<>"")*(D10:D82<>"")*(F10:F82=D10:D82))/SUMPRODUCT(--((F10:F82<>"")+(D10:D82<>"")>0)),"")} -> 0.23076923 | M5: {=IFERROR(SUMPRODUCT((F10:F82<>"")*(E10:E82<>"")*(F10:F82=E10:E82))/SUMPRODUCT(--((F10:F82<>"")+(E10:E82<>"")>0)),"")} -> 0.21428571 | Q5: XML run 1 | R5: {=IFERROR( SUMPRODUCT((C10:C82<>"")*(F10:F82<>"")* ((C10:C82=F10:F82)+((C10:C82=1)*(F10:F82=2))+((C10:C82=2)*(F10:F82=1)))) / SUMPRODUCT(--((C10:C82<>"")+(F10:F82<>"")>0)), "")} -> 0.33333333 | S5: {=IFERROR( SUMPRODUCT((F10:F82<>"")*(D10:D82<>"")* ((F10:F82=D10:D82)+((F10:F82=1)*(D10:D82=2))+((F10:F82=2)*(D10:D82=1)))) / SUMPRODUCT(--((F10:F82<>"")+(D10:D82<>"")>0)), "")} -> 0.35897436 | T5: {=IFERROR( SUMPRODUCT((F10:F82<>"")*(E10:E82<>"")* ((F10:F82=E10:E82)+((F10:F82=1)*(E10:E82=2))+((F10:F82=2)*(E10:E82=1)))) / SUMPRODUCT(--((F10:F82<>"")+(E10:E82<>"")>0)), "")} -> 0.33333333
A6: Semantic FP Strict | C6: =COUNTIF(C30:C98,0) + COUNTIF(C30:C98,1) -> 13 | D6: =COUNTIF(D30:D98,0) + COUNTIF(D30:D98,1) -> 10 | E6: =COUNTIF(E30:E98,0) + COUNTIF(E30:E98,1) -> 13 | F6: =COUNTIF(F30:F98,0) + COUNTIF(F30:F98,1) -> 13 | G6: =COUNTIF(G30:G98,0) + COUNTIF(G30:G98,1) -> 16 | H6: =COUNTIF(H30:H98,0) + COUNTIF(H30:H98,1) -> 24 | J6: XML run 2 | K6: {=IFERROR(SUMPRODUCT((C10:C82<>"")*(G10:G82<>"")*(C10:C82=G10:G82))/SUMPRODUCT(--((C10:C82<>"")+(G10:G82<>"")>0)),"")} -> 0.22727273 | L6: {=SUMPRODUCT((D10:D82<>0)*(G10:G82<>0)) / SUMPRODUCT(((D10:D82<>0)+(G10:G82<>0)>0)*1)} -> 0.325 | M6: {=IFERROR(SUMPRODUCT((G10:G82<>"")*(E10:E82<>"")*(G10:G82=E10:E82))/SUMPRODUCT(--((G10:G82<>"")+(E10:E82<>"")>0)),"")} -> 0.22727273 | N6: {=IFERROR(SUMPRODUCT((G10:G82<>"")*(F10:F82<>"")*(G10:G82=F10:F82))/SUMPRODUCT(--((G10:G82<>"")+(F10:F82<>"")>0)),"")} -> 0.67567568 | Q6: XML run 2 | R6: {=IFERROR( SUMPRODUCT((C10:C82<>"")*(G10:G82<>"")* ((C10:C82=G10:G82)+((C10:C82=1)*(G10:G82=2))+((C10:C82=2)*(G10:G82=1)))) / SUMPRODUCT(--((C10:C82<>"")+(G10:G82<>"")>0)), "")} -> 0.29545455 | S6: {=IFERROR( SUMPRODUCT((D10:D82<>"")*(G10:G82<>"")* ((D10:D82=G10:G82)+((D10:D82=1)*(G10:G82=2))+((D10:D82=2)*(G10:G82=1)))) / SUMPRODUCT(--((D10:D82<>"")+(G10:G82<>"")>0)), "")} -> 0.30952381 | T6: {=IFERROR( SUMPRODUCT((G10:G82<>"")*(E10:E82<>"")* ((G10:G82=E10:E82)+((G10:G82=1)*(E10:E82=2))+((G10:G82=2)*(E10:E82=1)))) / SUMPRODUCT(--((G10:G82<>"")+(E10:E82<>"")>0)), "")} -> 0.29545455 | U6: {=IFERROR( SUMPRODUCT((F10:F82<>"")*(G10:G82<>"")* ((F10:F82=G10:G82)+((F10:F82=1)*(G10:G82=2))+((F10:F82=2)*(G10:G82=1)))) / SUMPRODUCT(--((F10:F82<>"")+(G10:G82<>"")>0)), "")} -> 0.75675676
A7: Semantic FP Loose | C7: =COUNTIF(C30:C98,0) -> 5 | D7: =COUNTIF(D30:D98,0) -> 2 | E7: =COUNTIF(E30:E98,0) -> 6 | F7: =COUNTIF(F30:F98,0) -> 2 | G7: =COUNTIF(G30:G98,0) -> 0 | H7: =COUNTIF(H30:H98,0) -> 1 | J7: XML run 3 | K7: {=IFERROR(SUMPRODUCT((C10:C82<>"")*(H10:H82<>"")*(C10:C82=H10:H82))/SUMPRODUCT(--((C10:C82<>"")+(H10:H82<>"")>0)),"")} -> 0.30769231 | L7: {=IFERROR(SUMPRODUCT((H10:H82<>"")*(D10:D82<>"")*(H10:H82=D10:D82))/SUMPRODUCT(--((H10:H82<>"")+(D10:D82<>"")>0)),"")} -> 0.32 | M7: {=IFERROR(SUMPRODUCT((H10:H82<>"")*(E10:E82<>"")*(H10:H82=E10:E82))/SUMPRODUCT(--((H10:H82<>"")+(E10:E82<>"")>0)),"")} -> 0.30769231 | N7: {=IFERROR(SUMPRODUCT((F10:F82<>"")*(H10:H82<>"")*(F10:F82=H10:H82))/SUMPRODUCT(--((F10:F82<>"")+(H10:H82<>"")>0)),"")} -> 0.27083333 | O7: {=IFERROR(SUMPRODUCT((G10:G82<>"")*(H10:H82<>"")*(G10:G82=H10:H82))/SUMPRODUCT(--((G10:G82<>"")+(H10:H82<>"")>0)),"")} -> 0.47826087 | Q7: XML run 3 | R7: {=IFERROR( SUMPRODUCT((C10:C82<>"")*(H10:H82<>"")* ((C10:C82=H10:H82)+((C10:C82=1)*(H10:H82=2))+((C10:C82=2)*(H10:H82=1)))) / SUMPRODUCT(--((C10:C82<>"")+(H10:H82<>"")>0)), "")} -> 0.42307692 | S7: {=IFERROR( SUMPRODUCT((H10:H82<>"")*(D10:D82<>"")* ((H10:H82=D10:D82)+((H10:H82=1)*(D10:D82=2))+((H10:H82=2)*(D10:D82=1)))) / SUMPRODUCT(--((H10:H82<>"")+(D10:D82<>"")>0)), "")} -> 0.44 | T7: {=IFERROR( SUMPRODUCT((H10:H82<>"")*(E10:E82<>"")* ((H10:H82=E10:E82)+((H10:H82=1)*(E10:E82=2))+((H10:H82=2)*(E10:E82=1)))) / SUMPRODUCT(--((H10:H82<>"")+(E10:E82<>"")>0)), "")} -> 0.42307692 | U7: {=IFERROR( SUMPRODUCT((F10:F82<>"")*(H10:H82<>"")* ((F10:F82=H10:H82)+((F10:F82=1)*(H10:H82=2))+((F10:F82=2)*(H10:H82=1)))) / SUMPRODUCT(--((F10:F82<>"")+(H10:H82<>"")>0)), "")} -> 0.375 | V7: {=IFERROR( SUMPRODUCT((H10:H82<>"")*(G10:G82<>"")* ((H10:H82=G10:G82)+((H10:H82=1)*(G10:G82=2))+((H10:H82=2)*(G10:G82=1)))) / SUMPRODUCT(--((H10:H82<>"")+(G10:G82<>"")>0)), "")} -> 0.5
C9: Chatbot run 1 | D9: Chatbot run 2 | E9: Chatbot run 3 | F9: XML run 1 | G9: XML run 2 | H9: XML run 3
A10: Pools / Lanes | B10: Applicant | C10: 2 | D10: 2 | E10: 2 | F10: 2 | G10: 2 | H10: 2
B11: Austrian Representation Office | C11: 2 | D11: 2 | E11: 2 | F11: 2 | G11: 2 | H11: 2
A12: Tasks/Messages/Events | B12: Organize Accommodation | C12: 2 | D12: 2 | E12: 2 | F12: 2 | G12: 2 | H12: 2
B13: Open Bank Account | C13: 2 | D13: 2 | E13: 2 | F13: 2 | G13: 2 | H13: 2
B14: Prepare Visa Application Form | C14: 2 | D14: 2 | E14: 2 | F14: 2 | G14: 1 | H14: 1
B15: Collect Travel Document | C15: 2 | D15: 2 | E15: 2 | F15: 0 | G15: 0 | H15: 1
B16: Obtain Passport Photo | C16: 2 | D16: 2 | E16: 2 | F16: 0 | G16: 0 | H16: 1
B17: Arrange Travel Health Insurance | C17: 2 | D17: 2 | E17: 2 | F17: 0 | G17: 0 | H17: 1
B18: Gather Proof of Means of Subsistence | C18: 2 | D18: 2 | E18: 2 | F18: 0 | G18: 0 | H18: 1
B19: Collect Other Evidence | C19: 2 | D19: 2 | E19: 2 | F19: 1 | G19: 1 | H19: 1
B20: Submit Visa Application to Austrian Representation | C20: 2 | D20: 2 | E20: 2 | F20: 2 | G20: 2 | H20: 2
A21: Data Objects/ Messages | B21: Visa Application Form | C21: 2 | D21: 2 | E21: 2 | F21: 1 | G21: 1 | H21: 2
B22: Travel Document | C22: 2 | D22: 2 | E22: 2 | F22: 0 | G22: 0 | H22: 2
B23: Passport Photo | C23: 2 | D23: 2 | E23: 2 | F23: 0 | G23: 0 | H23: 2
B24: Travel Health Insurance Policy | C24: 2 | D24: 2 | E24: 2 | F24: 0 | G24: 0 | H24: 2
B25: Proof of Means of Subsistence | C25: 2 | D25: 2 | E25: 2 | F25: 0 | G25: 0 | H25: 2
B26: Other Evidence | C26: 2 | D26: 2 | E26: 2 | F26: 1 | G26: 0 | H26: 2
B27: Accommodation Agreement | C27: 2 | D27: 2 | E27: 2 | F27: 1 | G27: 2 | H27: 2
B28: Bank Account Details | C28: 2 | D28: 2 | E28: 2 | F28: 1 | G28: 2 | H28: 2
B30: Rot-Weiss-Rot Card DO | C30: 1 | E30: 1
B31: Receive Visa Application from Applicant | C31: 1 | D31: 1 | E31: 1 | F31: 1 | G31: 1 | H31: 1
B32: Check Application Completeness and Requirements | C32: 0 | E32: 0 | F32: 0 | G32: 1 | H32: 1
B33: Application Complete and Meets Requirements? | C33: 1 | D33: 1 | E33: 1 | F33: 1 | G33: 1 | H33: 1
B34: Issue Rot-Weiss-Rot Card | C34: 1 | D34: 1 | E34: 1
B35: Send Rot-Weiss-Rot Card to Applicant | C35: 1 | D35: 1 | E35: 1
B36: Reject Application | C36: 1 | D36: 1 | E36: 1
B37: Receive Rot-Weiss-Rot Card | C37: 1
B38: Wait for X Months | C38: 0 | E38: 0
B39: Submit Renewal Application to Austrian Representation | C39: 0 | D39: 0 | E39: 0
B40: Receive Renewal Application from Applicant | C40: 0
B41: Process Renewal Application | C41: 0 | E41: 0
B42: Visa | D42: 1
B43: Prepare for Visa Renewal | D43: 0
B44: Receive Visa from Representation Office | D44: 1 | F44: 1
B45: Issue Renewed Rot-Weiss-Rot Card | E45: 0
B46: Send Renewed Rot-Weiss-Rot Card to Applicant | E46: 0
B47: Consular Officer | F47: 1 | G47: 1 | H47: 1
B48: Check Visa and Living Requirements | F48: 1 | G48: 1
B49: Negotiation Complete? | F49: 0
B50: Request Additional Documents | C50: 1 | D50: 1 | E50: 1 | G50: 1 | H50: 1
B51: Receive Request for Additional Documents | F51: 1 | G51: 1 | H51: 1
B52: Provide Additional Documents | F52: 1 | G52: 1 | H52: 1
B53: Visa Granted? / Eligible? | F53: 1 | G53: 1 | H53: 1
B54: Review Additional Documents | F54: 1 | G54: 1
B55: Make Visa Decision | F55: 1 | G55: 1
B56: Send Visa Decision | F56: 1 | G56: 1 | H56: 1
B57: Receive Visa Decision | G57: 1 | H57: 1
B58: Visa Approved? | G58: 1 | H58: 1
B59: Visa Section Lane | G59: 1 | H59: 1
B60: Accommodation & Bank Lane | G60: 1 | H60: 1
B61: Visa Application Lane | H61: 1
B62: Personal Preparation Lane | H62: 1
B63: Accommodation/Bank Negotiation? | H63: 0
B64: Check Visa Type & Main Destination | H64: 1
B65: Contact Representation Office | H65: 1
B66: Visa Renewal Timer | H66: 1
B67: Renew Visa | H67: 1
B68: Verify Eligibility | H68: 1
B69: Check Absence of Refusal Grounds | H69: 1
B70: Assess Visa Type & Jurisdiction | H70: 1
B71: Check Completeness LOOP | H71: 1

Sheet c15
A1: Semantic Percision | C1: =SUM(C3:C4) / (C3+ C4+ C7) * 100 -> 100 | D1: =SUM(D3:D4) / (D3+ D4+ D7) * 100 -> 100 | E1: =SUM(E3:E4) / (E3+ E4+ E7) * 100 -> 100 | F1: =SUM(F3:F4) / (F3+ F4+ F7) * 100 -> 100 | G1: =SUM(G3:G4) / (G3+ G4+ G7) * 100 -> 100 | H1: =SUM(H3:H4) / (H3+ H4+ H7) * 100 -> 100 | J1: Jaccard Strict | K1: Chatbot run 1 | L1: Chatbot run 2 | M1: Chatbot run 3 | N1: XML run 1 | O1: XML run 2 | P1: XML run 3 | Q1: Jaccard Loose | R1: Chatbot run 1 | S1: Chatbot run 2 | T1: Chatbot run 3 | U1: XML run 1 | V1: XML run 2 | W1: XML run 3
A2: Semantic Recall | C2: =SUM(C3:C4) / SUM(C3:C5) *100 -> 96.610169 | D2: =SUM(D3:D4) / SUM(D3:D5) *100 -> 94.736842 | E2: =SUM(E3:E4) / SUM(E3:E5) *100 -> 94.827586 | F2: =SUM(F3:F4) / SUM(F3:F5) *100 -> 89.655172 | G2: =SUM(G3:G4) / SUM(G3:G5) *100 -> 94.915254 | H2: =SUM(H3:H4) / SUM(H3:H5) *100 -> 92.982456 | J2: Chatbot run 1 | Q2: Chatbot run 1
A3: Semantic TP Explicit | C3: =COUNTIF(C10:C68, 2) -> 55 | D3: =COUNTIF(D10:D68, 2) -> 53 | E3: =COUNTIF(E10:E68, 2) -> 54 | F3: =COUNTIF(F10:F68, 2) -> 47 | G3: =COUNTIF(G10:G68, 2) -> 51 | H3: =COUNTIF(H10:H68, 2) -> 46 | J3: Chatbot run 2 | K3: {=IFERROR(SUMPRODUCT((C10:C114<>"")*(D10:D114<>"")*(C10:C114=D10:D114))/SUMPRODUCT(--((C10:C114<>"")+(D10:D114<>"")>0)),"")} -> 0.80263158 | Q3: Chatbot run 2 | R3: {=IFERROR( SUMPRODUCT((C10:C114<>"")*(D10:D114<>"")* ((C10:C114=D10:D114)+((C10:C114=1)*(D10:D114=2))+((C10:C114=2)*(D10:D114=1)))) / SUMPRODUCT(--((C10:C114<>"")+(D10:D114<>"")>0)), "")} -> 0.81578947
A4: Semantic TP Implicit | C4: =COUNTIF(C10:C68, 1) -> 2 | D4: =COUNTIF(D10:D68, 1) -> 1 | E4: =COUNTIF(E10:E68, 1) -> 1 | F4: =COUNTIF(F10:F68, 1) -> 5 | G4: =COUNTIF(G10:G68, 1) -> 5 | H4: =COUNTIF(H10:H68, 1) -> 7 | J4: Chatbot run 3 | K4: {=IFERROR(SUMPRODUCT((C10:C114<>"")*(E10:E114<>"")*(C10:C114=E10:E114))/SUMPRODUCT(--((C10:C114<>"")+(E10:E114<>"")>0)),"")} -> 0.82666667 | L4: {=IFERROR(SUMPRODUCT((E10:E114<>"")*(D10:D114<>"")*(E10:E114=D10:D114))/SUMPRODUCT(--((E10:E114<>"")+(D10:D114<>"")>0)),"")} -> 0.91891892 | Q4: Chatbot run 3 | R4: {=IFERROR( SUMPRODUCT((C10:C114<>"")*(E10:E114<>"")* ((C10:C114=E10:E114)+((C10:C114=1)*(E10:E114=2))+((C10:C114=2)*(E10:E114=1)))) / SUMPRODUCT(--((C10:C114<>"")+(E10:E114<>"")>0)), "")} -> 0.84 | S4: {=IFERROR( SUMPRODUCT((E10:E114<>"")*(D10:D114<>"")* ((E10:E114=D10:D114)+((E10:E114=1)*(D10:D114=2))+((E10:E114=2)*(D10:D114=1)))) / SUMPRODUCT(--((E10:E114<>"")+(D10:D114<>"")>0)), "")} -> 0.91891892
A5: Semantic FN | C5: =COUNTIF(C10:C68, 0) -> 2 | D5: =COUNTIF(D10:D68, 0) -> 3 | E5: =COUNTIF(E10:E68, 0) -> 3 | F5: =COUNTIF(F10:F68, 0) -> 6 | G5: =COUNTIF(G10:G68, 0) -> 3 | H5: =COUNTIF(H10:H68, 0) -> 4 | J5: XML run 1 | K5: {=IFERROR(SUMPRODUCT((C10:C114<>"")*(F10:F114<>"")*(C10:C114=F10:F114))/SUMPRODUCT(--((C10:C114<>"")+(F10:F114<>"")>0)),"")} -> 0.74324324 | L5: {=IFERROR(SUMPRODUCT((F10:F114<>"")*(D10:D114<>"")*(F10:F114=D10:D114))/SUMPRODUCT(--((F10:F114<>"")+(D10:D114<>"")>0)),"")} -> 0.74025974 | M5: {=IFERROR(SUMPRODUCT((F10:F114<>"")*(E10:E114<>"")*(F10:F114=E10:E114))/SUMPRODUCT(--((F10:F114<>"")+(E10:E114<>"")>0)),"")} -> 0.74025974 | Q5: XML run 1 | R5: {=IFERROR( SUMPRODUCT((C10:C114<>"")*(F10:F114<>"")* ((C10:C114=F10:F114)+((C10:C114=1)*(F10:F114=2))+((C10:C114=2)*(F10:F114=1)))) / SUMPRODUCT(--((C10:C114<>"")+(F10:F114<>"")>0)), "")} -> 0.81081081 | S5: {=IFERROR( SUMPRODUCT((F10:F114<>"")*(D10:D114<>"")* ((F10:F114=D10:D114)+((F10:F114=1)*(D10:D114=2))+((F10:F114=2)*(D10:D114=1)))) / SUMPRODUCT(--((F10:F114<>"")+(D10:D114<>"")>0)), "")} -> 0.79220779 | T5: {=IFERROR( SUMPRODUCT((F10:F114<>"")*(E10:E114<>"")* ((F10:F114=E10:E114)+((F10:F114=1)*(E10:E114=2))+((F10:F114=2)*(E10:E114=1)))) / SUMPRODUCT(--((F10:F114<>"")+(E10:E114<>"")>0)), "")} -> 0.79220779
A6: Semantic FP Strict | C6: =COUNTIF(C70:C130,0) + COUNTIF(C70:C130,1) -> 8 | D6: =COUNTIF(D70:D130,0) + COUNTIF(D70:D130,1) -> 15 | E6: =COUNTIF(E70:E130,0) + COUNTIF(E70:E130,1) -> 14 | F6: =COUNTIF(F70:F130,0) + COUNTIF(F70:F130,1) -> 13 | G6: =COUNTIF(G70:G130,0) + COUNTIF(G70:G130,1) -> 11 | H6: =COUNTIF(H70:H130,0) + COUNTIF(H70:H130,1) -> 11 | J6: XML run 2 | K6: {=IFERROR(SUMPRODUCT((C10:C114<>"")*(G10:G114<>"")*(C10:C114=G10:G114))/SUMPRODUCT(--((C10:C114<>"")+(G10:G114<>"")>0)),"")} -> 0.79452055 | L6: {=SUMPRODUCT((D10:D114<>0)*(G10:G114<>0)) / SUMPRODUCT(((D10:D114<>0)+(G10:G114<>0)>0)*1)} -> 0.83783784 | M6: {=IFERROR(SUMPRODUCT((G10:G114<>"")*(E10:E114<>"")*(G10:G114=E10:E114))/SUMPRODUCT(--((G10:G114<>"")+(E10:E114<>"")>0)),"")} -> 0.81333333 | N6: {=IFERROR(SUMPRODUCT((G10:G114<>"")*(F10:F114<>"")*(G10:G114=F10:F114))/SUMPRODUCT(--((G10:G114<>"")+(F10:F114<>"")>0)),"")} -> 0.88888889 | Q6: XML run 2 | R6: {=IFERROR( SUMPRODUCT((C10:C114<>"")*(G10:G114<>"")* ((C10:C114=G10:G114)+((C10:C114=1)*(G10:G114=2))+((C10:C114=2)*(G10:G114=1)))) / SUMPRODUCT(--((C10:C114<>"")+(G10:G114<>"")>0)), "")} -> 0.8630137 | S6: {=IFERROR( SUMPRODUCT((D10:D114<>"")*(G10:G114<>"")* ((D10:D114=G10:G114)+((D10:D114=1)*(G10:G114=2))+((D10:D114=2)*(G10:G114=1)))) / SUMPRODUCT(--((D10:D114<>"")+(G10:G114<>"")>0)), "")} -> 0.84210526 | T6: {=IFERROR( SUMPRODUCT((G10:G114<>"")*(E10:E114<>"")* ((G10:G114=E10:E114)+((G10:G114=1)*(E10:E114=2))+((G10:G114=2)*(E10:E114=1)))) / SUMPRODUCT(--((G10:G114<>"")+(E10:E114<>"")>0)), "")} -> 0.86666667 | U6: {=IFERROR( SUMPRODUCT((F10:F114<>"")*(G10:G114<>"")* ((F10:F114=G10:G114)+((F10:F114=1)*(G10:G114=2))+((F10:F114=2)*(G10:G114=1)))) / SUMPRODUCT(--((F10:F114<>"")+(G10:G114<>"")>0)), "")} -> 0.91666667
A7: Semantic FP Loose | C7: =COUNTIF(C70:C130,0) -> 0 | D7: =COUNTIF(D70:D130,0) -> 0 | E7: =COUNTIF(E70:E130,0) -> 0 | F7: =COUNTIF(F70:F130,0) -> 0 | G7: =COUNTIF(G70:G130,0) -> 0 | H7: =COUNTIF(H70:H130,0) -> 0 | J7: XML run 3 | K7: {=IFERROR(SUMPRODUCT((C10:C114<>"")*(H10:H114<>"")*(C10:C114=H10:H114))/SUMPRODUCT(--((C10:C114<>"")+(H10:H114<>"")>0)),"")} -> 0.75342466 | L7: {=IFERROR(SUMPRODUCT((H10:H114<>"")*(D10:D114<>"")*(H10:H114=D10:D114))/SUMPRODUCT(--((H10:H114<>"")+(D10:D114<>"")>0)),"")} -> 0.72368421 | M7: {=IFERROR(SUMPRODUCT((H10:H114<>"")*(E10:E114<>"")*(H10:H114=E10:E114))/SUMPRODUCT(--((H10:H114<>"")+(E10:E114<>"")>0)),"")} -> 0.74666667 | N7: {=IFERROR(SUMPRODUCT((F10:F114<>"")*(H10:H114<>"")*(F10:F114=H10:H114))/SUMPRODUCT(--((F10:F114<>"")+(H10:H114<>"")>0)),"")} -> 0.82191781 | O7: {=IFERROR(SUMPRODUCT((G10:G114<>"")*(H10:H114<>"")*(G10:G114=H10:H114))/SUMPRODUCT(--((G10:G114<>"")+(H10:H114<>"")>0)),"")} -> 0.90140845 | Q7: XML run 3 | R7: {=IFERROR( SUMPRODUCT((C10:C114<>"")*(H10:H114<>"")* ((C10:C114=H10:H114)+((C10:C114=1)*(H10:H114=2))+((C10:C114=2)*(H10:H114=1)))) / SUMPRODUCT(--((C10:C114<>"")+(H10:H114<>"")>0)), "")} -> 0.82191781 | S7: {=IFERROR( SUMPRODUCT((H10:H114<>"")*(D10:D114<>"")* ((H10:H114=D10:D114)+((H10:H114=1)*(D10:D114=2))+((H10:H114=2)*(D10:D114=1)))) / SUMPRODUCT(--((H10:H114<>"")+(D10:D114<>"")>0)), "")} -> 0.80263158 | T7: {=IFERROR( SUMPRODUCT((H10:H114<>"")*(E10:E114<>"")* ((H10:H114=E10:E114)+((H10:H114=1)*(E10:E114=2))+((H10:H114=2)*(E10:E114=1)))) / SUMPRODUCT(--((H10:H114<>"")+(E10:E114<>"")>0)), "")} -> 0.82666667 | U7: {=IFERROR( SUMPRODUCT((F10:F114<>"")*(H10:H114<>"")* ((F10:F114=H10:H114)+((F10:F114=1)*(H10:H114=2))+((F10:F114=2)*(H10:H114=1)))) / SUMPRODUCT(--((F10:F114<>"")+(H10:H114<>"")>0)), "")} -> 0.87671233 | V7: {=IFERROR( SUMPRODUCT((H10:H114<>"")*(G10:G114<>"")* ((H10:H114=G10:G114)+((H10:H114=1)*(G10:G114=2))+((H10:H114=2)*(G10:G114=1)))) / SUMPRODUCT(--((H10:H114<>"")+(G10:G114<>"")>0)), "")} -> 0.92957746
C9: Chatbot run 1 | D9: Chatbot run 2 | E9: Chatbot run 3 | F9: XML run 1 | G9: XML run 2 | H9: XML run 3
A10: Pools / Lanes | B10: Customer | C10: 2 | D10: 2 | E10: 2 | F10: 0 | G10: 2 | H10: 2
B11: TELECO | C11: 2 | D11: 2 | E11: 2 | F11: 0 | G11: 0 | H11: 0
B12: Customer Service | C12: 2 | D12: 2 | E12: 2 | F12: 2 | G12: 2 | H12: 2
B13: electronic service | C13: 0 | D13: 0 | E13: 0 | F13: 0 | G13: 0 | H13: 0
B14: Service Management | C14: 2 | D14: 2 | E14: 2 | F14: 2 | G14: 2 | H14: 2
B15: Resource Provisioning | C15: 2 | D15: 2 | E15: 2 | F15: 2 | G15: 2 | H15: 2
B16: Billing & Collections | C16: 2 | D16: 2 | E16: 2 | F16: 2 | G16: 2 | H16: 2
A17: Tasks/Messages/Events | B17: subscribed service degraded | C17: 2 | D17: 2 | E17: 2 | F17: 3 | G17: 2 | H17: 2
B18: Send Problem Parameters to TELECO Customer Service | C18: 2 | D18: 2 | E18: 2 | F18: 2 | G18: 2 | H18: 2
B19: Receive Service Performance | C19: 2 | D19: 2 | E19: 2 | F19: 0 | G19: 2 | H19: 2
B20: Receive Resolution Report | C20: 2 | D20: 2 | E20: 2 | F20: 0 | G20: 2 | H20: 0
B21: Receive Problem Parameters from Customer | C21: 2 | D21: 2 | E21: 2 | F21: 2 | G21: 2 | H21: 2
B22: Enter Problem Report into System T | C22: 2 | D22: 2 | E22: 2 | F22: 2 | G22: 2 | H22: 2
B23: Compare Problem Report to SLA | C23: 2 | D23: 2 | E23: 2 | F23: 2 | G23: 2 | H23: 2
B24: Determine Counter Measures and Priorities | C24: 2 | D24: 2 | E24: 2 | F24: 2 | G24: 2 | H24: 2
B25: Determine Customer Significance | C25: 2 | D25: 2 | E25: 2 | F25: 2 | G25: 2 | H25: 2
B26: Link to Extra Problem Fix Process | C26: 2 | D26: 2 | E26: 2 | F26: 2 | G26: 2 | H26: 2
B27: Create Detailed Problem Report | C27: 2 | D27: 2 | E27: 2 | F27: 2 | G27: 2 | H27: 2
B28: Receive Detailed Problem Report from Customer Service | C28: 2 | D28: 2 | E28: 2 | F28: 2 | G28: 2 | H28: 2
B29: Analyze Problem | C29: 2 | D29: 2 | E29: 2 | F29: 2 | G29: 2 | H29: 2
... B41: Send Problem Resolution Report to Customer Service | C41: 2 | D41: 2 | E41: 2 | F41: 2 | G41: 2 | H41: 2
B42: Create Restoration Request | C42: 2 | D42: 2 | E42: 2 | F42: 2 | G42: 2
B43: Receive Restoration Request from Service Management | C43: 2 | D43: 2 | E43: 2 | F43: 2 | G43: 2
B44: Wait for Restoration Request (2 days) | C44: 2 | D44: 2 | E44: 2 | F44: 2 | G44: 2 | H44: 2
B45: Track Errors | C45: 2 | D45: 2 | E45: 2 | F45: 2 | G45: 2 | H45: 2
B46: Create Trouble-Shooting Report | C46: 2 | D46: 2 | E46: 2 | F46: 2 | G46: 2 | H46: 2
B47: Undertake Corrective Actions | C47: 2 | F47: 2 | G47: 2 | H47: 2
B48: Receive Trouble-Shooting Report from Resource Provisioning | C48: 2 | D48: 2 | E48: 2 | F48: 2 | G48: 2 | H48: 2
B49: Create Problem Resolution Report | C49: 2 | D49: 2 | E49: 2 | F49: 2 | G49: 1 | H49: 1
B50: Receive Service Performance from Service Management: Customer Service | C50: 2 | D50: 2 | E50: 0 | F50: 2 | G50: 2 | H50: 2
B51: Receive Problem Resolution Report from Service Management: Customer Service | C51: 2 | D51: 2 | E51: 2 | F51: 1 | G51: 2 | H51: 2
B52: Create Report for Customer | C52: 2 | D52: 2 | E52: 2 | F52: 2 | G52: 2 | H52: 2
B53: Send Report to Customer | C53: 2 | E53: 2 | F53: 2 | G53: 2 | H53: 2
B54: Report SLA Violation Rebate | C54: 2 | D54: 2 | E54: 2 | F54: 2 | G54: 2 | H54: 2
B55: Adjust Billing | C55: 2 | D55: 0 | E55: 2 | F55: 2 | G55: 2 | H55: 2
A56: Conditions/Loops/Parallel | B56: If significant goes back to re-prioritize these measures LOOP | C56: 1 | D56: 1 | E56: 1 | F56: 1 | G56: 1 | H56: 1
B57: Problem analyzable by Service Management? | C57: 2 | D57: 2 | E57: 2 | F57: 2 | G57: 2 | H57: 2
B58: Problem detected by Resource Provisioning? | C58: 2 | D58: 2 | E58: 2 | F58: 2 | G58: 2 | H58: 2
B59: Counter Measures Required? | C59: 2 | D59: 2 | E59: 2 | F59: 2 | G59: 2 | H59: 2
B60: Receive Service Performance OR Problem Resolution? | C60: 0 | D60: 0 | E60: 0 | F60: 0 | G60: 0 | H60: 0
B61: two concurrent activities || | C61: 2 | D61: 2 | E61: 2 | F61: 2 | G61: 2 | H61: 2
A62: Data Objects/ Messages | B62: Problem Parameters | C62: 2 | D62: 2 | E62: 2 | F62: 1 | G62: 1 | H62: 1
B63: Service Performance Report | C63: 2 | D63: 2 | E63: 2 | F63: 1 | G63: 1 | H63: 1
B64: Problem Report | C64: 2 | D64: 2 | E64: 2 | F64: 2 | G64: 2 | H64: 2
B65: Detailed Problem Report | C65: 2 | D65: 2 | E65: 2 | F65: 2 | G65: 2 | H65: 2
B66: Final Status Report | C66: 2 | D66: 2 | E66: 2 | F66: 1 | G66: 1 | H66: 1
B67: Problem Resolution Report | C67: 2 | D67: 2 | E67: 2 | F67: 2 | G67: 2 | H67: 1
B68: Trouble-Shooting Report | C68: 1 | D68: 2 | E68: 2 | F68: 2 | G68: 2 | H68: 1
B70: Prioritized Actions | C70: 1
B71: SLA Violation Rebate | C71: 1 | D71: 1 | E71: 1 | H71: 1
B72: Customer SLA | D72: 1 | E72: 1 | F72: 1 | G72: 1 | H72: 1
B73: Counter Measures | D73: 1 | E73: 1 | F73: 1 | G73: 1 | H73: 1
B74: Customer Significance | D74: 1 | E74: 1
B75: Status Report | D75: 1 | E75: 1
B76: Restoration Request | D76: 1 | E76: 1
B77: Contract Commitment Data | C77: 1 | F77: 1
B78: Send Detailed Problem Report to Service Management | C78: 1 | D78: 1 | E78: 1 | F78: 1 | G78: 1
B79: Send Status Report to Service Management | C79: 1 | D79: 1 | E79: 1 | F79: 1 | G79: 1 | H79: 1
B80: Send Restoration Request to Resource Provisioning | C80: 1 | D80: 1 | E80: 1 | F80: 1 | G80: 1 | H80: 1
B81: Identify Problem Parameters | C81: 1 | D81: 1 | E81: 1 | F81: 1 | G81: 1 | H81: 1
B82: Re-prioritize Counter Measures | C82: 1 | D82: 1 | E82: 1 | F82: 1 | G82: 1 | H82: 1
B83: Receive Problem Resolution Report from Service Management | D83: 1 | F83: 1
B84: Send Detailed Problem Report to Resource Provisioning | D84: 1 | E84: 1 | F84: 1 | G84: 1 | H84: 1
B85: Send Trouble-Shooting Report to Service Management | D85: 1 | E85: 1 | F85: 1 | G85: 1 | H85: 1
B86: Send Status Report to Customer Service | D86: 1
B87: Send Final Status Report to Customer Service | E87: 1
B88: Restoration Request or Timeout? | F88: 1 | G88: 1 | H88: 1
B89: Receive SLA Violation | F89: 1 | G89: 1 | H89: 1

Sheet c16
A1: Semantic Percision | C1: =SUM(C3:C4) / (C3+ C4+ C7) * 100 -> 96 | D1: =SUM(D3:D4) / (D3+ D4+ D7) * 100 -> 98.039216 | E1: =SUM(E3:E4) / (E3+ E4+ E7) * 100 -> 98 | F1: =SUM(F3:F4) / (F3+ F4+ F7) * 100 -> 97.87234 | G1: =SUM(G3:G4) / (G3+ G4+ G7) * 100 -> 100 | H1: =SUM(H3:H4) / (H3+ H4+ H7) * 100 -> 100 | J1: Jaccard Strict | K1: Chatbot run 1 | L1: Chatbot run 2 | M1: Chatbot run 3 | N1: XML run 1 | O1: XML run 2 | P1: XML run 3 | Q1: Jaccard Loose | R1: Chatbot run 1 | S1: Chatbot run 2 | T1: Chatbot run 3 | U1: XML run 1 | V1: XML run 2 | W1: XML run 3
A2: Semantic Recall | C2: =SUM(C3:C4) / SUM(C3:C5) *100 -> 88.888889 | D2: =SUM(D3:D4) / SUM(D3:D5) *100 -> 92.592593 | E2: =SUM(E3:E4) / SUM(E3:E5) *100 -> 92.45283 | F2: =SUM(F3:F4) / SUM(F3:F5) *100 -> 85.185185 | G2: =SUM(G3:G4) / SUM(G3:G5) *100 -> 81.481481 | H2: =SUM(H3:H4) / SUM(H3:H5) *100 -> 84.90566 | J2: Chatbot run 1 | Q2: Chatbot run 1
A3: Semantic TP Explicit | C3: =COUNTIF(C10:C63, 2) -> 48 | D3: =COUNTIF(D10:D63, 2) -> 46 | E3: =COUNTIF(E10:E63, 2) -> 49 | F3: =COUNTIF(F10:F63, 2) -> 39 | G3: =COUNTIF(G10:G63, 2) -> 38 | H3: =COUNTIF(H10:H63, 2) -> 44 | J3: Chatbot run 2 | K3: {=IFERROR(SUMPRODUCT((C10:C112<>"")*(D10:D112<>"")*(C10:C112=D10:D112))/SUMPRODUCT(--((C10:C112<>"")+(D10:D112<>"")>0)),"")} -> 0.75903614 | Q3: Chatbot run 2 | R3: {=IFERROR( SUMPRODUCT((C10:C112<>"")*(D10:D112<>"")* ((C10:C112=D10:D112)+((C10:C112=1)*(D10:D112=2))+((C10:C112=2)*(D10:D112=1)))) / SUMPRODUCT(--((C10:C112<>"")+(D10:D112<>"")>0)), "")} -> 0.79518072
A4: Semantic TP Implicit | C4: =COUNTIF(C10:C63, 1) -> 0 | D4: =COUNTIF(D10:D63, 1) -> 4 | E4: =COUNTIF(E10:E63, 1) -> 0 | F4: =COUNTIF(F10:F63, 1) -> 7 | G4: =COUNTIF(G10:G63, 1) -> 6 | H4: =COUNTIF(H10:H63, 1) -> 1 | J4: Chatbot run 3 | K4: {=IFERROR(SUMPRODUCT((C10:C112<>"")*(E10:E112<>"")*(C10:C112=E10:E112))/SUMPRODUCT(--((C10:C112<>"")+(E10:E112<>"")>0)),"")} -> 0.8125 | L4: {=IFERROR(SUMPRODUCT((E10:E112<>"")*(D10:D112<>"")*(E10:E112=D10:D112))/SUMPRODUCT(--((E10:E112<>"")+(D10:D112<>"")>0)),"")} -> 0.75308642 | Q4: Chatbot run 3 | R4: {=IFERROR( SUMPRODUCT((C10:C112<>"")*(E10:E112<>"")* ((C10:C112=E10:E112)+((C10:C112=1)*(E10:E112=2))+((C10:C112=2)*(E10:E112=1)))) / SUMPRODUCT(--((C10:C112<>"")+(E10:E112<>"")>0)), "")} -> 0.8125 | S4: {=IFERROR( SUMPRODUCT((E10:E112<>"")*(D10:D112<>"")* ((E10:E112=D10:D112)+((E10:E112=1)*(D10:D112=2))+((E10:E112=2)*(D10:D112=1)))) / SUMPRODUCT(--((E10:E112<>"")+(D10:D112<>"")>0)), "")} -> 0.80246914
A5: Semantic FN | C5: =COUNTIF(C10:C63, 0) -> 6 | D5: =COUNTIF(D10:D63, 0) -> 4 | E5: =COUNTIF(E10:E63, 0) -> 4 | F5: =COUNTIF(F10:F63, 0) -> 8 | G5: =COUNTIF(G10:G63, 0) -> 10 | H5: =COUNTIF(H10:H63, 0) -> 8 | J5: XML run 1 | K5: {=IFERROR(SUMPRODUCT((C10:C112<>"")*(F10:F112<>"")*(C10:C112=F10:F112))/SUMPRODUCT(--((C10:C112<>"")+(F10:F112<>"")>0)),"")} -> 0.62337662 | L5: {=IFERROR(SUMPRODUCT((F10:F112<>"")*(D10:D112<>"")*(F10:F112=D10:D112))/SUMPRODUCT(--((F10:F112<>"")+(D10:D112<>"")>0)),"")} -> 0.5443038 | M5: {=IFERROR(SUMPRODUCT((F10:F112<>"")*(E10:E112<>"")*(F10:F112=E10:E112))/SUMPRODUCT(--((F10:F112<>"")+(E10:E112<>"")>0)),"")} -> 0.62162162 | Q5: XML run 1 | R5: {=IFERROR( SUMPRODUCT((C10:C112<>"")*(F10:F112<>"")* ((C10:C112=F10:F112)+((C10:C112=1)*(F10:F112=2))+((C10:C112=2)*(F10:F112=1)))) / SUMPRODUCT(--((C10:C112<>"")+(F10:F112<>"")>0)), "")} -> 0.7012987 | S5: {=IFERROR( SUMPRODUCT((F10:F112<>"")*(D10:D112<>"")* ((F10:F112=D10:D112)+((F10:F112=1)*(D10:D112=2))+((F10:F112=2)*(D10:D112=1)))) / SUMPRODUCT(--((F10:F112<>"")+(D10:D112<>"")>0)), "")} -> 0.64556962 | T5: {=IFERROR( SUMPRODUCT((F10:F112<>"")*(E10:E112<>"")* ((F10:F112=E10:E112)+((F10:F112=1)*(E10:E112=2))+((F10:F112=2)*(E10:E112=1)))) / SUMPRODUCT(--((F10:F112<>"")+(E10:E112<>"")>0)), "")} -> 0.7027027
A6: Semantic FP Strict | C6: =COUNTIF(C65:C128,0) + COUNTIF(C65:C128,1) -> 22 | D6: =COUNTIF(D65:D128,0) + COUNTIF(D65:D128,1) -> 23 | E6: =COUNTIF(E65:E128,0) + COUNTIF(E65:E128,1) -> 18 | F6: =COUNTIF(F65:F128,0) + COUNTIF(F65:F128,1) -> 7 | G6: =COUNTIF(G65:G128,0) + COUNTIF(G65:G128,1) -> 6 | H6: =COUNTIF(H65:H128,0) + COUNTIF(H65:H128,1) -> 10 | J6: XML run 2 | K6: {=IFERROR(SUMPRODUCT((C10:C112<>"")*(G10:G112<>"")*(C10:C112=G10:G112))/SUMPRODUCT(--((C10:C112<>"")+(G10:G112<>"")>0)),"")} -> 0.63157895 | L6: {=SUMPRODUCT((D10:D112<>0)*(G10:G112<>0)) / SUMPRODUCT(((D10:D112<>0)+(G10:G112<>0)>0)*1)} -> 0.64864865 | M6: {=IFERROR(SUMPRODUCT((G10:G112<>"")*(E10:E112<>"")*(G10:G112=E10:E112))/SUMPRODUCT(--((G10:G112<>"")+(E10:E112<>"")>0)),"")} -> 0.64383562 | N6: {=IFERROR(SUMPRODUCT((G10:G112<>"")*(F10:F112<>"")*(G10:G112=F10:F112))/SUMPRODUCT(--((G10:G112<>"")+(F10:F112<>"")>0)),"")} -> 0.79032258 | Q6: XML run 2 | R6: {=IFERROR( SUMPRODUCT((C10:C112<>"")*(G10:G112<>"")* ((C10:C112=G10:G112)+((C10:C112=1)*(G10:G112=2))+((C10:C112=2)*(G10:G112=1)))) / SUMPRODUCT(--((C10:C112<>"")+(G10:G112<>"")>0)), "")} -> 0.71052632 | S6: {=IFERROR( SUMPRODUCT((D10:D112<>"")*(G10:G112<>"")* ((D10:D112=G10:G112)+((D10:D112=1)*(G10:G112=2))+((D10:D112=2)*(G10:G112=1)))) / SUMPRODUCT(--((D10:D112<>"")+(G10:G112<>"")>0)), "")} -> 0.65384615 | T6: {=IFERROR( SUMPRODUCT((G10:G112<>"")*(E10:E112<>"")* ((G10:G112=E10:E112)+((G10:G112=1)*(E10:E112=2))+((G10:G112=2)*(E10:E112=1)))) / SUMPRODUCT(--((G10:G112<>"")+(E10:E112<>"")>0)), "")} -> 0.71232877 | U6: {=IFERROR( SUMPRODUCT((F10:F112<>"")*(G10:G112<>"")* ((F10:F112=G10:G112)+((F10:F112=1)*(G10:G112=2))+((F10:F112=2)*(G10:G112=1)))) / SUMPRODUCT(--((F10:F112<>"")+(G10:G112<>"")>0)), "")} -> 0.88709677
A7: Semantic FP Loose | C7: =COUNTIF(C65:C128,0) -> 2 | D7: =COUNTIF(D65:D128,0) -> 1 | E7: =COUNTIF(E65:E128,0) -> 1 | F7: =COUNTIF(F65:F128,0) -> 1 | G7: =COUNTIF(G65:G128,0) -> 0 | H7: =COUNTIF(H65:H128,0) -> 0 | J7: XML run 3 | K7: {=IFERROR(SUMPRODUCT((C10:C112<>"")*(H10:H112<>"")*(C10:C112=H10:H112))/SUMPRODUCT(--((C10:C112<>"")+(H10:H112<>"")>0)),"")} -> 0.69230769 | L7: {=IFERROR(SUMPRODUCT((H10:H112<>"")*(D10:D112<>"")*(H10:H112=D10:D112))/SUMPRODUCT(--((H10:H112<>"")+(D10:D112<>"")>0)),"")} -> 0.6835443 | M7: {=IFERROR(SUMPRODUCT((H10:H112<>"")*(E10:E112<>"")*(H10:H112=E10:E112))/SUMPRODUCT(--((H10:H112<>"")+(E10:E112<>"")>0)),"")} -> 0.72 | N7: {=IFERROR(SUMPRODUCT((F10:F112<>"")*(H10:H112<>"")*(F10:F112=H10:H112))/SUMPRODUCT(--((F10:F112<>"")+(H10:H112<>"")>0)),"")} -> 0.68181818 | O7: {=IFERROR(SUMPRODUCT((G10:G112<>"")*(H10:H112<>"")*(G10:G112=H10:H112))/SUMPRODUCT(--((G10:G112<>"")+(H10:H112<>"")>0)),"")} -> 0.734375 | Q7: XML run 3 | R7: {=IFERROR( SUMPRODUCT((C10:C112<>"")*(H10:H112<>"")* ((C10:C112=H10:H112)+((C10:C112=1)*(H10:H112=2))+((C10:C112=2)*(H10:H112=1)))) / SUMPRODUCT(--((C10:C112<>"")+(H10:H112<>"")>0)), "")} -> 0.70512821 | S7: {=IFERROR( SUMPRODUCT((H10:H112<>"")*(D10:D112<>"")* ((H10:H112=D10:D112)+((H10:H112=1)*(D10:D112=2))+((H10:H112=2)*(D10:D112=1)))) / SUMPRODUCT(--((H10:H112<>"")+(D10:D112<>"")>0)), "")} -> 0.69620253 | T7: {=IFERROR( SUMPRODUCT((H10:H112<>"")*(E10:E112<>"")* ((H10:H112=E10:E112)+((H10:H112=1)*(E10:E112=2))+((H10:H112=2)*(E10:E112=1)))) / SUMPRODUCT(--((H10:H112<>"")+(E10:E112<>"")>0)), "")} -> 0.73333333 | U7: {=IFERROR( SUMPRODUCT((F10:F112<>"")*(H10:H112<>"")* ((F10:F112=H10:H112)+((F10:F112=1)*(H10:H112=2))+((F10:F112=2)*(H10:H112=1)))) / SUMPRODUCT(--((F10:F112<>"")+(H10:H112<>"")>0)), "")} -> 0.78787879 | V7: {=IFERROR( SUMPRODUCT((H10:H112<>"")*(G10:G112<>"")* ((H10:H112=G10:G112)+((H10:H112=1)*(G10:G112=2))+((H10:H112=2)*(G10:G112=1)))) / SUMPRODUCT(--((H10:H112<>"")+(G10:G112<>"")>0)), "")} -> 0.828125
C9: Chatbot run 1 | D9: Chatbot run 2 | E9: Chatbot run 3 | F9: XML run 1 | G9: XML run 2 | H9: XML run 3
A10: Pools / Lanes | B10: Customer | C10: 2 | D10: 2 | E10: 2 | F10: 2 | G10: 2 | H10: 2
B11: Company | C11: 2 | D11: 2 | E11: 2 | F11: 0 | G11: 0 | H11: 0
B12: Customer Service | C12: 2 | D12: 2 | E12: 2 | F12: 2 | G12: 2 | H12: 2
B13: customer information system | C13: 0 | D13: 0 | E13: 0 | F13: 0 | G13: 0 | H13: 0
B14: Grid Operator | C14: 2 | D14: 2 | E14: 2 | F14: 2 | G14: 2 | H14: 2
B15: Old Supplier | C15: 2 | D15: 2 | E15: 2 | F15: 2 | G15: 2 | H15: 2
A16: Tasks/Messages/Events | B16: Initiate Switch-over Request | C16: 2 | D16: 2 | E16: 2 | F16: 2 | G16: 2 | H16: 2
B17: Send Data to Customer Service | C17: 2 | D17: 2 | E17: 2 | F17: 2 | G17: 2 | H17: 2
B18: check the contract details | C18: 0 | D18: 0 | E18: 0 | F18: 2 | G18: 0 | H18: 0
B19: withdraw from the switch contract | C19: 2 | D19: 2 | E19: 2 | F19: 2 | G19: 1 | H19: 2
B20: confirm the switch contract | C20: 2 | D20: 2 | E20: 2 | F20: 2 | G20: 1 | H20: 2
B21: Enter Customer Data into CRM | C21: 2 | D21: 2 | E21: 2 | F21: 2 | G21: 2 | H21: 2
B22: Compare Data with Customer Database | C22: 2 | D22: 2 | E22: 2 | F22: 2 | G22: 2 | H22: 2
B23: Check Data for Completeness and Plausibility | C23: 2 | D23: 1 | E23: 2 | F23: 0 | G23: 0 | H23: 1
B24: Correct Errors using Error List | C24: 2 | D24: 2 | E24: 2 | F24: 2 | G24: 0 | H24: 2
B25: Create New Customer Object | C25: 2 | D25: 2 | E25: 2 | F25: 2 | G25: 2 | H25: 2
B26: Prepare Contract Documents for Switch-over | C26: 2 | D26: 2 | E26: 2 | F26: 2 | G26: 2 | H26: 2
B27: Automated Check of Contract Documents in CIS | C27: 2 | D27: 2 | E27: 2 | F27: 2 | G27: 2 | H27: 2
B28: Analyze and Resolve Issues | C28: 2 | D28: 2 | E28: 2 | F28: 2 | G28: 2 | H28: 2
... B30: Send Confirmation Document to Customer | C30: 2 | D30: 2 | E30: 2 | F30: 2 | G30: 2 | H30: 2
B31: Send Request to Grid Operator | C31: 2 | D31: 2 | E31: 2 | F31: 2 | G31: 2
B32: Create CIS Contract | C32: 2 | D32: 2 | E32: 2 | F32: 2 | G32: 2 | H32: 2
B33: Receive Withdrawal Notice from Customer | C33: 2 | D33: 2 | E33: 2 | F33: 2 | G33: 2 | H33: 2
B34: Receive Contract Confirmation from Customer | C34: 2 | D34: 2 | E34: 2 | F34: 2 | G34: 2 | H34: 2
B35: Wait for 7 days (Auto-accept) | C35: 2 | D35: 2 | E35: 2 | F35: 2 | G35: 2 | H35: 2
B36: Regard Contract as Accepted | C36: 0 | D36: 2 | E36: 0 | F36: 0 | G36: 0 | H36: 0
B37: Import Meter Data to Systems | C37: 2 | D37: 2 | E37: 2 | F37: 2 | G37: 2 | H37: 2
B38: Check Supplier Concurrence | C38: 2 | D38: 2 | E38: 2 | F38: 2 | G38: 2 | H38: 2
B39: Transmit Response Comment | C39: 2 | D39: 2 | E39: 2 | F39: 2 | G39: 2 | H39: 2
B40: Inform Suppliers and Demand Conflict Resolution | C40: 2 | D40: 2 | E40: 2 | F40: 2 | G40: 2 | H40: 2
B41: Terminate Sales Agreement with Old Supplier | C41: 2 | D41: 0 | E41: 2 | F41: 2 | G41: 2 | H41: 2
B42: Send Meter Data to Company | C42: 2 | D42: 2 | E42: 2 | F42: 2 | G42: 2 | H42: 2
B43: Send Meter Data to Old Supplier | C43: 2 | D43: 2 | E43: 2 | F43: 2 | G43: 2 | H43: 2
... B48: Send Final Bill to Customer: Old Supplier | C48: 2 | D48: 2 | E48: 2 | F48: 2 | G48: 2 | H48: 2
A49: Conditions/Loops/Parallel | B49: Customer Exists? | C49: 2 | D49: 1 | E49: 2 | F49: 2 | G49: 2 | H49: 0
B50: Errors? | C50: 2 | D50: 1 | E50: 2 | F50: 0 | G50: 0 | H50: 0
B51: Contract Documents Correct? | C51: 2 | D51: 2 | E51: 2 | F51: 2 | G51: 2 | H51: 2
B52: Supplier Concurrence? | C52: 2 | D52: 2 | E52: 2 | F52: 2 | G52: 2 | H52: 2
B53: confrim or withdraw | C53: 2 | D53: 2 | E53: 2 | F53: 2 | G53: 1 | H53: 2
B54: Event-based confrim or withdraw | C54: 2 | D54: 2 | E54: 2 | F54: 2 | G54: 2 | H54: 0
B55: At the same time || | C55: 0 | D55: 0 | E55: 0 | F55: 0 | G55: 0 | H55: 0
A56: Data Objects/ Messages | B56: Customer Data | C56: 2 | D56: 2 | E56: 2 | F56: 1 | G56: 2 | H56: 2
B57: Customer Database | C57: 2 | D57: 2 | E57: 2 | F57: 1 | G57: 2 | H57: 2
B58: Contract Documents | C58: 2 | D58: 2 | E58: 2 | F58: 1 | G58: 2 | H58: 2
B59: Meter Data | C59: 2 | D59: 2 | F59: 1 | G59: 1 | H59: 2
B60: Final Bill | C60: 2 | D60: 2 | E60: 2 | F60: 1 | G60: 1 | H60: 2
B61: services consumption report | C61: 0 | D61: 2 | E61: 2 | F61: 1 | G61: 0 | H61: 2
B62: CRM System | C62: 2 | D62: 2 | E62: 2 | F62: 0 | G62: 0 | H62: 2
B63: Confirmation Document/Contract Details | C63: 2 | D63: 2 | E63: 2 | F63: 1 | G63: 1 | H63: 2
B65: Sales | C65: 1 | D65: 1 | E65: 1
B66: Distribution | C66: 1 | D66: 1 | E66: 1
B67: Billing | C67: 0
B68: Switch-over Request | C68: 1 | D68: 1 | E68: 1
B69: Contract Confirmation | C69: 1 | E69: 1
B70: Withdrawal Notice | C70: 1 | D70: 1 | E70: 1
B71: Error List | C71: 1 | D71: 1 | H71: 1
B72: CIS System | C72: 1 | D72: 1
B73: Response Comment | C73: 1
B74: Conflict Resolution | D74: 1
B75: Prepare Switch-over Request and Data | C75: 1 | E75: 1 | F75: 1 | G75: 1 | H75: 1
B76: Receive Confirmation Document/ Receive Contract Details | C76: 1 | D76: 1 | E76: 1 | G76: 1 | H76: 1
B77: Prepare Contract Confirmation (optional) | C77: 1 | D77: 1 | E77: 1
B78: Prepare Withdrawal Notice | C78: 1 | D78: 1 | E78: 1
B79: Wait for 7 days (if no confirmation) | C79: 0
B80: Receive Final Bill from Old Supplier | C80: 1 | D80: 1 | E80: 1 | H80: 1
B81: Receive Meter Data/Service Consumption Report from Grid Operator | C81: 1 | D81: 1 | E81: 1 | F81: 1 | G81: 1 | H81: 1
B82: Receive Switch-over Request and Data from Customer | C82: 1 | D82: 1 | E82: 1 | F82: 1
B83: Generate Confirmation Document | C83: 1
B84: Receive Grid Operator Response | C84: 1 | D84: 1 | E84: 1 | F84: 1 | G84: 1 | H84: 1
B85: Receive Conflict Resolution from Grid Operator | C85: 1 | D85: 1
B86: Receive Switch-over Request from New Supplier | C86: 1 | D86: 1 | F86: 1 | G86: 1 | H86: 1
B87: Receive Final Billing from Grid Operator | C87: 1 | D87: 1 | E87: 1 | F87: 1 | G87: 1 | H87: 1
B88: Customer Object | D88: 1 | E88: 1 | H88: 1
B89: Re-Check Data | D89: 0
B90: Prepare Meter Data and Service Consumption Report | D90: 1
B91: Grid Operator Response | D91: 1 | E91: 1
B92: Send Conflict Resolution to Company | D92: 1
B93: Prepare Grid Operator Response | D93: 1
B94: Wait for Grid Operator to Resolve Conflict | E94: 1
B95: Send Service Consumption Report to Customer | E95: 0
B96: Wait for Consumption Report | F96: 0
B97: Demand Conflict Resolution | H97: 1
